Workbook

Sheet WH Stock Mastersheet
B1: Material Receipt Details | N1: =SUBTOTAL(9,N3:N1048576) -> 173694 | O1: =SUBTOTAL(9,O3:O1048576) -> 13208 | P1: =SUBTOTAL(9,P3:P1048576) -> 24149 | Q1: =+N1-P1 -> 149545
A2: Project Name | B2: Sr. No. | C2: Date of receipt | D2: Material Receipt From | E2: Warehouse Doc. No & Vendor Document No. | F2: Warehouse Documents Date / Vendor Doc. Date | G2: LR No/ Date | H2: Vendor Place | I2: P.O. No. | J2: SAP Code | K2: Part Code | L2: Description | M2: UOM | N2: Received Qty | O2: Qty. Verified | P2: Dispatched Qty | Q2: Balance Qty | R2: VNS Item Location | S2: Box No / Bin No | T2: Customer Invoice / Challan No | U2: Date | V2: Dispatch Date | W2: Customer Name | X2: Location | Y2: Order By | Z2: Docket No | AA2: Transporter / Courier Name | AB2: Project | AC2: Customer P.O. No | AD2: WBS | AE2: Remark if Any
B3: 1 | C3: 44637 | D3: Delhi Sahabad Warehouse | E3: SMO/0002 | F3: 44634 | H3: DELHI | J3: 109687772 | K3: 109687772 | L3: DISPLAY (FRAM )MOUNTING BRACKET | M3: Nos | N3: 20 | Q3: =+N3-P3 -> 20 | R3: Near Gate No 3 | S3: W. Box No 34 (1 To 5)
B4: 2 | C4: 44637 | D4: Delhi Sahabad Warehouse | E4: SMO/0001 | F4: 44634 | H4: DELHI | K4: HN350 ( DH350/HK351N)6 | L4: BATTERY CHARGER ASSEMBLY DRG NO 4TRS-231 | M4: Nos | N4: 8 | Q4: =+N4-P4 -> 8 | R4: Near Gate No 3 | S4: W. Box No 35
B5: 3 | C5: 44643 | D5: Delhi Sahabad Warehouse SHUBHADA POLYMERS PRODUCTS PVT LTD | E5: SMO/0004 SHS201001538 | F5: 17-03-2022 13-01-20 | G5: 359972307 GATIKWE | H5: MUMBAI | I5: 4509462642 | J5: 102316360 | K5: ECC1/ECC2 S3 | L5: CABLE PENETRATION 800A ECC1/ECC2 S3 | M5: Nos | N5: 24 | Q5: =+N5-P5 -> 24 | R5: Rack No 25 | S5: Box No 25 & 26
B6: 4 | C6: 44643 | D6: Delhi Sahabad Warehouse SHUBHADA POLYMERS PRODUCTS PVT LTD | E6: SMO/0004 SHS201001538 | F6: 17-03-2022 13-01-20 | G6: 359972307 GATIKWE | H6: MUMBAI | I6: 4509462642 | J6: A5E47174092 | K6: A5E436723831_AD | L6: CABLE PENETRATION 600-650A | M6: Nos | N6: 24 | Q6: =+N6-P6 -> 24 | R6: Rack No 29 | S6: Box No 27 & 28
A7: WAG9/6k | B7: 5 | C7: 44643 | D7: Delhi Sahabad Warehouse HARTING INDIA LTD. | E7: SMO/0004 3600059304 | F7: 17-03-2022 31-12-20 | G7: XPRESSBEES,91691183107 31-12-20 | H7: chennai | I7: 4509978514 | J7: 112136075 | K7: 09300240581 | L7: HARTING Hood Female HAN 24B-GS-ZV-29 '09300240581 | M7: Nos | N7: 54 | P7: 10 | Q7: =+N7-P7 -> 44 | R7: Rack No 6/D1 | S7: Box No 29 | T7: UP/DC/FY22/00065 | U7: 44707 | V7: 44707 | W7: SIEMENS LTD. G. HOUSE | X7: Paschim Burdwan WB | Y7: Mr. Arka Dey | Z7: 218110400 | AA7: SPOTON/DELHIVERY | AB7: WAG9/6k | AC7: 70201134101308 | AD7: 62OP 30878
A8: WAG9/6k | B8: 5 | D8: Delhi Sahabad Warehouse HARTING INDIA LTD. | J8: 112136075 | K8: 09300240581 | L8: HARTING Hood Female HAN 24B-GS-ZV-29 '09300240581 | M8: Nos | P8: 6 | Q8: =+Q7-P8 -> 38 | R8: Rack No 6/D1 | S8: Box No 29 | T8: UP/DC/FY22/00078 | U8: 44711 | V8: 44711 | W8: DDU Shed Mugal Sarai | X8: VARANASI | Y8: Mr. Arka Dey | Z8: BY HAND | AA8: Mr. Saurabh Mishra | AB8: WAG9/6k | AE8: Material for BLW Commissioning against 49x CLW
A9: WAG9/6k | B9: 5 | D9: Delhi Sahabad Warehouse HARTING INDIA LTD. | J9: 112136075 | K9: 09300240581 | L9: HARTING Hood Female HAN 24B-GS-ZV-29 '09300240581 | M9: Nos | P9: 4 | Q9: =+Q8-P9 -> 34 | R9: Rack No 6/D1 | S9: Box No 29 | T9: UP/DC/FY22/00079 | U9: 44712 | V9: 44712 | W9: SD II Stores Depot 2 PLW | X9: Patiala | Y9: Mr. Arka Dey | Z9: 215973860 | AA9: SPOTON/DELHIVERY | AB9: WAG9/6k | AC9: 20212095100413 | AD9: 62OP 30878
A10: WAG9/6k | B10: 5 | D10: Delhi Sahabad Warehouse HARTING INDIA LTD. | J10: 112136075 | K10: 09300240581 | L10: HARTING Hood Female HAN 24B-GS-ZV-29 '09300240581 | M10: Nos | P10: 6 | Q10: =+Q9-P10 -> 28 | R10: Rack No 6/D1 | S10: Box No 29 | T10: UP/DC/FY22/00090 | U10: 44714 | V10: 44714 | W10: SD II Stores Depot 2 PLW | X10: Patiala | Y10: Mr. Arka Dey | Z10: 216001993 | AA10: DELHIVERY LTD | AB10: WAG9/6k | AC10: 20212095100413 | AD10: 62OP 30878
A11: WAG9/6k | B11: 5 | D11: Delhi Sahabad Warehouse HARTING INDIA LTD. | J11: 112136075 | K11: 09300240581 | L11: HARTING Hood Female HAN 24B-GS-ZV-29 '09300240581 | M11: Nos | P11: 4 | Q11: =+Q10-P11 -> 24 | R11: Rack No 6/D1 | S11: Box No 29 | T11: UP/DC/FY22/00089 | U11: 44714 | V11: 44714 | W11: SR DEE ELECTRIC LOCO SHED | X11: TUGHALAKABAD DELHI | Y11: Mr. Arka Dey | Z11: 216001992 | AA11: DELHIVERY LTD | AB11: WAG9/6k | AC11: 29215006D00977 | AD11: 62OP 30878
A12: WAG9/6k | B12: 5 | D12: Delhi Sahabad Warehouse HARTING INDIA LTD. | J12: 112136075 | K12: 09300240581 | L12: HARTING Hood Female HAN 24B-GS-ZV-29 '09300240581 | M12: Nos | P12: 4 | Q12: =+Q11-P12 -> 20 | R12: Rack No 6/D1 | S12: Box No 29 | T12: UP/DC/FY22/00128 | U12: 44734 | V12: 44734 | W12: CEE/D&D/CLW/CRJ | X12: CHITTARANJAN WB | Y12: MR. ARKA DEY | Z12: 215973560 | AA12: DELHIVERY LTD | AB12: WAG9/6k | AC12: 70201134101308 | AD12: 62OP 30878
B13: 6 | C13: 44643 | D13: Delhi Sahabad Warehouse WEIDMULLER ELECTRONIC INDIA PVT LTD | E13: SMO/0004 203001 | F13: 17-03-2022 25-11-19 | G13: 1004427023 26-11-19 Rivigo Service Pvt.Ltd. | H13: BENGALURU | I13: 4509411596 | J13: 109710324 | K13: WFF185/AH 600V 360 AMP | L13: FEED THROUGH TERMINAL BLOCK WFF 185/AH 1029600000 | M13: Nos | N13: 36 | Q13: =+N13-P13 -> 36 | R13: Rack No 2 /F1 & 2 | S13: Box No 30 & 31
B14: 7 | C14: 44643 | D14: Delhi Sahabad Warehouse TDK COMPONENTS PTE LTD | E14: SMO/0004 56738710 | F14: 17-03-2022 24-12-21 | G14: MANJEET TRANSPORT / 10923 | H14: SINGAPORE | I14: 4200899863 | J14: 109443666 | K14: B32373A4257J 80 | L14: MET FILM CAPACITOR RoHS COMPATIBLE 250uF +-5% 480V PEC MKD AC | M14: Nos | N14: 19 | Q14: =+N14-P14 -> 19 | R14: Rack No 6/E | S14: Box No 24
B15: 8 | C15: 44643 | D15: Delhi Sahabad Warehouse Span HI tech Pvt. Ltd. | E15: SMO/0004 337 | F15: 17-03-2022 03-02-21 | G15: 123315152 03-02-21 GATI KWE | H15: NASIK | I15: 4510318862 | J15: 110320774 | K15: 1902MA1001_A | L15: HEP CUBICLE FOR WAP7 DRG NO 1902MA1001_A (GASKET) | M15: MTR | N15: 94 | Q15: =+N15-P15 -> 94 | R15: Rack No 6/C | S15: Box 18
B16: 9 | C16: 44643 | D16: Delhi Sahabad Warehouse | E16: SMO/0015 | F16: 44646 | H16: DELHI | J16: 107983770 | K16: 7210N-181 | L16: INSTRUMENT COOLING FAN. 7210N-181 /Churning Fan | M16: Nos | N16: 25 | Q16: =+N16-P16 -> 25 | R16: Rack No 27 | S16: Box No 19,20,21
B17: 10 | C17: 44643 | D17: Delhi Sahabad Warehouse SIEMENS AG | E17: SM0/0003 7411RF3800333725 | F17: 16-03-2022 10-12-20 | G17: MANJEET TRANSPORT / 8359, 04-03-21 | H17: GERMANY | I17: 4200791659 | J17: 101999218 | K17: XL KF i (A2B00075622) | L17: SITET® XL KF i (A2B00075622) | M17: Nos | N17: 36 | P17: 2 | Q17: =+N17-P17 -> 34 | R17: Rack No 6/A,B,C | S17: Box No 32 (32/1 to 32/36) | T17: UP/DC/FY22/00064 | U17: 44706 | V17: 44706 | W17: SR DEE ELECTRIC LOCO SHED | X17: TUGHALAKABAD DELHI | Y17: Mr. Arka Dey | Z17: 218110392 | AA17: SPOTON LOGISTIC Pvt. Ltd. | AB17: 9000HP Locomotive | AE17: Mitigate loco failure
B18: 10 | D18: Delhi Sahabad Warehouse SIEMENS AG | J18: 101999218 | K18: XL KF i (A2B00075622) | L18: SITET® XL KF i (A2B00075622) | M18: Nos | P18: 30 | Q18: =+Q17-P18 -> 4 | R18: Rack No 6/A,B,C | S18: Box No 32 (32/1 to 32/36) | T18: UP/DC/FY22/00076 | U18: 44711 | V18: 44712 | W18: Siemens Ltd- Nasik Work | X18: NASIK | Y18: Mr. Arka Dey | Z18: 215973859 | AA18: SPOTON LOGISTIC Pvt. Ltd. | AE18: Item sent for inspection
B19: 10 | D19: Delhi Sahabad Warehouse SIEMENS AG | J19: 101999218 | K19: XL KF i (A2B00075622) | L19: SITET® XL KF i (A2B00075622) | M19: Nos | P19: 4 | Q19: =+Q18-P19 -> 0 | R19: Rack No 6/A,B,C | S19: Box No 32 (32/1 to 32/36) | T19: UP/DC/FY22/00079 | U19: 44712 | V19: 44712 | W19: SD II Stores Depot 2 PLW | X19: Patiala | Y19: Mr. Arka Dey | Z19: 215973860 | AA19: SPOTON LOGISTIC Pvt. Ltd. | AB19: WAG9/6k | AC19: 20212095100413 | AD19: 62OP 30878
B20: 11 | C20: 44645 | D20: Delhi Sahabad Warehouse Norish Automation GMBH | E20: SM0/0007 2022116 | F20: 19-03-2022 13-02-20 | G20: MANJEET TRANSPORT/ 5799 26-02-20 | H20: GERMANY | I20: 4200754583 | J20: 107123964 | K20: FAHZ5-P3-024/028/007 | L20: SPEED SENSOR NORIS | M20: Nos | N20: =93+47+8+32+8+42 -> 230 | P20: 70 | Q20: =+N20-P20 -> 160 | R20: Rack No 31,32,35,36 | S20: Box No 13,9,11,10,12 | T20: UP/DC/FY22/00046 | U20: 44690 | V20: 44694 | W20: Siemens ltd Jodhpur Site | X20: Bhagat Ki kothi Jodhpur | Y20: Mr. Arka Dey | Z20: 223951853 | AA20: Spoton | AB20: DE loco AMC | AC20: NA | AD20: 62OP-30781.P.02 | AE20: Faulty Batch Replacement from Noris And Transport and Packaging Debits to the CS
B21: 12 | C21: 44645 | D21: Delhi Sahabad Warehouse | E21: SM0/0007 | F21: 44639 | J21: 107123967 | K21: GT46MAC-T | L21: TEMP. SENSOR GT46MAC-T | M21: Nos | N21: 38 | Q21: =+N21-P21 -> 38 | R21: Rack No 31 | S21: Box No 13 & 14
B22: 13 | C22: 44645 | D22: Delhi Sahabad Warehouse | E22: SM0/0007 | F22: 44639 | J22: 101668554 | K22: A5E00747920 | L22: MAIN BOARD 6FH9543-3BY60 A5E00747920 | M22: Nos | N22: 3 | Q22: =+N22-P22 -> 3 | R22: Rack No 31 | S22: Box No 14
A23: WAG9/6k | B23: 14 | C23: 44645 | D23: Delhi Sahabad Warehouse HARTING INDIA LTD. | E23: SMO/0008 3600076242 | F23: 21-03-2022 28-02-2022 | G23: 4532/ 10-03-2022 Paul Service | H23: chennai | I23: 4511059519 | J23: 109492181 | K23: 09670003476 | L23: HARTING D SUB -S- FEMALE-18-22 CRIMP CONDUCT P.N. 09670003476 | M23: Nos | N23: 1000 | P23: 460 | Q23: =+N23-P23 -> 540 | R23: Rack No 2/ D2 | S23: Box No 15 | T23: UP/DC/FY22/00022 | U23: 44672 | V23: 44674 | W23: TEKNOCRATS CONTROL PVT. LTD. | X23: NASIK | Y23: Mr. Arka Dey | Z23: 50815918834 | AA23: BLUE DART SARFACE | AB23: WAG9/6k | AC23: 70201134101308 | AD23: 62OP 30878 | AE23: Short supply material dispatched now
A24: WAG9/6k | B24: 14 | D24: Delhi Sahabad Warehouse HARTING INDIA LTD. | J24: 109492181 | K24: 09670003476 | L24: HARTING D SUB -S- FEMALE-18-22 CRIMP CONDUCT P.N. 09670003476 | M24: Nos | P24: 50 | Q24: =+Q23-P24 -> 490 | R24: Rack No 2/ D2 | S24: Box No 15 | T24: UP/DC/FY22/00040 | U24: 44685 | V24: 44685 | W24: Siemens / Guest house | X24: Paschim Burdwan WB | Y24: Mr. Arka Dey | Z24: BY HAND | AA24: Mr. Saurabh Mishra | AB24: 6000HP: CLW PO 6k49x | AC24: 70201134101308 | AD24: 62OP 30878 | AE24: Short supply material dispatched now
A25: WAG9/6k | B25: 14 | D25: Delhi Sahabad Warehouse HARTING INDIA LTD. | J25: 109492181 | K25: 09670003476 | L25: HARTING D SUB -S- FEMALE-18-22 CRIMP CONDUCT P.N. 09670003476 | M25: Nos | P25: 160 | Q25: =+Q24-P25 -> 330 | R25: Rack No 2/ D2 | S25: Box No 15 | T25: UP/DC/FY22/00065 | U25: 44707 | V25: 44707 | W25: SIEMENS LTD. G. HOUSE | X25: Paschim Burdwan WB | Y25: Mr. Arka Dey | Z25: 218110400 | AA25: SPOTON/DELHIVERY | AB25: WAG9/6k | AC25: 70201134101308 | AD25: 62OP 30878
A26: WAG9/6k | B26: 14 | D26: Delhi Sahabad Warehouse HARTING INDIA LTD. | J26: 109492181 | K26: 09670003476 | L26: HARTING D SUB -S- FEMALE-18-22 CRIMP CONDUCT P.N. 09670003476 | M26: Nos | P26: 64 | Q26: =+Q25-P26 -> 266 | R26: Rack No 2/ D2 | S26: Box No 15 | T26: UP/DC/FY22/00079 | U26: 44712 | V26: 44712 | W26: SD II Stores Depot 2 PLW | X26: Patiala | Y26: Mr. Arka Dey | Z26: 215973860 | AA26: SPOTON/DELHIVERY | AB26: WAG9/6k | AC26: 20212095100413 | AD26: 62OP 30878
A27: WAG9/6k | B27: 14 | D27: Delhi Sahabad Warehouse HARTING INDIA LTD. | J27: 109492181 | K27: 09670003476 | L27: HARTING D SUB -S- FEMALE-18-22 CRIMP CONDUCT P.N. 09670003476 | M27: Nos | P27: 96 | Q27: =+Q26-P27 -> 170 | R27: Rack No 2/ D2 | S27: Box No 15 | T27: UP/DC/FY22/00090 | U27: 44714 | V27: 44714 | W27: SD II Stores Depot 2 PLW | X27: Patiala | Y27: Mr. Arka Dey | Z27: 216001993 | AA27: DELHIVERY LTD | AB27: WAG9/6k | AC27: 20212095100413 | AD27: 62OP 30878
A28: WAG9/6k | B28: 14 | D28: Delhi Sahabad Warehouse HARTING INDIA LTD. | J28: 109492181 | K28: 09670003476 | L28: HARTING D SUB -S- FEMALE-18-22 CRIMP CONDUCT P.N. 09670003476 | M28: Nos | P28: 64 | Q28: =+Q27-P28 -> 106 | R28: Rack No 2/ D2 | S28: Box No 15 | T28: UP/DC/FY22/00089 | U28: 44714 | V28: 44714 | W28: SR DEE ELECTRIC LOCO SHED | X28: TUGHALAKABAD DELHI | Y28: Mr. Arka Dey | Z28: 216001992 | AA28: DELHIVERY LTD | AB28: WAG9/6k | AC28: 29215006D00977 | AD28: 62OP 30878
A29: WAG9/6k | B29: 14 | D29: Delhi Sahabad Warehouse HARTING INDIA LTD. | J29: 109492181 | K29: 09670003476 | L29: HARTING D SUB -S- FEMALE-18-22 CRIMP CONDUCT P.N. 09670003476 | M29: Nos | P29: 64 | Q29: =+Q28-P29 -> 42 | R29: Rack No 2/ D2 | S29: Box No 15 | T29: UP/DC/FY22/00128 | U29: 44734 | V29: 44734 | W29: CEE/D&D/CLW/CRJ | X29: CHITTARANJAN WB | Y29: MR. ARKA DEY | Z29: 215973560 | AA29: DELHIVERY LTD | AB29: WAG9/6k | AC29: 70201134101308 | AD29: 62OP 30878
A30: WAG9/6k | B30: 15 | C30: 44645 | D30: Delhi Sahabad Warehouse HARTING INDIA LTD. | E30: SMO/0008 3600076242 | F30: 21-03-2022 28-02-2022 | G30: 4532/PAUL SERVICE | H30: CHENNAI | I30: 4511059519 | J30: 109609630 | K30: 09150006123 | L30: HARTING R15-STI-C (AU) 0.5-AWG20 09150006123 | M30: Nos | N30: 200 | P30: 48 | Q30: =+N30-P30 -> 152 | R30: Rack No 2 /D2 | S30: Box No 15 | T30: UP/DC/FY22/00040 | U30: 44685 | V30: 44685 | W30: Siemens / Guest house | X30: Paschim Burdwan WB | Y30: Mr. Arka Dey | Z30: BY HAND | AA30: Mr. Saurabh Mishra | AB30: 6000HP: CLW PO 6k49x | AC30: 70201134101308 | AD30: 62OP 30878 | AE30: Short supply material dispatched now
A31: WAG9/6k | B31: 15 | D31: Delhi Sahabad Warehouse HARTING INDIA LTD. | I31: 4511059519 | J31: 109609630 | K31: 09150006123 | L31: HARTING R15-STI-C (AU) 0.5-AWG20 09150006123 | M31: Nos | P31: 80 | Q31: =+Q30-P31 -> 72 | R31: Rack No 2 /D2 | S31: Box No 15 | T31: UP/DC/FY22/00065 | U31: 44707 | V31: 44707 | W31: SIEMENS LTD. G. HOUSE | X31: Paschim Burdwan WB | Y31: Mr. Arka Dey | Z31: 218110400 | AA31: SPOTON/DELHIVERY | AB31: WAG9/6k | AC31: 70201134101308 | AD31: 62OP 30878
A32: WAG9/6k | B32: 15 | D32: Delhi Sahabad Warehouse HARTING INDIA LTD. | J32: 109609630 | K32: 09150006123 | L32: HARTING R15-STI-C (AU) 0.5-AWG20 09150006123 | M32: Nos | P32: 48 | Q32: =+Q31-P32 -> 24 | R32: Rack No 2 /D2 | S32: Box No 15 | T32: UP/DC/FY22/00078 | U32: 44711 | V32: 44711 | W32: DDU Shed Mugal Sarai | X32: VARANASI | Y32: Mr. Arka Dey | Z32: BY HAND | AA32: Mr. Saurabh Mishra | AB32: WAG9/6k | AE32: Material for BLW Commissioning against 49x CLW
A33: WAG9/6k | B33: 15 | D33: Delhi Sahabad Warehouse HARTING INDIA LTD. | J33: 109609630 | K33: 09150006123 | L33: HARTING R15-STI-C (AU) 0.5-AWG20 09150006123 | M33: Nos | P33: 24 | Q33: =+Q32-P33 -> 0 | R33: Rack No 2 /D2 | S33: Box No 15 | T33: UP/DC/FY22/00079 | U33: 44712 | V33: 44712 | W33: SD II Stores Depot 2 PLW | X33: Patiala | Y33: Mr. Arka Dey | Z33: 215973860 | AA33: SPOTON/DELHIVERY | AB33: WAG9/6k | AC33: 20212095100413 | AD33: 62OP 30878
A34: WAG9/6k | B34: 16 | C34: 44645 | D34: Delhi Sahabad Warehouse HARTING INDIA LTD. | E34: SMO/0008 3600076242 | F34: 44641 | G34: 4532/PAUL SERVICE | H34: chennai | I34: 4511059519 | J34: 109492197 | K34: 61030000067 | L34: CRIMP FLANGE FOR D-SUB HARTING (S102117360) FORMVB CONNECTOR 61030000067 | M34: Nos | N34: 600 | P34: 80 | Q34: =+N34-P34 -> 520 | R34: Rack No 2 /D2 | S34: Box No 15 | T34: UP/DC/FY22/00065 | U34: 44707 | V34: 44707 | W34: SIEMENS LTD. G. HOUSE | X34: Paschim Burdwan WB | Y34: Mr. Arka Dey | Z34: 218110400 | AA34: SPOTON/DELHIVERY | AB34: WAG9/6k | AC34: 70201134101308 | AD34: 62OP 30878
A35: WAG9/6k | B35: 16 | D35: Delhi Sahabad Warehouse HARTING INDIA LTD. | J35: 109492197 | K35: 61030000067 | L35: CRIMP FLANGE FOR D-SUB HARTING (S102117360) FORMVB CONNECTOR 61030000067 | M35: Nos | P35: 14 | Q35: =+Q34-P35 -> 506 | R35: Rack No 2 /D2 | S35: Box No 15 | T35: UP/DC/FY22/00079 | U35: 44712 | V35: 44712 | W35: SD II Stores Depot 2 PLW | X35: Patiala | Y35: Mr. Arka Dey | Z35: 215973860 | AA35: SPOTON/DELHIVERY | AB35: WAG9/6k | AC35: 20212095100413 | AD35: 62OP 30878
A36: WAG9/6k | B36: 16 | D36: Delhi Sahabad Warehouse HARTING INDIA LTD. | J36: 109492197 | K36: 61030000067 | L36: CRIMP FLANGE FOR D-SUB HARTING (S102117360) FORMVB CONNECTOR 61030000067 | M36: Nos | P36: 48 | Q36: =+Q35-P36 -> 458 | R36: Rack No 2 /D2 | S36: Box No 15 | T36: UP/DC/FY22/00090 | U36: 44714 | V36: 44714 | W36: SD II Stores Depot 2 PLW | X36: Patiala | Y36: Mr. Arka Dey | Z36: 216001993 | AA36: DELHIVERY LTD | AB36: WAG9/6k | AC36: 20212095100413 | AD36: 62OP 30878
A37: WAG9/6k | B37: 16 | D37: Delhi Sahabad Warehouse HARTING INDIA LTD. | J37: 109492197 | K37: 61030000067 | L37: CRIMP FLANGE FOR D-SUB HARTING (S102117360) FORMVB CONNECTOR 61030000067 | M37: Nos | P37: 32 | Q37: =+Q36-P37 -> 426 | R37: Rack No 2 /D2 | S37: Box No 15 | T37: UP/DC/FY22/00089 | U37: 44714 | V37: 44714 | W37: SR DEE ELECTRIC LOCO SHED | X37: TUGHALAKABAD DELHI | Y37: Mr. Arka Dey | Z37: 216001992 | AA37: DELHIVERY LTD | AB37: WAG9/6k | AC37: 29215006D00977 | AD37: 62OP 30878
A38: WAG9/6k | B38: 16 | D38: Delhi Sahabad Warehouse HARTING INDIA LTD. | J38: 109492197 | K38: 61030000067 | L38: CRIMP FLANGE FOR D-SUB HARTING (S102117360) FORMVB CONNECTOR 61030000067 | M38: Nos | P38: 32 | Q38: =+Q37-P38 -> 394 | R38: Rack No 46 | S38: Box No 16 | T38: UP/DC/FY22/00128 | U38: 44734 | V38: 44734 | W38: CEE/D&D/CLW/CRJ | X38: CHITTARANJAN WB | Y38: MR. ARKA DEY | Z38: 215973560 | AA38: DELHIVERY LTD | AB38: WAG9/6k | AC38: 70201134101308 | AD38: 62OP 30878
A39: WAG9/6k | B39: 17 | C39: 44645 | D39: Delhi Sahabad Warehouse HARTING INDIA LTD. | E39: SMO/0008 3600076242 | F39: 21-03-2022 20-02-2022 | G39: 4532/10-03-22 Paul Service | H39: CHENNAI | I39: 4511059519 | J39: 109492194 | K39: 61030012010 | L39: HARTING INDU COM 9P 1T ENTRY HEX SCREW 4-40 P.N. 61030012010 | M39: Nos | N39: 470 | P39: 30 | Q39: =+N39-P39 -> 440 | R39: Rack 2/E1 & E2 | S39: Box No 16 & 17 | T39: UP/DC/FY22/00022 | U39: 44672 | V39: 44674 | W39: TEKNOCRATS CONTROL PVT. LTD. | X39: NASIK | Y39: Mr. Arka Dey | Z39: 50815918834 | AA39: BLUE DART SARFACE | AB39: WAG9/6k | AC39: 70201134101308 | AD39: 62OP 30878 | AE39: Short supply material dispatched now
A40: WAG9/6k | B40: 17 | D40: Delhi Sahabad Warehouse HARTING INDIA LTD. | J40: 109492194 | K40: 61030012010 | L40: HARTING INDU COM 9P 1T ENTRY HEX SCREW 4-40 P.N. 61030012010 | M40: Nos | P40: 80 | Q40: =+Q39-P40 -> 360 | R40: Rack 2/E1 & E2 | S40: Box No 16 & 17 | T40: UP/DC/FY22/00065 | U40: 44707 | V40: 44707 | W40: SIEMENS LTD. G. HOUSE | X40: Paschim Burdwan WB | Y40: Mr. Arka Dey | Z40: 218110400 | AA40: SPOTON/DELHIVERY | AB40: WAG9/6k | AC40: 70201134101308 | AD40: 62OP 30878
A41: WAG9/6k | B41: 17 | D41: Delhi Sahabad Warehouse HARTING INDIA LTD. | J41: 109492194 | K41: 61030012010 | L41: HARTING INDU COM 9P 1T ENTRY HEX SCREW 4-40 P.N. 61030012010 | M41: Nos | P41: 32 | Q41: =+Q40-P41 -> 328 | R41: Rack 2/E1 & E2 | S41: Box No 16 & 17 | T41: UP/DC/FY22/00079 | U41: 44712 | V41: 44712 | W41: SD II Stores Depot 2 PLW | X41: Patiala | Y41: Mr. Arka Dey | Z41: 215973860 | AA41: SPOTON/DELHIVERY | AB41: WAG9/6k | AC41: 20212095100413 | AD41: 62OP 30878
A42: WAG9/6k | B42: 17 | D42: Delhi Sahabad Warehouse HARTING INDIA LTD. | J42: 109492194 | K42: 61030012010 | L42: HARTING INDU COM 9P 1T ENTRY HEX SCREW 4-40 P.N. 61030012010 | M42: Nos | P42: 48 | Q42: =+Q41-P42 -> 280 | R42: Rack 2/E1 & E2 | S42: Box No 16 & 17 | T42: UP/DC/FY22/00090 | U42: 44714 | V42: 44714 | W42: SD II Stores Depot 2 PLW | X42: Patiala | Y42: Mr. Arka Dey | Z42: 216001993 | AA42: DELHIVERY LTD | AB42: WAG9/6k | AC42: 20212095100413 | AD42: 62OP 30878
A43: WAG9/6k | B43: 17 | D43: Delhi Sahabad Warehouse HARTING INDIA LTD. | J43: 109492194 | K43: 61030012010 | L43: HARTING INDU COM 9P 1T ENTRY HEX SCREW 4-40 P.N. 61030012010 | M43: Nos | P43: 32 | Q43: =+Q42-P43 -> 248 | R43: Rack 2/E1 & E2 | S43: Box No 16 & 17 | T43: UP/DC/FY22/00089 | U43: 44714 | V43: 44714 | W43: SR DEE ELECTRIC LOCO SHED | X43: TUGHALAKABAD DELHI | Y43: Mr. Arka Dey | Z43: 216001992 | AA43: DELHIVERY LTD | AB43: WAG9/6k | AC43: 29215006D00977 | AD43: 62OP 30878
A44: WAG9/6k | B44: 17 | D44: Delhi Sahabad Warehouse HARTING INDIA LTD. | J44: 109492194 | K44: 61030012010 | L44: HARTING INDU COM 9P 1T ENTRY HEX SCREW 4-40 P.N. 61030012010 | M44: Nos | P44: 32 | Q44: =+Q43-P44 -> 216 | R44: Rack No 46 | S44: Box No 16 | T44: UP/DC/FY22/00128 | U44: 44734 | V44: 44734 | W44: CEE/D&D/CLW/CRJ | X44: CHITTARANJAN WB | Y44: MR. ARKA DEY | Z44: 215973560 | AA44: DELHIVERY LTD | AB44: WAG9/6k | AC44: 70201134101308 | AD44: 62OP 30878
A45: WAG9/6k | B45: 18 | C45: 44645 | D45: Delhi Sahabad Warehouse HARTING INDIA LTD. | E45: SMO/0008 3600076242 | F45: 21-03-2022 28-02-2022 | G45: 4532/PAUL SERVICE | H45: CHENNAI | I45: 4511059519 | J45: 109609632 | K45: 09150043013 | L45: HARTING HAN 4 QUINTAX - STI (3-9,5M) P.N. 09150043013 | M45: Nos | N45: 60 | P45: 12 | Q45: =+N45-P45 -> 48 | R45: Rack No 2 /D2 | S45: Box No 15 | T45: UP/DC/FY22/00040 | U45: 44685 | V45: 44685 | W45: Siemens / Guest house | X45: Paschim Burdwan WB | Y45: Mr. Arka Dey | Z45: BY HAND | AA45: Mr. Saurabh Mishra | AB45: 6000HP: CLW PO 6k49x | AC45: 70201134101308 | AD45: 62OP 30878 | AE45: Short supply material dispatched now
A46: WAG9/6k | B46: 18 | D46: Delhi Sahabad Warehouse HARTING INDIA LTD. | J46: 109609632 | K46: 09150043013 | L46: HARTING HAN 4 QUINTAX - STI (3-9,5M) P.N. 09150043013 | M46: Nos | P46: 20 | Q46: =+Q45-P46 -> 28 | R46: Rack No 2 /D2 | S46: Box No 15 | T46: UP/DC/FY22/00065 | U46: 44707 | V46: 44707 | W46: SIEMENS LTD. G. HOUSE | X46: Paschim Burdwan WB | Y46: Mr. Arka Dey | Z46: 218110400 | AA46: SPOTON/DELHIVERY | AB46: WAG9/6k | AC46: 70201134101308 | AD46: 62OP 30878
A47: WAG9/6k | B47: 18 | D47: Delhi Sahabad Warehouse HARTING INDIA LTD. | J47: 109609632 | K47: 09150043013 | L47: HARTING HAN 4 QUINTAX - STI (3-9,5M) P.N. 09150043013 | M47: Nos | P47: 12 | Q47: =Q46-P47 -> 16 | R47: Rack No 2 /D2 | S47: Box No 15 | T47: UP/DC/FY22/00078 | U47: 44711 | V47: 44711 | W47: DDU Shed Mugal Sarai | X47: VARANASI | Y47: Mr. Arka Dey | Z47: BY HAND | AA47: Mr. Saurabh Mishra | AB47: WAG9/6k | AE47: Material for BLW Commissioning against 49x CLW
A48: WAG9/6k | B48: 18 | D48: Delhi Sahabad Warehouse HARTING INDIA LTD. | J48: 109609632 | K48: 09150043013 | L48: HARTING HAN 4 QUINTAX - STI (3-9,5M) P.N. 09150043013 | M48: Nos | P48: 8 | Q48: =Q47-P48 -> 8 | R48: Rack No 2 /D2 | S48: Box No 15 | T48: UP/DC/FY22/00079 | U48: 44712 | V48: 44712 | W48: SD II Stores Depot 2 PLW | X48: Patiala | Y48: Mr. Arka Dey | Z48: 215973860 | AA48: SPOTON/DELHIVERY | AB48: WAG9/6k | AC48: 20212095100413 | AD48: 62OP 30878
A49: WAG9/6k | B49: 18 | D49: Delhi Sahabad Warehouse HARTING INDIA LTD. | J49: 109609632 | K49: 09150043013 | L49: HARTING HAN 4 QUINTAX - STI (3-9,5M) P.N. 09150043013 | M49: Nos | P49: 8 | Q49: =Q48-P49 -> 0 | R49: Rack No 2 /D2 | S49: Box No 15 | T49: UP/DC/FY22/00089 | U49: 44714 | V49: 44714 | W49: SR DEE ELECTRIC LOCO SHED | X49: TUGHALAKABAD DELHI | Y49: Mr. Arka Dey | Z49: 216001992 | AA49: DELHIVERY LTD | AB49: WAG9/6k | AC49: 29215006D00977 | AD49: 62OP 30878
A50: WAG9/6k | B50: 19 | C50: 44645 | D50: Delhi Sahabad Warehouse HARTING INDIA LTD. | E50: SMO/0008 3600076242 | F50: 21-03-2022 28-02-2022 | G50: 4532/ 10-03-22 Paul Service | H50: Chennai | I50: 4511059519 | J50: 109492180 | K50: 09670094701 | L50: HARTING D-SUB CRIMP HOUSING P.N. 09670094701 | M50: Nos | N50: 600 | P50: 45 | Q50: =+N50-P50 -> 555 | R50: Rack No 2/E2 | S50: Box No 16 | T50: UP/DC/FY22/00037 | U50: 44683 | V50: 44683 | W50: Siemens / Guest house | X50: Paschim Burdwan WB | Y50: Mr. Arka Dey | Z50: BY HAND | AA50: Mr. Saurabh Mishra | AB50: 6000HP: CLW PO 6k49x | AC50: 70201134101308 | AD50: 62OP 30878 | AE50: Short supply material dispatched now
A51: WAG9/6k | B51: 19 | D51: Delhi Sahabad Warehouse HARTING INDIA LTD. | J51: 109492180 | K51: 09670094701 | L51: HARTING D-SUB CRIMP HOUSING P.N. 09670094701 | M51: Nos | P51: 70 | Q51: =+Q50-P51 -> 485 | R51: Rack No 2/E2 | S51: Box No 16 | T51: UP/DC/FY22/00058 | U51: 44700 | V51: 44700 | W51: Technocrats' Control Systems (India) Pvt. Ltd. | X51: NASIK | Y51: Mr. Tushar Narkhade | Z51: 215973541 | AA51: Spoton/Delhivery | AB51: 6000HP: CLW PO 6k49x | AC51: 70201134101308 | AD51: 62OP 30878 | AE51: Short supply material dispatched now
A52: WAG9/6k | B52: 19 | D52: Delhi Sahabad Warehouse HARTING INDIA LTD. | J52: 109492180 | K52: 09670094701 | L52: HARTING D-SUB CRIMP HOUSING P.N. 09670094701 | M52: Nos | P52: 40 | Q52: =+Q51-P52 -> 445 | R52: Rack No 2/E2 | S52: Box No 16 | T52: UP/DC/FY22/00065 | U52: 44707 | V52: 44707 | W52: SIEMENS LTD. G. HOUSE | X52: Paschim Burdwan WB | Y52: Mr. Arka Dey | Z52: 218110400 | AA52: SPOTON/DELHIVERY | AB52: WAG9/6k | AC52: 70201134101308 | AD52: 62OP 30878
A53: WAG9/6k | B53: 19 | D53: Delhi Sahabad Warehouse HARTING INDIA LTD. | J53: 109492180 | K53: 09670094701 | L53: HARTING D-SUB CRIMP HOUSING P.N. 09670094701 | M53: Nos | P53: 16 | Q53: =+Q52-P53 -> 429 | R53: Rack No 2/E2 | S53: Box No 16 | T53: UP/DC/FY22/00079 | U53: 44712 | V53: 44712 | W53: SD II Stores Depot 2 PLW | X53: Patiala | Y53: Mr. Arka Dey | Z53: 215973860 | AA53: SPOTON/DELHIVERY | AB53: WAG9/6k | AC53: 20212095100413 | AD53: 62OP 30878
A54: WAG9/6k | B54: 19 | D54: Delhi Sahabad Warehouse HARTING INDIA LTD. | J54: 109492180 | K54: 09670094701 | L54: HARTING D-SUB CRIMP HOUSING P.N. 09670094701 | M54: Nos | P54: 24 | Q54: =+Q53-P54 -> 405 | R54: Rack No 2/E2 | S54: Box No 16 | T54: UP/DC/FY22/00090 | U54: 44714 | V54: 44714 | W54: SD II Stores Depot 2 PLW | X54: Patiala | Y54: Mr. Arka Dey | Z54: 216001993 | AA54: DELHIVERY LTD | AB54: WAG9/6k | AC54: 20212095100413 | AD54: 62OP 30878
A55: WAG9/6k | B55: 19 | D55: Delhi Sahabad Warehouse HARTING INDIA LTD. | J55: 109492180 | K55: 09670094701 | L55: HARTING D-SUB CRIMP HOUSING P.N. 09670094701 | M55: Nos | P55: 16 | Q55: =+Q54-P55 -> 389 | R55: Rack No 2/E2 | S55: Box No 16 | T55: UP/DC/FY22/00089 | U55: 44714 | V55: 44714 | W55: SR DEE ELECTRIC LOCO SHED | X55: TUGHALAKABAD DELHI | Y55: Mr. Arka Dey | Z55: 216001992 | AA55: DELHIVERY LTD | AB55: WAG9/6k | AC55: 29215006D00977 | AD55: 62OP 30878
A56: WAG9/6k | B56: 19 | D56: Delhi Sahabad Warehouse HARTING INDIA LTD. | J56: 109492180 | K56: 09670094701 | L56: HARTING D-SUB CRIMP HOUSING P.N. 09670094701 | M56: Nos | P56: 2 | Q56: =+Q55-P56 -> 387 | R56: Rack No 2/E2 | S56: Box No 16 | T56: UP/DC/FY22/00123 | U56: 44732 | V56: 44732 | W56: SD II Stores Depot 2 PLW | X56: Patiala | Y56: Mr. Arka Dey | Z56: 312-72015145 | AA56: Indigo | AB56: WAG9/6k | AC56: 20212095100413 | AD56: 62OP 30878
A57: WAG9/6k | B57: 19 | D57: Delhi Sahabad Warehouse HARTING INDIA LTD. | J57: 109492180 | K57: 09670094701 | L57: HARTING D-SUB CRIMP HOUSING P.N. 09670094701 | M57: Nos | P57: 16 | Q57: =+Q56-P57 -> 371 | R57: Rack No 46 | S57: Box No 16 | T57: UP/DC/FY22/00128 | U57: 44734 | V57: 44734 | W57: CEE/D&D/CLW/CRJ | X57: CHITTARANJAN WB | Y57: MR. ARKA DEY | Z57: 215973560 | AA57: DELHIVERY LTD | AB57: WAG9/6k | AC57: 70201134101308 | AD57: 62OP 30878
B58: 20 | C58: 44645 | D58: Delhi Sahabad Warehouse SIEMENS LTD | E58: SMO/0005 MH1927751244 MH1927751265 | F58: 18-03-2022 11-09-19 16-09-19 | G58: X32953068/26-11-19 DTDC COURIER | H58: BHIWANDI | I58: 4509192857 | J58: 108140376 | K58: 3RT1076-6XF46-0LA2 | L58: CONTACTOR 3RT1076-6XF46-0LA2 | M58: Nos | N58: 18 | Q58: =+N58-P58 -> 18 | R58: Material Shift to Room | S58: Box No 1,2,3,4,5,6,7,8
B59: 21 | C59: 44648 | D59: Delhi Sahabad Warehouse | E59: SMO/0011 | F59: 44644 | H59: DELHI | J59: 107983770 | K59: 7210-N-181 | L59: Churning fan -part no. 7210N-181 DIN-55636 | M59: Nos | N59: 100 | Q59: =+N59-P59 -> 100 | R59: Rack No 41 | S59: Box No 51 (1 To 13)
B60: 22 | C60: 44648 | D60: Delhi Sahabad Warehouse | E60: SMO/0011 | F60: 44644 | H60: DELHI | J60: A | K60: A | L60: AMIT SPOL LAB | M60: BOX | N60: 2 | Q60: =+N60-P60 -> 2 | R60: Rack No 23 | S60: Box No 44 & 45
B61: 23 | C61: 44648 | D61: Delhi Sahabad Warehouse LEROY | E61: SMO/0011 FE410009 | F61: 24-03-2022 25-02-21 | H61: FRANCE | I61: 4200826011 | J61: 111381215 | K61: BRIO R114 | L61: MODULE BRIO R114 MAKE LEROY-AUTOMATION | M61: Nos | N61: 10 | Q61: =+N61-P61 -> 10 | R61: Material Shift to Room | S61: Box No 48
B62: 24 | C62: 44648 | D62: Delhi Sahabad Warehouse LEROY | E62: SMO/10001 FE410009 | F62: 22-03-2022 25-02-21 | H62: FRANCE | I62: 4200826011 | J62: 111381214 | K62: RIOM T51321 | L62: MODULE RIOM T51321 MAKE LEROY-AUTOMATION | M62: Nos | N62: 1 | Q62: =+N62-P62 -> 1 | R62: Material Shift to Room | S62: Box No 48
B63: 25 | C63: 44648 | D63: Delhi Sahabad Warehouse SVAN ANALYTICAL INSTRUMENT PVT LTD. | E63: SMO/0011 3081/21-22 | F63: 24-03-2022 27-04-2021 | H63: DOMBILLI MH | I63: 4510395452 | J63: 111391860 | K63: 111391860 | L63: Micro volume Viscometer-OIL APPLICATION | M63: Set | N63: 1 | Q63: =+N63-P63 -> 1 | R63: Material Shift to Room | S63: Box No 48
B64: 26 | C64: 44648 | D64: Delhi Sahabad Warehouse | E64: SMO/0006 | F64: 44637 | H64: DELHI | J64: 101668585 | K64: EDPM4610 | L64: S101091363 GASKET GISTA SECTION EDPM4610 | M64: MTR | N64: 50 | Q64: =+N64-P64 -> 50 | R64: Material Shift to Room | S64: Box No 49
B65: 27 | C65: 44648 | D65: Delhi Sahabad Warehouse | E65: SMO/10001 | F65: 44642 | H65: DELHI | J65: A5E41521351 | K65: 3P_5.8mm | L65: ACC_CONN_HOUSING_FEMALE_3P_5.8mm | M65: Nos | N65: 46 | Q65: =+N65-P65 -> 46 | R65: Material Shift to Room | S65: Box No 49
B66: 28 | C66: 44648 | D66: Delhi Sahabad Warehouse | E66: SMO/10001 | F66: 44642 | H66: DELHI | J66: A5E41521162 | K66: 0.08-0.33mm2_PhBz | L66: ACC_CONN_CONT_FEMALE_0.08-0.33mm2_PhBz | M66: Nos | N66: 48 | Q66: =+N66-P66 -> 48 | R66: Material Shift to Room | S66: Box No 49
B67: 29 | C67: 44648 | D67: Delhi Sahabad Warehouse | E67: SMO/10001 | F67: 44642 | H67: DELHI | J67: A5E46938651 | K67: SN 66355 B30-A | L67: Siemens Name Plate as per SN 66355 B30-A | M67: Nos | N67: 4 | Q67: =+N67-P67 -> 4 | R67: Material Shift to Room | S67: Box No 49
B68: 30 | C68: 44648 | D68: Delhi Sahabad Warehouse | E68: SMO/0006 | F68: 44637 | H68: DELHI | J68: 102086056 | K68: 102086056 | L68: HEAT SHRINK TUBE 12.0/6 BLACK | M68: MTR | N68: 100 | Q68: =+N68-P68 -> 100 | R68: Material Shift to Room | S68: Box No 50
B69: 31 | C69: 44648 | D69: Delhi Sahabad Warehouse | E69: SMO/0006 | F69: 44637 | H69: DELHI | J69: A5E49610997 | K69: A5E49610997 | L69: Heat Shrink Sleeve_30.0/15.0mm Black | M69: MTR | N69: 50 | Q69: =+N69-P69 -> 50 | R69: Material Shift to Room | S69: Box No 50
B70: 32 | C70: 44648 | D70: Delhi Sahabad Warehouse | E70: SMO/0006 | F70: 44637 | H70: DELHI | J70: 110408140 | K70: 110408140 | L70: Heat Shrinkable Transperant Tube for 185 SqmmCable HST 30 Clear | M70: MTR | N70: 100 | Q70: =+N70-P70 -> 100 | R70: Material Shift to Room | S70: Box No 50
B71: 33 | C71: 44648 | D71: Delhi Sahabad Warehouse JAINSONS INDIA | E71: SMO/0006 0000880/20-21 | F71: 17-03-2022 24-09-20 | H71: NEW DELHI | I71: 4510011036 | J71: 110456652 | K71: 1061000250230 | L71: Heat Shrinkable Transperant Tube 150 Sqmm cable 25/12.5 | M71: MTR | N71: 50 | Q71: =+N71-P71 -> 50 | R71: Material Shift to Room | S71: Box No 50
B72: 34 | C72: 44648 | D72: Delhi Sahabad Warehouse JAINSONS INDIA | E72: SMO/0006 0000880/20-21 | F72: 17-03-2022 24-09-20 | H72: NEW DELHI | I72: 4510011036 | J72: 110456658 | K72: 110456658 | L72: Heat Shrinkable Transparent tube 35 cabl (12/6) | M72: MTR | N72: 100 | Q72: =+N72-P72 -> 100 | R72: Material Shift to Room | S72: Box No 50
B73: 35 | C73: 44648 | D73: Delhi Sahabad Warehouse JAINSONS INDIA | E73: SMO/0006 0000880/20-21 | F73: 17-03-2022 24-09-20 | H73: NEW DELHI | I73: 4510011036 | J73: 110456655 | K73: 110456655 | L73: Heat Shrinkable Transparent tube 50 cabl (14/7 | M73: MTR | N73: 100 | Q73: =+N73-P73 -> 100 | R73: Material Shift to Room | S73: Box No 50
B74: 36 | C74: 44648 | D74: Delhi Sahabad Warehouse JAINSONS INDIA | E74: SMO/0006 0000880/20-21 | F74: 17-03-2022 24-09-20 | H74: NEW DELHI | I74: 4510011036 | J74: 110408141 | K74: 110408141 | L74: Heat Shrinkable Transperant Tube for70Sq (18/9) | M74: MTR | N74: 100 | Q74: =+N74-P74 -> 100 | R74: Material Shift to Room | S74: Box No 50
B75: 37 | C75: 44648 | D75: Delhi Sahabad Warehouse | E75: SMO/0006 | F75: 44637 | H75: DELHI | J75: B | K75: B | L75: HEP CUBICAL | M75: BOX | N75: 2 | Q75: =+N75-P75 -> 2 | R75: RACK NO 28 | S75: Box No 46 & 47
A76: WAG9/6k | B76: 38 | C76: 44648 | D76: Delhi Sahabad Warehouse | E76: SMO/0009 | F76: 44642 | H76: DELHI | J76: 109611234 | K76: 3742612236 | L76: Active Speed Sensors suitable for IGBT locos [3-Phase Locos] DSD 1616.73 QHW - F267S 3742612236 | M76: Nos | N76: 101 | P76: 1 | Q76: =+N76-P76 -> 100 | R76: Rack No 33 | S76: Box No 36 To 43 | T76: UP/DC/FY22/00024 | U76: 44672 | V76: 44674 | W76: Siemens Ltd- Nasik Work | X76: Nasik | Y76: Mr. Arka Dey | Z76: 50815918845 | AA76: BLUE DART SARFACE | AB76: WAG9/6k | AC76: - | AD76: - | AE76: For Lab Testing
A77: WAG9/6k | B77: 38 | D77: Delhi Sahabad Warehouse | J77: 109611234 | K77: 3742612236 | L77: Active Speed Sensors suitable for IGBT locos [3-Phase Locos] DSD 1616.73 QHW - F267S 3742612236 | M77: Nos | P77: 30 | Q77: =+Q76-P77 -> 70 | R77: Rack No 33 | S77: Box No 36 To 43 | T77: UP/DC/FY22/00065 | U77: 44707 | V77: 44707 | W77: SIEMENS LTD. G. HOUSE | X77: Paschim Burdwan WB | Y77: Mr. Arka Dey | Z77: 218110400 | AA77: SPOTON/DELHIVERY | AB77: WAG9/6k | AC77: 70201134101308 | AD77: 62OP 30878
A78: WAG9/6k | B78: 38 | D78: Delhi Sahabad Warehouse | J78: 109611234 | K78: 3742612236 | L78: Active Speed Sensors suitable for IGBT locos [3-Phase Locos] DSD 1616.73 QHW - F267S 3742612236 | M78: Nos | P78: 12 | Q78: =+Q77-P78 -> 58 | R78: Rack No 33 | S78: Box No 36 To 43 | T78: UP/DC/FY22/00079 | U78: 44712 | V78: 44712 | W78: SD II Stores Depot 2 PLW | X78: Patiala | Y78: Mr. Arka Dey | Z78: 215973860 | AA78: SPOTON/DELHIVERY | AB78: WAG9/6k | AC78: 20212095100413 | AD78: 62OP 30878
A79: WAG9/6k | B79: 38 | D79: Delhi Sahabad Warehouse | J79: 109611234 | K79: 3742612236 | L79: Active Speed Sensors suitable for IGBT locos [3-Phase Locos] DSD 1616.73 QHW - F267S 3742612236 | M79: Nos | P79: 18 | Q79: =+Q78-P79 -> 40 | R79: Rack No 33 | S79: Box No 36 To 43 | T79: UP/DC/FY22/00090 | U79: 44714 | V79: 44714 | W79: SD II Stores Depot 2 PLW | X79: Patiala | Y79: Mr. Arka Dey | Z79: 216001993 | AA79: DELHIVERY LTD | AB79: WAG9/6k | AC79: 20212095100413 | AD79: 62OP 30878
A80: WAG9/6k | B80: 38 | D80: Delhi Sahabad Warehouse | J80: 109611234 | K80: 3742612236 | L80: Active Speed Sensors suitable for IGBT locos [3-Phase Locos] DSD 1616.73 QHW - F267S 3742612236 | M80: Nos | P80: 12 | Q80: =+Q79-P80 -> 28 | R80: Rack No 34 | S80: Box No 36 To 43 | T80: UP/DC/FY22/00089 | U80: 44714 | V80: 44714 | W80: SR DEE ELECTRIC LOCO SHED | X80: TUGHALAKABAD DELHI | Y80: Mr. Arka Dey | Z80: 216001992 | AA80: DELHIVERY LTD | AB80: WAG9/6k | AC80: 29215006D00977 | AD80: 62OP 30878
A81: WAG9/6k | B81: 38 | D81: Delhi Sahabad Warehouse | J81: 109611234 | K81: 3742612236 | L81: Active Speed Sensors suitable for IGBT locos [3-Phase Locos] DSD 1616.73 QHW - F267S 3742612236 | M81: Nos | P81: 1 | Q81: =+Q80-P81 -> 27 | R81: Rack No 34 | S81: Box No 36 To 43 | T81: UP/DC/FY22/00115 | U81: 44728 | V81: 44728 | W81: Siemens Ltd- Nasik Work | X81: NASIK | Y81: Mr. Arka Dey | Z81: 215979587 | AA81: DELHIVERY LTD | AB81: WAG9/6k | AE81: This material is being send for Teasting Purpose Only, Returnable Basis.
A82: WAG9/6k | B82: 38 | D82: Delhi Sahabad Warehouse | J82: 109611234 | K82: 3742612236 | L82: Active Speed Sensors suitable for IGBT locos [3-Phase Locos] DSD 1616.73 QHW - F267S 3742612236 | M82: Nos | P82: 12 | Q82: =+Q81-P82 -> 15 | R82: Rack No 34 | S82: Box No 36 To 43 | T82: UP/DC/FY22/00128 | U82: 44734 | V82: 44734 | W82: CEE/D&D/CLW/CRJ | X82: CHITTARANJAN WB | Y82: MR. ARKA DEY | Z82: 215973560 | AA82: DELHIVERY LTD | AB82: WAG9/6k | AC82: 70201134101308 | AD82: 62OP 30878
B83: 39 | C83: 44651 | D83: BODY SMITHS PVT. LTD. | E83: BSPL/147/21-22 | F83: 44648 | H83: KOLKATA | I83: 4511101428 | J83: 107143203 | K83: 107143203 | L83: PANEL LIFTING ARRANGEMENT LOA LIMIT-2MT (Tackler) | M83: Nos | N83: 8 | Q83: =+N83-P83 -> 8 | R83: Row No- E | S83: Loose
B84: 40 | C84: 44652 | D84: Delhi Sahabad Warehouse | E84: SMO/0013 | F84: 44645 | H84: DELHI | J84: 108334275 | K84: EP23 | L84: EAR MUFF HELMET ATTACHABLE EP23 | M84: Pair | N84: 30 | Q84: =+N84-P84 -> 30 | R84: Material Shift to Room | S84: Box No 53 | AE84: Safety Item
B85: 41 | C85: 44652 | D85: Delhi Sahabad Warehouse | E85: SMO/0013 | F85: 44645 | H85: DELHI | J85: 107151794 | K85: 76-301 | L85: knitted glove with PVC 76-301 | M85: Pair | N85: 600 | Q85: =+N85-P85 -> 600 | R85: Material Shift to Room | S85: Box No 53 | AE85: Safety Item
B86: 42 | C86: 44652 | D86: Delhi Sahabad Warehouse | E86: SMO/0013 | F86: 44645 | H86: DELHI | J86: 107151794 | K86: 11-624 Cut level 3 | L86: coating on seamless liner. PU coating on a Dyneema® /Lycra® / nylon liner. Palm coated. Knitwrist. Length 220-'270 mm (9-11 inch). Light grey/dark grey. Model no: 11-624 Cut level 3 | M86: Pair | N86: 60 | Q86: =+N86-P86 -> 60 | R86: Material Shift to Room | S86: Box No 53 | AE86: Safety Item
B87: 43 | C87: 44652 | D87: Delhi Sahabad Warehouse EBM-PAPST INDIA PVT. LTD | E87: SMO/0013 11128/20-21 | F87: 25-03-2022 28-10-20 | G87: FEDEX EXPRESS 8155 7173 6961 | H87: chennai | I87: 4509974791 | J87: 107146625 | K87: 4318N/2N | L87: Ebm-Papst Churning Fan-Model No- 4318N/2N | M87: Nos | N87: 69 | P87: 69 | Q87: =+N87-P87 -> 0 | R87: Rack No 37 | S87: Box No 55 | T87: UP/DC/FY22/00022 | U87: 44672 | V87: 44674 | W87: TEKNOCRATS CONTROL PVT. LTD. | X87: NASIK | Y87: Mr. Arka Dey | Z87: 50815918834 | AA87: BLUE DART SARFACE | AB87: WAG9/6k | AC87: 70201134101308 | AD87: 62OP 30878 | AE87: Short supply material dispatched now
B88: 44 | C88: 44652 | D88: Delhi Sahabad Warehouse | E88: SMO/0016 | F88: 44646 | H88: DELHI | J88: 106288808 | K88: 106288808 | L88: PVC GENRIC PRINT TUBE SIZE 5.5MM ID 130821 | M88: MTR | N88: 2000 | Q88: =+N88-P88 -> 2000 | R88: Material Shift to Room | S88: Box No 54/( 1 T0 4)
B89: 45 | C89: 44652 | D89: Delhi Sahabad Warehouse | E89: SMO/0016 | F89: 44646 | H89: DELHI | J89: 106288811 | K89: 106288811 | L89: PVC GENRIC PRINT TUBE SIZE 8.00MM ID 140116 | M89: MTR | N89: 100 | Q89: =+N89-P89 -> 100 | R89: Material Shift to Room | S89: Box No 54/( 1 T0 4)
B90: 46 | C90: 44652 | D90: Delhi Sahabad Warehouse | E90: SMO/0016 | F90: 44646 | H90: DELHI | J90: 107143092 | K90: 107143092 | L90: PVC GENRIC PRINT TUBE SIZE 4.50MM ID BATCH NO 130424 | M90: MTR | N90: 800 | Q90: =+N90-P90 -> 800 | R90: Material Shift to Room | S90: Box No 54/( 1 T0 4)
B91: 47 | C91: 44652 | D91: Delhi Sahabad Warehouse | E91: SMO/0016 | F91: 44646 | H91: DELHI | J91: 107123142 | K91: IELHK11-1REC4-52-3.00-01-V | L91: MCB 3 AMPS WITH AUX SWITCH IELHK11-1REC4-52-3.00-01-V -Remmlot | M91: Nos | N91: 38 | Q91: =+N91-P91 -> 38 | R91: Rack No 4/E1 | S91: Bin No 56
B92: 48 | C92: 44652 | D92: Delhi Sahabad Warehouse | E92: SMO/0016 | F92: 44646 | H92: DELHI | J92: 101148348 | K92: 101148348 | L92: REMMLOT ANTINNA BRACKET BLACK | M92: Nos | N92: 2 | Q92: =+N92-P92 -> 2 | R92: Rack No 4/E1 | S92: Bin No 56
B93: 49 | C93: 44652 | D93: Delhi Sahabad Warehouse LUTZE TRANSPORTATION GMBH | E93: SMO/0010 9111028851 | F93: 23-03-2022 07-10-20 | G93: GEETA SHIPPING 239679 / 04-03-21 | H93: GERMANY | I93: 4200789641 | J93: 109447737 | K93: 800103 | L93: LION POWER SUPPLY 36 W DC24V/110V 800103 | M93: Nos | N93: 89 | P93: 89 | Q93: =+N93-P93 -> 0 | R93: Dispached On Same Day | S93: Dispached On Same Day | T93: UP/DC/FY22/00018 | U93: 44666 | V93: 44666 | W93: Siemens Ltd. | X93: Nasik | Y93: Mr. Arka Dey | Z93: 226168328 | AA93: SPOTON LOGISTIC Pvt. Ltd. | AB93: WAG9/6k | AC93: 70201134101308 | AD93: 62OP 30878 | AE93: Short supply material dispatched now
B94: 50 | C94: 44652 | D94: Delhi Sahabad Warehouse LUTZE TRANSPORTATION GMBH | E94: SMO/0010 9111028601 | F94: 23-03-2022 23-09-20 | G94: GEETA SHIPPING AND CLEARING SERVICE 239666 / 05-3-21 | H94: GERMANY | I94: 4200789641 | J94: 109447740 | K94: 803001 | L94: LION-Busskoppler-MVB-LUE 803001 | M94: Nos | N94: 91 | P94: 91 | Q94: =+N94-P94 -> 0 | R94: Dispached On Same Day | S94: Dispached On Same Day | T94: UP/DC/FY22/00018 | U94: 44666 | V94: 44666 | W94: Siemens Ltd. | X94: Nasik | Y94: Mr. Arka Dey | Z94: 226168328 | AA94: SPOTON LOGISTIC Pvt. Ltd. | AB94: WAG9/6k | AC94: 70201134101308 | AD94: 62OP 30878 | AE94: Short supply material dispatched now
B95: 51 | C95: 44652 | D95: Delhi Sahabad Warehouse LUTZE TRANSPORTATION GMBH | E95: SMO/0010 9111029215 | F95: 23-03-2022 28-10-20 | G95: GEETA SHIPPING AND CLEARING SERVICE 239667 / 11-3-21 | H95: GERMANY | I95: 4200789641 | J95: 109447743 | K95: 803201 | L95: LION Erweiterungsmodul,8 Wechslerkanaele 803201 | M95: Nos | N95: 89 | P95: 89 | Q95: =+N95-P95 -> 0 | R95: Dispached On Same Day | S95: Dispached On Same Day | T95: UP/DC/FY22/00018 | U95: 44666 | V95: 44666 | W95: Siemens Ltd. | X95: Nasik | Y95: Mr. Arka Dey | Z95: 226168328 | AA95: SPOTON LOGISTIC Pvt. Ltd. | AB95: WAG9/6k | AC95: 70201134101308 | AD95: 62OP 30878 | AE95: Short supply material dispatched now
B96: 52 | C96: 44652 | D96: Delhi Sahabad Warehouse LUTZE TRANSPORTATION GMBH | E96: SMO/0010 9111029215 | F96: 23-03-2022 28-10-20 | G96: GEETA SHIPPING AND CLEARING SERVICE 239667 / 11-3-21 | H96: GERMANY | I96: 4200789641 | J96: 109447744 | K96: 803203 | L96: LION DA 8xDC24V/110V 803203 | M96: Nos | N96: 129 | P96: 129 | Q96: =+N96-P96 -> 0 | R96: Dispached On Same Day | S96: Dispached On Same Day | T96: UP/DC/FY22/00018 | U96: 44666 | V96: 44666 | W96: Siemens Ltd. | X96: Nasik | Y96: Mr. Arka Dey | Z96: 226168328 | AA96: SPOTON LOGISTIC Pvt. Ltd. | AB96: WAG9/6k | AC96: 70201134101308 | AD96: 62OP 30878 | AE96: Short supply material dispatched now
B97: 53 | C97: 44652 | D97: Delhi Sahabad Warehouse LUTZE TRANSPORTATION GMBH | E97: SMO/0010 9111029215 | F97: 23-03-2022 28-10-20 | G97: GEETA SHIPPING AND CLEARING SERVICE 239667 / 11-3-21 | H97: GERMANY | I97: 4200789641 | J97: 109447745 | K97: 803301 | L97: LION-AI4-U-LUE (Analog Input, 4 channels 803301 | M97: Nos | N97: 35 | P97: 35 | Q97: =+N97-P97 -> 0 | R97: Dispached On Same Day | S97: Dispached On Same Day | T97: UP/DC/FY22/00018 | U97: 44666 | V97: 44666 | W97: Siemens Ltd. | X97: Nasik | Y97: Mr. Arka Dey | Z97: 226168328 | AA97: SPOTON LOGISTIC Pvt. Ltd. | AB97: WAG9/6k | AC97: 70201134101308 | AD97: 62OP 30878 | AE97: Short supply material dispatched now
B98: 54 | C98: 44652 | D98: Delhi Sahabad Warehouse | E98: SMO/0010 | F98: 44643 | H98: DELHI | J98: 109447749 | K98: 803401 | L98: LION Erweiterungsmodul, 4 analoge Ausg. 803401 | M98: Nos | N98: 36 | P98: 36 | Q98: =+N98-P98 -> 0 | R98: Dispached On Same Day | S98: Dispached On Same Day | T98: UP/DC/FY22/00018 | U98: 44666 | V98: 44666 | W98: Siemens Ltd. | X98: Nasik | Y98: Mr. Arka Dey | Z98: 226168328 | AA98: SPOTON LOGISTIC Pvt. Ltd. | AB98: WAG9/6k | AC98: 70201134101308 | AD98: 62OP 30878 | AE98: Short supply material dispatched now
B99: 55 | C99: 44655 | D99: Delhi Sahabad Warehouse EMTEX ENGINEERING PVT LTD | E99: SMO/0020 AWH200020504 | F99: 29-03-2022 20-09-2021 | G99: 2113001728 | H99: DELHI | I99: 4510789342 | J99: 111448667 | K99: 221 | L99: SIKAFLEX 221 | M99: Nos | N99: 48 | P99: 48 | Q99: =+N99-P99 -> 0 | R99: RACK NO 7/F | S99: Bin No 02 | T99: UP/DC/FY22/00022 | U99: 44672 | V99: 44674 | W99: TEKNOCRATS CONTROL PVT. LTD | X99: NASIK | Y99: Mr. Arka Dey | Z99: 50815918834 | AA99: BLUE DART SARFACE | AB99: WAG9/6k | AC99: 70201134101308 | AD99: 62OP 30878 | AE99: Short supply material dispatched now
B100: 56 | C100: 44655 | D100: Delhi Sahabad Warehouse | E100: SMO/0020 | F100: 44649 | H100: DELHI | J100: 109350976 | K100: 09300060301 | L100: VOLTAGE SENSOR CONNECTION - 3 PIN 10A HAN 6B-AGG-LB | M100: Nos | N100: 9 | Q100: =+N100-P100 -> 9 | R100: RACK NO 7/F | S100: Bin No 01
...

Sheet In-ward Register
N1: =M1-M2 -> -1157585.4 | O1: =O2/10000000 -> 0.28611668
B2: Material In-ward register as on 31 -July-25 | M2: =SUM(M4:M1048576) -> 1157585.4 | O2: =SUBTOTAL(9,O3:O1735) -> 2861166.8 | Q2: 55
A3: Sr. No. | B3: Date of receipt | C3: Material Receipt From | D3: Warehouse Doc. No & Vendor Document No. | E3: Warehouse Documents Date / Vendor Doc. Date | F3: LR No/ Date | G3: Vendor Place | H3: PO. No. | I3: Sap Code | J3: Part Code | K3: Description | L3: UOM | M3: Received Qty | N3: Unit Price as per P.o. | O3: Total Value Of Receipt | P3: Remarks
A4: 1 | B4: 44637 | C4: Delhi Sahabad Warehouse Integra Engineering India Ltd. | D4: SMO/0002 | E4: 44634 | G4: DELHI | H4: 4509249408 | I4: 109687772 | J4: 109687772 | K4: DISPLAY (FRAM )MOUNTING BRACKET | L4: Nos | M4: 20 | N4: 911 | O4: =M4*N4 -> 18220
A5: 2 | B5: 44637 | C5: Delhi Sahabad Warehouse Hind Rectifiers Ltd. | D5: SMO/0001 | E5: 44634 | G5: DELHI | H5: 4508422862 | I5: 108227130 | J5: HN350 ( DH350/HK351N)6 | K5: BATTERY CHARGER ASSEMBLY DRG NO 4TRS-231 rectifier with Blocker Diodes and Current Limiting Resistors for WDx4 Diesel Locomotive” | L5: Nos | M5: 8 | N5: 42000 | O5: =M5*N5 -> 336000
A6: 3 | B6: 44643 | C6: Delhi Sahabad Warehouse SHUBHADA POLYMERS PRODUCTS PVT LTD | D6: SMO/0004 SHS201001538 | E6: 17-03-2022 13-01-20 | F6: 359972307 GATIKWE | G6: MUMBAI | H6: 4509462642 | I6: 102316360 | J6: ECC1/ECC2 S3 | K6: CABLE PENETRATION 800A ECC1/ECC2 S3 | L6: Nos | M6: 24 | N6: 1141 | O6: =M6*N6 -> 27384
A7: 4 | B7: 44643 | C7: Delhi Sahabad Warehouse SHUBHADA POLYMERS PRODUCTS PVT LTD | D7: SMO/0004 SHS201001538 | E7: 17-03-2022 13-01-20 | F7: 359972307 GATIKWE | G7: MUMBAI | H7: 4509462642 | I7: A5E47174092 | J7: A5E436723831_AD | K7: CABLE PENETRATION 600-650A | L7: Nos | M7: 24 | N7: 953 | O7: =M7*N7 -> 22872
A8: 5 | B8: 44643 | C8: Delhi Sahabad Warehouse HARTING INDIA LTD. | D8: SMO/0004 3600059304 | E8: 17-03-2022 31-12-20 | F8: XPRESSBEES,91691183107 31-12-20 | G8: chennai | H8: 4509978514 | I8: 112136075 | J8: 09300240581 | K8: HARTING Hood Female HAN 24B-GS-ZV-29 '09300240581 | L8: Nos | M8: 54 | N8: 1196.19 | O8: =M8*N8 -> 64594.26
A9: 6 | B9: 44643 | C9: Delhi Sahabad Warehouse WEIDMULLER ELECTRONIC INDIA PVT LTD | D9: SMO/0004 203001 | E9: 17-03-2022 25-11-19 | F9: 1004427023 26-11-19 Rivigo Service Pvt.Ltd. | G9: BENGALURU | H9: 4509411596 | I9: 109710324 | J9: WFF185/AH 600V 360 AMP | K9: FEED THROUGH TERMINAL BLOCK WFF 185/AH 1029600000 | L9: Nos | M9: 36 | N9: 74 | O9: =M9*N9 -> 2664
A10: 7 | B10: 44643 | C10: Delhi Sahabad Warehouse TDK COMPONENTS PTE LTD | D10: SMO/0004 56738710 | E10: 17-03-2022 24-12-21 | F10: MANJEET TRANSPORT / 10923 | G10: SINGAPORE | H10: 4200899863 | I10: 109443666 | J10: B32373A4257J 80 | K10: MET FILM CAPACITOR RoHS COMPATIBLE 250uF +-5% 480V PEC MKD AC | L10: Nos | M10: 19 | N10: 4222.16 | O10: =M10*N10 -> 80221.04
A11: 8 | B11: 44643 | C11: Delhi Sahabad Warehouse Span HI tech Pvt. Ltd. | D11: SMO/0004 337 | E11: 17-03-2022 03-02-21 | F11: 123315152 03-02-21 GATI KWE | G11: NASIK | H11: 4510318862 | I11: 110320774 | J11: 1902MA1001_A | K11: HEP CUBICLE FOR WAP7 DRG NO 1902MA1001_A (GASKET) | L11: Mtr. | M11: 94 | N11: 295 | O11: =M11*N11 -> 27730
A12: 9 | B12: 44643 | C12: Delhi Sahabad Warehouse Ebm-Papst India Pvt. Ltd. | D12: SMO/0015 | E12: 44646 | G12: DELHI | H12: 4508872517 | I12: 107146625 | J12: 7210N-181 | K12: INSTRUMENT COOLING FAN. 7210N-181 /Churning Fan | L12: Nos | M12: 25 | N12: 4954 | O12: =M12*N12 -> 123850
A13: 10 | B13: 44643 | C13: Delhi Sahabad Warehouse SIEMENS AG | D13: SM0/0003 7411RF3800333725 | E13: 16-03-2022 10-12-20 | F13: MANJEET TRANSPORT / 8359, 04-03-21 | G13: GERMANY | H13: 4200791659 | I13: 101999218 | J13: XL KF i (A2B00075622) | K13: A2B00075622 DRIVER'S DESK TERMINAL SITET XL KF 1 74V | L13: Nos | M13: 36 | N13: 239925.69 | O13: =M13*N13 -> 8637324.8
A14: 11 | B14: 44645 | C14: Delhi Sahabad Warehouse Norish Automation GMBH | D14: SM0/0007 2022116 | E14: 19-03-2022 13-02-20 | F14: MANJEET TRANSPORT/ 5799 26-02-20 | G14: GERMANY | H14: 4200754583 | I14: 107123964 | J14: FAHZ5-P3-024/028/007 | K14: SPEED SENSOR NORIS | L14: Nos | M14: 230 | N14: 9467.32 | O14: =M14*N14 -> 2177483.6
A15: 12 | B15: 44645 | C15: Delhi Sahabad Warehouse Oasis Instruments Company | D15: SM0/0007 | E15: 44639 | G15: Hyderabad | H15: 4507585177 | I15: 107123967 | J15: GT46MAC-T | K15: TEMP. SENSOR GT46MAC-T | L15: Nos | M15: 38 | N15: 11000 | O15: =M15*N15 -> 418000
A16: 13 | B16: 44645 | C16: Delhi Sahabad Warehouse P6230A607 | D16: SM0/0007 | E16: 44639 | H16: 4505739651 | I16: 101668554 | J16: A5E00747920 | K16: MAIN BOARD 6FH9543-3BY60 A5E00747920, S101638370 | L16: Nos | M16: 3 | N16: 0 | O16: =M16*N16 -> 0
A17: 14 | B17: 44645 | C17: Delhi Sahabad Warehouse HARTING INDIA LTD. | D17: SMO/0008 3600076242 | E17: 21-03-2022 28-02-2022 | F17: 4532/ 10-03-2022 Paul Service | G17: chennai | H17: 4511059519 | I17: 109492181 | J17: 09670003476 | K17: HARTING D SUB -S- FEMALE-18-22 CRIMP CONDUCT P.N. 09670003476 | L17: Nos | M17: 1000 | N17: 18.35 | O17: =M17*N17 -> 18350
A18: 15 | B18: 44645 | C18: Delhi Sahabad Warehouse HARTING INDIA LTD. | D18: SMO/0008 3600076242 | E18: 21-03-2022 28-02-2022 | F18: 4532/PAUL SERVICE | G18: CHENNAI | H18: 4511059519 | I18: 109609630 | J18: 09150006123 | K18: HARTING R15-STI-C (AU) 0.5-AWG20 09150006123 | L18: Nos | M18: 200 | N18: 19.26 | O18: =M18*N18 -> 3852
A19: 16 | B19: 44645 | C19: Delhi Sahabad Warehouse HARTING INDIA LTD. | D19: SMO/0008 3600076242 | E19: 44641 | F19: 4532/PAUL SERVICE | G19: chennai | H19: 4511059519 | I19: 109492197 | J19: 61030000067 | K19: CRIMP FLANGE FOR D-SUB HARTING (S102117360) FORMVB CONNECTOR 61030000067 | L19: Nos | M19: 600 | N19: 66.92 | O19: =M19*N19 -> 40152
A20: 17 | B20: 44645 | C20: Delhi Sahabad Warehouse HARTING INDIA LTD. | D20: SMO/0008 3600076242 | E20: 21-03-2022 20-02-2022 | F20: 4532/10-03-22 Paul Service | G20: CHENNAI | H20: 4511059519 | I20: 109492194 | J20: 61030012010 | K20: HARTING INDU COM 9P 1T ENTRY HEX SCREW 4-40 P.N. 61030012010 | L20: Nos | M20: 470 | N20: 234.9 | O20: =M20*N20 -> 110403
A21: 18 | B21: 44645 | C21: Delhi Sahabad Warehouse HARTING INDIA LTD. | D21: SMO/0008 3600076242 | E21: 21-03-2022 28-02-2022 | F21: 4532/PAUL SERVICE | G21: CHENNAI | H21: 4511059519 | I21: 109609632 | J21: 09150043013 | K21: HAN 4 QUINTAX STIFT, 3-9.5MM 09150043013 | L21: Nos | M21: 60 | N21: 100.06 | O21: =M21*N21 -> 6003.6
A22: 19 | B22: 44645 | C22: Delhi Sahabad Warehouse HARTING INDIA LTD. | D22: SMO/0008 3600076242 | E22: 21-03-2022 28-02-2022 | F22: 4532/ 10-03-22 Paul Service | G22: Chennai | H22: 4511059519 | I22: 109492180 | J22: 09670094701 | K22: D- SUB CRIMP 9-POLE FEMALE ASSEMBLY '09670094701 | L22: Nos | M22: 600 | N22: 32.22 | O22: =M22*N22 -> 19332
A23: 20 | B23: 44645 | C23: Delhi Sahabad Warehouse SIEMENS LTD | D23: SMO/0005 MH1927751244 MH1927751265 | E23: 18-03-2022 11-09-19 16-09-19 | F23: X32953068/26-11-19 DTDC COURIER | G23: BHIWANDI | H23: 4509192857 | I23: 108140376 | J23: 3RT1076-6XF46-0LA2 | K23: CONTACTOR 3RT1076-6XF46-0LA2 | L23: Nos | M23: 18 | N23: 29845 | O23: =M23*N23 -> 537210
A24: 21 | B24: 44648 | C24: Delhi Sahabad Warehouse Ebm-Papst India Pvt. Ltd. | D24: SMO/0011 | E24: 44644 | G24: DELHI | H24: 4508872517 | I24: 107146625 | J24: 7210N-181 | K24: INSTRUMENT COOLING FAN. 7210N-181 /Churning Fan | L24: Nos | M24: 100 | N24: 4954 | O24: =M24*N24 -> 495400
A25: 22 | B25: 44648 | C25: Delhi Sahabad Warehouse LEROY | D25: SMO/0011 FE410009 | E25: 24-03-2022 25-02-21 | G25: FRANCE | H25: 4200826011 | I25: 111381215 | J25: BRIO R114 | K25: MODULE BRIO R114 MAKE LEROY-AUTOMATION | L25: Nos | M25: 4 | N25: 79877 | O25: =M25*N25 -> 319508
A26: 23 | B26: 44648 | C26: Delhi Sahabad Warehouse LEROY | D26: SMO/0011 FE410009 | E26: 24-03-2022 25-02-21 | G26: FRANCE | H26: 4200826011 | I26: 111381216 | J26: PTOLBPX118 | K26: MODULE PTOLBPX118 MAKE LEROY-AUTOMATION | L26: Nos | M26: 6 | N26: 4438 | O26: =M26*N26 -> 26628
A27: 24 | B27: 44648 | C27: Delhi Sahabad Warehouse LEROY | D27: SMO/10001 FE410009 | E27: 22-03-2022 25-02-21 | G27: FRANCE | H27: 4200826011 | I27: 111381214 | J27: RIOM T51321 | K27: MODULE RIOM T51321 MAKE LEROY-AUTOMATION | L27: Nos | M27: 1 | N27: 97627 | O27: =M27*N27 -> 97627
A28: 25 | B28: 44648 | C28: Delhi Sahabad Warehouse SVAN ANALYTICAL INSTRUMENT PVT LTD. | D28: SMO/0011 3081/21-22 | E28: 24-03-2022 27-04-2021 | G28: DOMBILLI MH | H28: 4510395452 | I28: 111391860 | J28: 111391860 | K28: Micro volume Viscometer-OIL APPLICATION | L28: Set | M28: 1 | N28: 375000 | O28: =M28*N28 -> 375000
A29: 26 | B29: 44648 | C29: Delhi Sahabad Warehouse Siemens Ltd-Nashik Works | D29: SMO/0006 | E29: 44637 | G29: DELHI | H29: 4510365470 | I29: 101668585 | J29: EDPM4610 | K29: S101091363 GASKET GISTA SECTION EDPM4610 | L29: Mtr. | M29: 50 | N29: 415 | O29: =M29*N29 -> 20750
A30: 27 | B30: 44648 | C30: Delhi Sahabad Warehouse Spectra Connectronics LLP | D30: SMO/10001 | E30: 44642 | G30: DELHI | H30: 4510927065 | I30: A5E41521351 | J30: 3P_5.8mm | K30: ACC_CONN_HOUSING_FEMALE_3P_5.8mm | L30: Nos | M30: 46 | N30: 10.53 | O30: =M30*N30 -> 484.38
A31: 28 | B31: 44648 | C31: Delhi Sahabad Warehouse Spectra Connectronics LLP | D31: SMO/10001 | E31: 44642 | G31: DELHI | H31: 4508414831 | I31: A5E41521162 | J31: 0.08-0.33mm2_PhBz | K31: ACC_CONN_CONT_FEMALE_0.08-0.33mm2_PhBz | L31: Nos | M31: 48 | N31: 1.17 | O31: =M31*N31 -> 56.16
A32: 29 | B32: 44648 | C32: Delhi Sahabad Warehouse New United Metal & Engineering Work | D32: SMO/10001 | E32: 44642 | G32: DELHI | H32: 4510987455 | I32: A5E46938651 | J32: SN 66355 B30-A | K32: Siemens Name Plate as per SN 66355 B30-A | L32: Nos | M32: 4 | N32: 406 | O32: =M32*N32 -> 1624
A33: 30 | B33: 44648 | C33: Delhi Sahabad Warehouse | D33: SMO/0006 | E33: 44637 | G33: DELHI | I33: 102086056 | J33: 102086056 | K33: HEAT SHRINK TUBE 12.0/6 BLACK | L33: Mtr. | M33: 100 | N33: 8.75 | O33: =M33*N33 -> 875
A34: 31 | B34: 44648 | C34: Delhi Sahabad Warehouse Gala Shrink Fit | D34: SMO/0006 | E34: 44637 | G34: DELHI | H34: 4510385088 | I34: A5E49610997 | J34: A5E49610997 | K34: Heat Shrink Sleeve_30.0/15.0mm Black | L34: Mtr. | M34: 50 | N34: 34 | O34: =M34*N34 -> 1700
A35: 32 | B35: 44648 | C35: Delhi Sahabad Warehouse | D35: SMO/0006 | E35: 44637 | G35: DELHI | H35: 4509771905 | I35: 110408140 | J35: 110408140 | K35: Heat Shrinkable Transperant Tube for 185 SqmmCable | L35: Mtr. | M35: 100 | N35: 40 | O35: =M35*N35 -> 4000
A36: 33 | B36: 44648 | C36: Delhi Sahabad Warehouse JAINSONS INDIA | D36: SMO/0006 0000880/20-21 | E36: 17-03-2022 24-09-20 | G36: NEW DELHI | H36: 4510011036 | I36: 110456652 | J36: 1061000250230 | K36: Heat Shrinkable Transperant Tube 150 Sqmm cable 25/12.5 | L36: Mtr. | M36: 50 | N36: 33 | O36: =M36*N36 -> 1650
A37: 34 | B37: 44648 | C37: Delhi Sahabad Warehouse JAINSONS INDIA | D37: SMO/0006 0000880/20-21 | E37: 17-03-2022 24-09-20 | G37: NEW DELHI | H37: 4510011036 | I37: 110456658 | J37: 110456658 | K37: Heat Shrinkable Transparent tube 35 cabl (12/6) | L37: Mtr. | M37: 100 | N37: 8.75 | O37: =M37*N37 -> 875
A38: 35 | B38: 44648 | C38: Delhi Sahabad Warehouse JAINSONS INDIA | D38: SMO/0006 0000880/20-21 | E38: 17-03-2022 24-09-20 | G38: NEW DELHI | H38: 4510011036 | I38: 110456655 | J38: 110456655 | K38: Heat Shrinkable Transparent tube 50 cabl (14/7 | L38: Mtr. | M38: 100 | N38: 11 | O38: =M38*N38 -> 1100
A39: 36 | B39: 44648 | C39: Delhi Sahabad Warehouse JAINSONS INDIA | D39: SMO/0006 0000880/20-21 | E39: 17-03-2022 24-09-20 | G39: NEW DELHI | H39: 4510011036 | I39: 110408141 | J39: 110408141 | K39: Heat Shrinkable Transperant Tube for 70 Sq.mm Cable HST 18MM Clear | L39: Mtr. | M39: 100 | N39: 19.5 | O39: =M39*N39 -> 1950
A40: 37 | B40: 44648 | C40: Delhi Sahabad Warehouse | D40: SMO/0006 | E40: 44637 | G40: DELHI | I40: B | J40: B | K40: HEP CUBICAL | L40: Box | M40: 2 | N40: 0 | O40: =M40*N40 -> 0
A41: 38 | B41: 44648 | C41: Delhi Sahabad Warehouse Tyco Electronics Middle East FZE | D41: SMO/0009 | E41: 44642 | G41: DELHI | H41: 4200791035 | I41: 109611234 | J41: 3742612236 | K41: Active Speed Sensors suitable for IGBT locos [3-Phase Locos] DSD 1616.73 QHW - F267S 3742612236 | L41: Nos | M41: 101 | N41: 19072.55 | O41: =M41*N41 -> 1926327.5
A42: 39 | B42: 44648 | C42: Delhi Sahabad Warehouse | D42: SMO/0006 | E42: 44637 | G42: DELHI | J42: LF 1010-S/SP36 | K42: LEM Sensor LF 1010-S/SP36 | L42: Nos | M42: 4 | N42: 0 | O42: =M42*N42 -> 0
A43: 40 | B43: 44648 | C43: Delhi Sahabad Warehouse | D43: SMO/0006 | E43: 44637 | G43: DELHI | I43: 110411274 | J43: 45HH1050 M10 | K43: POWERMAT DMC RED INSULATOR 45HH1050 M10 | L43: Nos | M43: 16 | N43: 0 | O43: =M43*N43 -> 0
A44: 41 | B44: 44648 | C44: Delhi Sahabad Warehouse | D44: SMO/0006 | E44: 44637 | G44: DELHI | I44: 110316950 | J44: 72394502 / 45HH1060 (M10 ) | K44: TOO.INS ( Dmc Red Insulator with ms Insert ) 72394502 / 45HH1060 (M10 ) FHH0069 DRDM03 | L44: Nos | M44: 4 | N44: 0 | O44: =M44*N44 -> 0
A45: 42 | B45: 44648 | C45: Delhi Sahabad Warehouse | D45: SMO/0006 | E45: 44637 | G45: DELHI | I45: 110316958 | J45: 42394524 / 14HH680-M6.07F6.07 | K45: TOO.INS ( Dmc Red Spacer -14HH680-M6.07F6.07 ) 42394524 FHH0289DRDOM03 | L45: Nos | M45: 8 | N45: 0 | O45: =M45*N45 -> 0
A46: 43 | B46: 44648 | C46: Delhi Sahabad Warehouse | D46: SMO/0006 | E46: 44637 | G46: DELHI | I46: 100168113 | J46: 5SY6306-7 | K46: 5SY6306-7 \CIRCUIT BREAKER 6KA 3POL | L46: Nos | M46: 2 | N46: 3650 | O46: =M46*N46 -> 7300
A47: 44 | B47: 44648 | C47: Delhi Sahabad Warehouse | D47: SMO/0006 | E47: 44637 | G47: DELHI | I47: 102373683 | J47: 5SY5114-7 | K47: 5SY5114-7 \CIRCUIT BREAKER UC 10KA 1 P | L47: Nos | M47: 1 | N47: 1256 | O47: =M47*N47 -> 1256
A48: 45 | B48: 44648 | C48: Delhi Sahabad Warehouse | D48: SMO/0006 | E48: 44637 | G48: DELHI | I48: 102625238 | J48: 3RV2421-4DA10 | K48: 3RV2421-4DA10 \CIRCUIT-BREAKER SCREW CO | L48: Nos | M48: 1 | N48: 2206 | O48: =M48*N48 -> 2206
A49: 46 | B49: 44648 | C49: Delhi Sahabad Warehouse | D49: SMO/0006 | E49: 44637 | G49: DELHI | I49: 109710326 | J49: 249-117 | K49: Wago- Screwless End Stop 249-117 | L49: Nos | M49: 10 | N49: 5.88 | O49: =M49*N49 -> 58.8
A50: 47 | B50: 44648 | C50: Delhi Sahabad Warehouse | D50: SMO/0006 | E50: 44637 | G50: DELHI | I50: 100185391 | J50: 5SY62037 | K50: CIRCUIT BRACKER 6 KA 5SY62037 | L50: Nos | M50: 1 | N50: 14 | O50: =M50*N50 -> 14
A51: 48 | B51: 44648 | C51: Delhi Sahabad Warehouse | D51: SMO/0006 | E51: 44637 | G51: DELHI | I51: 110408141 | J51: 110408141 | K51: Heat Shrinkable Transperant Tube for 70 Sq.mm Cable HST 18MM Clear | L51: Mtr. | M51: 3 | N51: 19.5 | O51: =M51*N51 -> 58.5
A52: 49 | B52: 44648 | C52: Delhi Sahabad Warehouse | D52: SMO/0006 | E52: 44637 | G52: DELHI | I52: 110456658 | J52: 110456658 | K52: Heat Shrinkable Transparent tube 35 cabl (12/6) | L52: Mtr. | M52: 3 | N52: 0 | O52: =M52*N52 -> 0
A53: 50 | B53: 44648 | C53: Delhi Sahabad Warehouse | D53: SMO/0006 | E53: 44637 | G53: DELHI | H53: 4510011036 | I53: 110408140 | J53: 110408140 | K53: Heat Shrinkable Transperant Tube for 185 SqmmCable | L53: Mtr. | M53: 3 | N53: 40 | O53: =M53*N53 -> 120
A54: 51 | B54: 44648 | C54: Delhi Sahabad Warehouse | D54: SMO/0006 | E54: 44637 | G54: DELHI | I54: 110456653 | J54: 110456653 | K54: Heat Shrinkable Transparent tube 150 mm | L54: Mtr. | M54: 3 | N54: 40 | O54: =M54*N54 -> 120
A55: 52 | B55: 44648 | C55: Delhi Sahabad Warehouse | D55: SMO/0006 | E55: 44637 | G55: DELHI | I55: 110408141 | J55: 110408141 | K55: Heat Shrinkable Transperant Tube for 70 Sq.mm Cable HST 18MM Clear | L55: Mtr. | M55: 3 | N55: 19.5 | O55: =M55*N55 -> 58.5
A56: 53 | B56: 44648 | C56: Delhi Sahabad Warehouse | D56: SMO/0006 | E56: 44637 | G56: DELHI | I56: 110492019 | J56: 2002 - 1491/ 281-311 / 60270122 | K56: WAGO END AND INTERMEDIATE PLATE 2002 - 1491/ 281-311 | L56: Nos | M56: 10 | N56: 4.6 | O56: =M56*N56 -> 46
A57: 54 | B57: 44648 | C57: Delhi Sahabad Warehouse | D57: SMO/0006 | E57: 44637 | G57: DELHI | J57: 280-308 | K57: END & INTERMEDIATE PLATE FOR TERMINAL BLOCK | L57: Nos | M57: 15 | N57: 0 | O57: =M57*N57 -> 0
A58: 55 | B58: 44648 | C58: Delhi Sahabad Warehouse | D58: SMO/0006 | E58: 44637 | G58: DELHI | I58: 100071911 | J58: 5ST3010 | K58: 5ST3010 \AUXILIARY SWITCH 1S1OE 1NO+1NC FOR MCB 5SL, 5SY, 5SP, ON-OFF-SW. 5TL1, RCBO 5SU1, RCD 5SV | L58: Nos | M58: 6 | N58: 448 | O58: =M58*N58 -> 2688
A59: 56 | B59: 44648 | C59: Delhi Sahabad Warehouse | D59: SMO/0006 | E59: 44637 | G59: DELHI | I59: 110317035 | J59: 280-402 | K59: WAGO ADJACENT JUMPER 280-402 | L59: Nos | M59: 30 | N59: 4.27 | O59: =M59*N59 -> 128.1
A60: 57 | B60: 44648 | C60: Delhi Sahabad Warehouse | D60: SMO/0006 | E60: 44637 | G60: DELHI | I60: 110408123 | J60: 110408123 | K60: PVC tape non adhesive ( PVC Tapes 8546 3/4" ) | L60: Mtr. | M60: 5 | N60: 0 | O60: =M60*N60 -> 0
A61: 58 | B61: 44648 | C61: Delhi Sahabad Warehouse | D61: SMO/0006 | E61: 44637 | G61: DELHI | I61: 110408136 | J61: 110408136 | K61: Heat Shrinkable Sleeve (185 Sq.mmCable)dia 30mm HST 30 Black | L61: Mtr. | M61: 3 | N61: 41 | O61: =M61*N61 -> 123
A62: 59 | B62: 44648 | C62: Delhi Sahabad Warehouse | D62: SMO/0006 | E62: 44637 | G62: DELHI | I62: 110408122 | J62: 110408122 | K62: Non-Adhesive Black Insulation Tape XLPE Tape Black 20mm | L62: Mtr. | M62: 30 | N62: 0 | O62: =M62*N62 -> 0
A63: 60 | B63: 44648 | C63: Delhi Sahabad Warehouse | D63: SMO/0006 | E63: 44637 | G63: DELHI | I63: 110408139 | J63: HST 18MM Black | K63: Heat Shrinkable Sleeve(70Sq.mmCable)dia18mm | L63: Mtr. | M63: 3 | N63: 19.5 | O63: =M63*N63 -> 58.5
A64: 61 | B64: 44648 | C64: Delhi Sahabad Warehouse Ebm-Papst India Pvt. Ltd. | D64: SMO/0006 | E64: 44637 | G64: DELHI | H64: 4508872517 | I64: 107146625 | J64: 7210-N | K64: INSTRUMENT COOLING FAN. 7210N-181 /Churning Fan | L64: Nos | M64: 3 | N64: 4954 | O64: =M64*N64 -> 14862
A65: 62 | B65: 44648 | C65: Delhi Sahabad Warehouse | D65: SMO/0006 | E65: 44637 | G65: DELHI | I65: A5E50017538 A5E50017537 | J65: A5E50017538 | K65: SA5E41521162 Cont_Female 0.8-0.33sq_PhBz | L65: Nos | M65: 12 | N65: 10 | O65: =M65*N65 -> 120
A66: 63 | B66: 44648 | C66: Delhi Sahabad Warehouse | D66: SMO/0006 | E66: 44637 | G66: DELHI | I66: A5E50017529 | J66: A5E50017529 | K66: SA5E41521351 Conn_Hsg_FEMALE_3P_5.8mm | L66: Nos | M66: 4 | N66: 20 | O66: =M66*N66 -> 80
A67: 64 | B67: 44648 | C67: Delhi Sahabad Warehouse | D67: SMO/0006 | E67: 44637 | G67: DELHI | I67: 110408100 | J67: 110408100 | K67: Marking Tape 9.0 MM 9mm Tape Max 1Roll=8 mtr | L67: Nos | M67: 1 | N67: 0 | O67: =M67*N67 -> 0
A68: 65 | B68: 44648 | C68: Delhi Sahabad Warehouse | D68: SMO/0006 | E68: 44637 | G68: DELHI | I68: 111418258 | J68: 0234002.MXP | K68: FUSE FOR TERMINAL BOARD LITTLE FUSE 234 SERIES, 3A | L68: Nos | M68: 6 | N68: 28.68 | O68: =M68*N68 -> 172.08
A69: 66 | B69: 44648 | C69: Delhi Sahabad Warehouse | D69: SMO/0006 | E69: 44637 | G69: DELHI | I69: 110294841 | J69: 281-611/864-8391 | K69: FUSE TERMINAL BLOCK WITH HOLDER / FUSE HOLDER 281-611 864-8391 | L69: Nos | M69: 26 | N69: 0 | O69: =M69*N69 -> 0
A70: 67 | B70: 44648 | C70: Delhi Sahabad Warehouse | D70: SMO/0006 | E70: 44637 | G70: DELHI | I70: 109601556 | J70: 1609320050 | K70: CABLE GLAND M32 METAL | L70: Nos | M70: 6 | N70: 0 | O70: =M70*N70 -> 0
A71: 68 | B71: 44648 | C71: Delhi Sahabad Warehouse | D71: SMO/0006 | E71: 44637 | G71: DELHI | I71: C1B41210060405 | J71: 1161320050 | K71: LOCK NUT M32X1.5 METAL | L71: Nos | M71: 6 | N71: 0 | O71: =M71*N71 -> 0
A72: 69 | B72: 44648 | C72: Delhi Sahabad Warehouse | D72: SMO/0006 | E72: 44637 | G72: DELHI | I72: 110315978 | J72: 1161250050 | K72: NUT FOR GLAND M25X1.5 (HUMMEL) 1161250050 | L72: Nos | M72: 4 | N72: 0 | O72: =M72*N72 -> 0
A73: 70 | B73: 44648 | C73: Delhi Sahabad Warehouse | D73: SMO/0006 | E73: 44637 | G73: DELHI | I73: 110315975 | J73: 1609250050 | K73: GLAND FOR M 25 *1.5 (HUMMEL) 1609250050 | L73: Nos | M73: 4 | N73: 0 | O73: =M73*N73 -> 0
A74: 71 | B74: 44648 | C74: Delhi Sahabad Warehouse | D74: SMO/0006 | E74: 44637 | G74: DELHI | I74: 110315977 | J74: 1609120050 | K74: GLAND FOR M 12 *1.5 (HUMMEL) 1609120050 | L74: Nos | M74: 5 | N74: 0 | O74: =M74*N74 -> 0
A75: 72 | B75: 44648 | C75: Delhi Sahabad Warehouse | D75: SMO/0006 | E75: 44637 | G75: DELHI | I75: 110315979 | J75: 1161120050 | K75: NUT FOR GLAND M12X1.5 (HUMMEL) 1161120050 | L75: Nos | M75: 5 | N75: 0 | O75: =M75*N75 -> 0
A76: 73 | B76: 44648 | C76: Delhi Sahabad Warehouse | D76: SMO/0006 | E76: 44637 | G76: DELHI | I76: 110322233 | J76: 54168.200 | K76: CABLE ENRTY FRAME WITH V2A SCREW 54168.200 | L76: Nos | M76: 1 | N76: 1006 | O76: =M76*N76 -> 1006
A77: 74 | B77: 44648 | C77: Delhi Sahabad Warehouse | D77: SMO/0006 | E77: 44637 | G77: DELHI | I77: 110322239 | J77: 42905 | K77: PLUGS FOR MEMBRANES ST7 DIAMETER 7MM 42905 | L77: Nos | M77: 2 | N77: 38 | O77: =M77*N77 -> 76
A78: 75 | B78: 44648 | C78: Delhi Sahabad Warehouse | D78: SMO/0006 | E78: 44637 | G78: DELHI | I78: 110322243 | J78: 42040 | K78: SNAP MOUNTING FRAMES KEL-SNAP 16 , 42040 | L78: Nos | M78: 1 | N78: 405 | O78: =M78*N78 -> 405
A79: 76 | B79: 44648 | C79: Delhi Sahabad Warehouse | D79: SMO/0006 | E79: 44637 | G79: DELHI | I79: 110322235 | J79: 41205 | K79: GROMMETS SMALL SINGLE KT 5 CLAMPING | L79: Nos | M79: 2 | N79: 69 | O79: =M79*N79 -> 138
A80: 77 | B80: 44648 | C80: Delhi Sahabad Warehouse | D80: SMO/0006 | E80: 44637 | G80: DELHI | I80: 110322239 | J80: 41207 | K80: GROMMETS SMALL SINGLE KT 7 CLAMPING 41207 | L80: Nos | M80: 6 | N80: 69 | O80: =M80*N80 -> 414
A81: 78 | B81: 44648 | C81: Delhi Sahabad Warehouse | D81: SMO/0006 | E81: 44637 | G81: DELHI | I81: 110315212 | J81: 110315212 | K81: Ferrule Sleeve 2.2 mm | L81: Mtr. | M81: 100 | N81: 1.5 | O81: =M81*N81 -> 150
A82: 79 | B82: 44648 | C82: Delhi Sahabad Warehouse | D82: SMO/0006 | E82: 44637 | G82: DELHI | I82: 110315349 | J82: 110315349 | K82: Feerule Sleeve 3.5 mm (PVC WHITE TUBE 3.5) | L82: Mtr. | M82: 20 | N82: 2.65 | O82: =M82*N82 -> 53
A83: 80 | B83: 44648 | C83: Delhi Sahabad Warehouse | D83: SMO/0006 | E83: 44637 | G83: DELHI | I83: 110315347 | J83: 110315347 | K83: Feerule Sleeve 3.0 mm | L83: Mtr. | M83: 20 | N83: 0 | O83: =M83*N83 -> 0
A84: 81 | B84: 44648 | C84: Delhi Sahabad Warehouse | D84: SMO/0006 | E84: 44637 | G84: DELHI | I84: 110315376 | J84: 110315376 | K84: Cable Tie 8 inch | L84: Nos | M84: 1000 | N84: 1.33 | O84: =M84*N84 -> 1330
A85: 82 | B85: 44648 | C85: Delhi Sahabad Warehouse | D85: SMO/0006 | E85: 44637 | G85: DELHI | I85: 110408152 | J85: 110408152 | K85: Cable Tie 12 inch, Black colour PLT3S-M0 (292X4.8MM) 1 packet-1000 pcs | L85: Nos | M85: 1000 | N85: 2.65 | O85: =M85*N85 -> 2650
A86: 83 | B86: 44648 | C86: Delhi Sahabad Warehouse | D86: SMO/0006 | E86: 44637 | G86: DELHI | I86: 110315371 | J86: 110315371 | K86: Cable Tie 6 inch Hellermann | L86: Nos | M86: 1000 | N86: 0.82 | O86: =M86*N86 -> 820
A87: 84 | B87: 44648 | C87: Delhi Sahabad Warehouse | D87: SMO/0006 | E87: 44637 | G87: DELHI | K87: FILTER RESISTER | L87: Nos | M87: 3 | N87: 0 | O87: =M87*N87 -> 0
A88: 85 | B88: 44648 | C88: Delhi Sahabad Warehouse | D88: SMO/0006 | E88: 44637 | G88: DELHI | I88: 109492247 | J88: 20772083003 | K88: HARTING ETHERNET SWITCH Ha-VIS eCon 4080-B3 20772083003 | L88: Nos | M88: 1 | N88: 44921 | O88: =M88*N88 -> 44921
A89: 86 | B89: 44648 | C89: Delhi Sahabad Warehouse | D89: SMO/0006 | E89: 44637 | G89: DELHI | I89: 107180447 | J89: 107180447 | K89: EARTHING ROUNDED 1'' for Trafo Enclosure STICKER 3M-7860-POLYSTER | L89: Nos | M89: 20 | N89: 0 | O89: =M89*N89 -> 0
A90: 87 | B90: 44648 | C90: Delhi Sahabad Warehouse | D90: SMO/0006 | E90: 44637 | G90: DELHI | I90: 110408156 | J90: 110408156 | K90: Danger labels(Caution) 3M-7860-POLYSTER | L90: Nos | M90: 4 | N90: 0 | O90: =M90*N90 -> 0
A91: 88 | B91: 44648 | C91: Delhi Sahabad Warehouse | D91: SMO/0006 | E91: 44637 | G91: DELHI | I91: 109710327 | J91: 280-621 | K91: Wago- 4 Conductor through treminal block 280-621 | L91: Nos | M91: 60 | N91: 25.31 | O91: =M91*N91 -> 1518.6
A92: 89 | B92: 44648 | C92: Delhi Sahabad Warehouse | D92: SMO/0006 | E92: 44637 | G92: DELHI | I92: A5E35676870 | J92: ELRM44V-10 | K92: ELR TYPE: ELRM44V-10 ( EARTH LEAKAGE RELAY) | L92: Nos | M92: 2 | N92: 0 | O92: =M92*N92 -> 0
A93: 90 | B93: 44648 | C93: Delhi Sahabad Warehouse | D93: SMO/0006 | E93: 44637 | G93: DELHI | I93: 100754372 | J93: 138238151 | K93: TYPE - BZCT120 ( 120Ø) 138238151 SA5E35676842 | L93: Nos | M93: 2 | N93: 0 | O93: =M93*N93 -> 0
A94: 91 | B94: 44648 | C94: Delhi Sahabad Warehouse | D94: SMO/0006 | E94: 44637 | G94: DELHI | K94: BUSING 800 AMP | L94: Nos | M94: 6 | N94: 1141 | O94: =M94*N94 -> 6846
A95: 92 | B95: 44648 | C95: Delhi Sahabad Warehouse | D95: SMO/0006 | E95: 44637 | G95: DELHI | K95: BUSING 650 AMP | L95: Nos | M95: 6 | N95: 953 | O95: =M95*N95 -> 5718
A96: 93 | B96: 44648 | C96: Delhi Sahabad Warehouse | D96: SMO/0006 | E96: 44637 | G96: DELHI | K96: LUG 70/10 | L96: Nos | M96: 27 | N96: 62.25 | O96: =M96*N96 -> 1680.75
A97: 94 | B97: 44648 | C97: Delhi Sahabad Warehouse | D97: SMO/0006 | E97: 44637 | G97: DELHI | K97: LUG 150/10 | L97: Nos | M97: 12 | N97: 98.4 | O97: =M97*N97 -> 1180.8
A98: 95 | B98: 44648 | C98: Delhi Sahabad Warehouse | D98: SMO/0006 | E98: 44637 | G98: DELHI | K98: LUG 120/10 | L98: Nos | M98: 6 | N98: 72.8 | O98: =M98*N98 -> 436.8
A99: 96 | B99: 44648 | C99: Delhi Sahabad Warehouse | D99: SMO/0006 | E99: 44637 | G99: DELHI | K99: LUG 120/12 | L99: Nos | M99: 6 | N99: 78.4 | O99: =M99*N99 -> 470.4
A100: 97 | B100: 44648 | C100: Delhi Sahabad Warehouse | D100: SMO/0006 | E100: 44637 | G100: DELHI | I100: 112308582/ 110522356 | J100: CCLW 185 X M10 | K100: CABLE LUGS 185SQ.MM X M10 | L100: Nos | M100: 4 | N100: 218.95 | O100: =M100*N100 -> 875.8
...

Sheet Out-ward Register
F1: Total Disp Qty. | G1: =Summery!H2-'Out-ward Register'!F2 -> 0 | U1: Dispatch Value | V1: Receipt Value | W1: Balance
A2: Material Out-ward register As on 31-July-25 | F2: =SUM(F4:F1048576) -> 604899.94 | U2: =SUBTOTAL(9,U4:U3176) -> 2.3616877e+08 | V2: ='In-ward Register'!O2 -> 2861166.8 | W2: =V2-U2 -> -2.333076e+08
A3: Sr. No. | B3: SAP Code | C3: Part Code | D3: Description | E3: UOM | F3: Dispatched Qty | G3: Customer Invoice / Challan No | H3: Date | I3: Dispatch Date | J3: Customer Name | K3: Location | L3: Order By | M3: Docket No | N3: Transporter / Courier Name | O3: Project | P3: Customer P.O. No | Q3: WBS | R3: Remark if Any | S3: Price As per P.o. | T3: Currency | U3: Dispatch Value
A4: 1 | B4: 109447744 | C4: 803203 | D4: 803203 LION-DO8-24V-110V-LUE LION I/O MODULE DIGITAL OUTPUTS | E4: Nos | F4: 129 | G4: UP/DC/FY22/00018 | H4: 44666 | I4: 44666 | J4: Siemens Ltd- Nasik Work | K4: Nasik | L4: Mr. Arka Dey | M4: 226168328 | N4: SPOTON LOGISTIC Pvt. Ltd. | O4: WAG9/6k | P4: 70201134101308 | Q4: 62OP 30878 | R4: Short supply material dispatched now | S4: 19040 | T4: INR | U4: =S4*F4 -> 2456160
A5: 2 | B5: 109447749 | C5: 803401 | D5: LION Erweiterungsmodul, 4 analoge Ausg. 803401 | E5: Nos | F5: 36 | G5: UP/DC/FY22/00018 | H5: 44666 | I5: 44666 | J5: Siemens Ltd- Nasik Work | K5: Nasik | L5: Mr. Arka Dey | M5: 226168328 | N5: SPOTON LOGISTIC Pvt. Ltd. | O5: WAG9/6k | P5: 70201134101308 | Q5: 62OP 30878 | R5: Short supply material dispatched now | S5: 22525 | T5: INR | U5: =S5*F5 -> 810900
A6: 3 | B6: 109447743 | C6: 803201 | D6: LION Erweiterungsmodul,8 Wechslerkanaele 803201 | E6: Nos | F6: 89 | G6: UP/DC/FY22/00018 | H6: 44666 | I6: 44666 | J6: Siemens Ltd- Nasik Work | K6: Nasik | L6: Mr. Arka Dey | M6: 226168328 | N6: SPOTON LOGISTIC Pvt. Ltd. | O6: WAG9/6k | P6: 70201134101308 | Q6: 62OP 30878 | R6: Short supply material dispatched now | S6: 18615 | T6: INR | U6: =S6*F6 -> 1656735
A7: 4 | B7: 109447737 | C7: 800103 | D7: LION POWER SUPPLY 36 W DC24V/110V 800103 | E7: Nos | F7: 89 | G7: UP/DC/FY22/00018 | H7: 44666 | I7: 44666 | J7: Siemens Ltd- Nasik Work | K7: Nasik | L7: Mr. Arka Dey | M7: 226168328 | N7: SPOTON LOGISTIC Pvt. Ltd. | O7: WAG9/6k | P7: 70201134101308 | Q7: 62OP 30878 | R7: Short supply material dispatched now | S7: 18020 | T7: INR | U7: =S7*F7 -> 1603780
A8: 5 | B8: 109447745 | C8: 803301 | D8: LION-AI4-U-LUE (Analog Input, 4 channels 803301 | E8: Nos | F8: 35 | G8: UP/DC/FY22/00018 | H8: 44666 | I8: 44666 | J8: Siemens Ltd- Nasik Work | K8: Nasik | L8: Mr. Arka Dey | M8: 226168328 | N8: SPOTON LOGISTIC Pvt. Ltd. | O8: WAG9/6k | P8: 70201134101308 | Q8: 62OP 30878 | R8: Short supply material dispatched now | S8: 26265 | T8: INR | U8: =S8*F8 -> 919275
A9: 6 | B9: 109447740 | C9: 803001 | D9: LION-Busskoppler-MVB-LUE 803001 | E9: Nos | F9: 91 | G9: UP/DC/FY22/00018 | H9: 44666 | I9: 44666 | J9: Siemens Ltd- Nasik Work | K9: Nasik | L9: Mr. Arka Dey | M9: 226168328 | N9: SPOTON LOGISTIC Pvt. Ltd. | O9: WAG9/6k | P9: 70201134101308 | Q9: 62OP 30878 | R9: Short supply material dispatched now | S9: 40800 | T9: INR | U9: =S9*F9 -> 3712800
A10: 7 | B10: 109492197 | C10: 61030000067 | D10: CRIMP FLANGE FOR D-SUB HARTING (S102117360) FORMVB CONNECTOR 61030000067 | E10: Nos | F10: 92 | G10: UP/DC/FY22/00022 | H10: 44672 | I10: 44674 | J10: TEKNOCRATS CONTROL PVT. LTD. | K10: NASIK | L10: Mr. Arka Dey | M10: 50815918834 | N10: BLUE DART SARFACE | O10: WAG9/6k | P10: 70201134101308 | Q10: 62OP 30878 | R10: Short supply material dispatched now | S10: 66.92 | T10: INR | U10: =S10*F10 -> 6156.64
A11: 8 | B11: 107146625 | C11: 4318N/2N | D11: Ebm-Papst Churning Fan-Model No- 4318N/2N | E11: Nos | F11: 69 | G11: UP/DC/FY22/00022 | H11: 44672 | I11: 44674 | J11: TEKNOCRATS CONTROL PVT. LTD. | K11: NASIK | L11: Mr. Arka Dey | M11: 50815918834 | N11: BLUE DART SARFACE | O11: WAG9/6k | P11: 70201134101308 | Q11: 62OP 30878 | R11: Short supply material dispatched now | S11: 1516 | T11: INR | U11: =S11*F11 -> 104604
A12: 9 | B12: 109612594 | C12: 279-316 | D12: END AND INTERMEDIATE PLATE 279-316 | E12: Nos | F12: 200 | G12: UP/DC/FY22/00022 | H12: 44672 | I12: 44674 | J12: TEKNOCRATS CONTROL PVT. LTD. | K12: NASIK | L12: Mr. Arka Dey | M12: 50815918834 | N12: BLUE DART SARFACE | O12: WAG9/6k | P12: 70201134101308 | Q12: 62OP 30878 | R12: Short supply material dispatched now | S12: 8.22 | T12: INR | U12: =S12*F12 -> 1644
A13: 10 | B13: 111418258 | C13: 0234002.MXP | D13: FUSE FOR TERMINAL BOARD LITTLE FUSE 234 SERIES, 3A | E13: Nos | F13: 36 | G13: UP/DC/FY22/00022 | H13: 44672 | I13: 44674 | J13: TEKNOCRATS CONTROL PVT. LTD | K13: NASIK | L13: Mr. Arka Dey | M13: 50815918834 | N13: BLUE DART SARFACE | O13: WAG9/6k | P13: 70201134101308 | Q13: 62OP 30878 | R13: Short supply material dispatched now | S13: 28.68 | T13: INR | U13: =S13*F13 -> 1032.48
A14: 11 | B14: 109492181 | C14: 09670003476 | D14: HARTING D SUB -S- FEMALE-18-22 CRIMP CONDUCT P.N. 09670003476 | E14: Nos | F14: 460 | G14: UP/DC/FY22/00022 | H14: 44672 | I14: 44674 | J14: TEKNOCRATS CONTROL PVT. LTD. | K14: NASIK | L14: Mr. Arka Dey | M14: 50815918834 | N14: BLUE DART SARFACE | O14: WAG9/6k | P14: 70201134101308 | Q14: 62OP 30878 | R14: Short supply material dispatched now | S14: 18.35 | T14: INR | U14: =S14*F14 -> 8441
A15: 12 | B15: 109492194 | C15: 61030012010 | D15: HARTING INDU COM 9P 1T ENTRY HEX SCREW 4-40 P.N. 61030012010 | E15: Nos | F15: 30 | G15: UP/DC/FY22/00022 | H15: 44672 | I15: 44674 | J15: TEKNOCRATS CONTROL PVT. LTD. | K15: NASIK | L15: Mr. Arka Dey | M15: 50815918834 | N15: BLUE DART SARFACE | O15: WAG9/6k | P15: 70201134101308 | Q15: 62OP 30878 | R15: Short supply material dispatched now | S15: 234.9 | T15: INR | U15: =S15*F15 -> 7047
A16: 13 | B16: 109492196 | C16: 61030000054 | D16: Harting Inducom Crimp ferrule 9,5- 10,5mm 61030000054 | E16: Nos | F16: 92 | G16: UP/DC/FY22/00022 | H16: 44672 | I16: 44674 | J16: TEKNOCRATS CONTROL PVT. LTD. | K16: NASIK | L16: Mr. Arka Dey | M16: 50815918834 | N16: BLUE DART SARFACE | O16: WAG9/6k | P16: 70201134101308 | Q16: 62OP 30878 | R16: Short supply material dispatched now | S16: 21.36 | T16: INR | U16: =S16*F16 -> 1965.12
A17: 14 | B17: 109609637 | C17: 09670008476 | D17: M12 A TYPE FEMALE CONNECTER CRIMP CONTACT PIN PN 09670008476 | E17: Nos | F17: 57 | G17: UP/DC/FY22/00022 | H17: 44672 | I17: 44674 | J17: TEKNOCRATS CONTROL PVT. LTD. | K17: NASIK | L17: Mr. Arka Dey | M17: 50815918834 | N17: BLUE DART SARFACE | O17: WAG9/6k | P17: 70201134101308 | Q17: 62OP 30878 | R17: Short supply material dispatched now | S17: 18.62 | T17: INR | U17: =S17*F17 -> 1061.34
A18: 15 | B18: 111448661 | C18: 1802CP1043 | D18: Plug for Looming bar | E18: Nos | F18: 300 | G18: UP/DC/FY22/00022 | H18: 44672 | I18: 44674 | J18: TEKNOCRATS CONTROL PVT. LTD. | K18: NASIK | L18: Mr. Arka Dey | M18: 50815918834 | N18: BLUE DART SARFACE | O18: WAG9/6k | P18: 70201134101308 | Q18: 62OP 30878 | R18: Short supply material dispatched now | S18: 48.6 | T18: INR | U18: =S18*F18 -> 14580
A19: 16 | B19: 110317066 | C19: 110317066 | D19: SCREW STAR M4 X 15 V4D 9039 | E19: Nos | F19: 640 | G19: UP/DC/FY22/00022 | H19: 44672 | I19: 44674 | J19: TEKNOCRATS CONTROL PVT. LTD. | K19: NASIK | L19: Mr. Arka Dey | M19: 50815918834 | N19: BLUE DART SARFACE | O19: WAG9/6k | P19: 70201134101308 | Q19: 62OP 30878 | R19: Short supply material dispatched now | S19: 1.15 | T19: INR | U19: =S19*F19 -> 736
A20: 17 | B20: 111448667 | C20: 221 | D20: SIKAFLEX 221 | E20: Nos | F20: 48 | G20: UP/DC/FY22/00022 | H20: 44672 | I20: 44674 | J20: TEKNOCRATS CONTROL PVT. LTD | K20: NASIK | L20: Mr. Arka Dey | M20: 50815918834 | N20: BLUE DART SARFACE | O20: WAG9/6k | P20: 70201134101308 | Q20: 62OP 30878 | R20: Short supply material dispatched now | S20: 475.2 | T20: INR | U20: =S20*F20 -> 22809.6
A21: 18 | B21: 109710327 | C21: 280-621 | D21: Wago- 4 Conductor through treminal block 280-621 | E21: Nos | F21: 1100 | G21: UP/DC/FY22/00022 | H21: 44672 | I21: 44674 | J21: TEKNOCRATS CONTROL PVT. LTD. | K21: NASIK | L21: Mr. Arka Dey | M21: 50815918834 | N21: BLUE DART SARFACE | O21: WAG9/6k | P21: 70201134101308 | Q21: 62OP 30878 | R21: Short supply material dispatched now | S21: 25.31 | T21: INR | U21: =S21*F21 -> 27841
A22: 19 | B22: 109611234 | C22: 3742612236 | D22: Active Speed Sensors suitable for IGBT locos [3-Phase Locos] DSD 1616.73 QHW - F267S 3742612236 | E22: Nos | F22: 1 | G22: UP/DC/FY22/00024 | H22: 44672 | I22: 44674 | J22: Siemens Ltd- Nasik Work | K22: Nasik | L22: Mr. Arka Dey | M22: 50815918845 | N22: BLUE DART SARFACE | O22: WAG9/6k | P22: - | Q22: - | R22: For Lab Testing | S22: 19072.55 | T22: INR | U22: =S22*F22 -> 19072.55
A23: 20 | B23: 109447742 | C23: 803102 | D23: 803102 LION-DI16-72V-110V-LUE LION I/O MODULE DIGITAL OUTPUTS | E23: Nos | F23: 1 | G23: UP/DC/FY22/00035 | H23: 44682 | I23: 44682 | J23: DLW- DDU SHED MUGAL SARAI | K23: VARANASI | L23: Mr. Arka Dey | M23: BY HAND | N23: Mr. Saurabh Mishra | O23: 6000HP: CLW PO 6k49x | P23: 20212095100413 | Q23: 62OP-30878.P.89 | R23: Material for BLW Commissioning against 49x CLW | S23: 15118.36 | T23: INR | U23: =S23*F23 -> 15118.36
A24: 21 | B24: 109492180 | C24: 09670094701 | D24: D- SUB CRIMP 9-POLE FEMALE ASSEMBLY '09670094701 | E24: Nos | F24: 45 | G24: UP/DC/FY22/00037 | H24: 44683 | I24: 44683 | J24: Siemens / Guest house | K24: Paschim Burdwan WB | L24: Mr. Arka Dey | M24: BY HAND | N24: Mr. Saurabh Mishra | O24: 6000HP: CLW PO 6k49x | P24: 70201134101308 | Q24: 62OP 30878 | R24: Short material supply to CLW | S24: 32.22 | T24: INR | U24: =S24*F24 -> 1449.9
A25: 22 | B25: 109492212 | C25: 09670008576 | D25: D-Sub, MA AWG 20-24 crimp cont 09670008576 | E25: Nos | F25: 139 | G25: UP/DC/FY22/00037 | H25: 44683 | I25: 44683 | J25: Siemens / Guest house | K25: Paschim Burdwan WB | L25: Mr. Arka Dey | M25: BY HAND | N25: Mr. Saurabh Mishra | O25: 6000HP: CLW PO 6k49x | P25: 70201134101308 | Q25: 62OP 30878 | R25: Short material supply to CLW | S25: 11.26 | T25: INR | U25: =S25*F25 -> 1565.14
A26: 23 | B26: 109492212 | C26: 09670008576 | D26: D-Sub, MA AWG 20-24 crimp cont 09670008576 | E26: Nos | F26: 210 | G26: UP/DC/FY22/00037 | H26: 44683 | I26: 44683 | J26: Siemens / Guest house | K26: Paschim Burdwan WB | L26: Mr. Arka Dey | M26: BY HAND | N26: Mr. Saurabh Mishra | O26: 6000HP: CLW PO 6k49x | P26: 70201134101308 | Q26: 62OP 30878 | R26: Short material supply to CLW | S26: 11.26 | T26: INR | U26: =S26*F26 -> 2364.6
A27: 24 | B27: 109492198 | C27: 21038811405 | D27: M12 CRIMP SLIM DESIGN 4 POL D CODED M '21038811405 | E27: Nos | F27: 170 | G27: UP/DC/FY22/00037 | H27: 44683 | I27: 44683 | J27: Siemens / Guest house | K27: Paschim Burdwan WB | L27: Mr. Arka Dey | M27: BY HAND | N27: Mr. Saurabh Mishra | O27: 6000HP: CLW PO 6k49x | P27: 70201134101308 | Q27: 62OP 30878 | R27: Short material supply to CLW | S27: 1139.38 | T27: INR | U27: =S27*F27 -> 193694.6
A28: 25 | B28: 109609632 | C28: 09150043013 | D28: HAN 4 QUINTAX STIFT, 3-9.5MM 09150043013 | E28: Nos | F28: 12 | G28: UP/DC/FY22/00040 | H28: 44685 | I28: 44685 | J28: Siemens / Guest house | K28: Paschim Burdwan WB | L28: Mr. Arka Dey | M28: BY HAND | N28: Mr. Saurabh Mishra | O28: 6000HP: CLW PO 6k49x | P28: 70201134101308 | Q28: 62OP 30878 | R28: Short material supply to CLW | S28: 100.06 | T28: INR | U28: =S28*F28 -> 1200.72
A29: 26 | B29: 109492181 | C29: 09670003476 | D29: HARTING D SUB -S- FEMALE-18-22 CRIMP CONDUCT P.N. 09670003476 | E29: Nos | F29: 50 | G29: UP/DC/FY22/00040 | H29: 44685 | I29: 44685 | J29: Siemens / Guest house | K29: Paschim Burdwan WB | L29: Mr. Arka Dey | M29: BY HAND | N29: Mr. Saurabh Mishra | O29: 6000HP: CLW PO 6k49x | P29: 70201134101308 | Q29: 62OP 30878 | R29: Short material supply to CLW | S29: 18.35 | T29: INR | U29: =S29*F29 -> 917.5
A30: 27 | B30: 109609630 | C30: 09150006123 | D30: HARTING R15-STI-C (AU) 0.5-AWG20 09150006123 | E30: Nos | F30: 48 | G30: UP/DC/FY22/00040 | H30: 44685 | I30: 44685 | J30: Siemens / Guest house | K30: Paschim Burdwan WB | L30: Mr. Arka Dey | M30: BY HAND | N30: Mr. Saurabh Mishra | O30: 6000HP: CLW PO 6k49x | P30: 70201134101308 | Q30: 62OP 30878 | R30: Short material supply to CLW | S30: 19.26 | T30: INR | U30: =S30*F30 -> 924.48
A31: 28 | B31: 109612592 | C31: 280-941/281-492 | D31: WAGO COMPONENT TERMINAL BLOCK 280-941/281-492 | E31: Nos | F31: 7 | G31: UP/DC/FY22/00042 | H31: 44686 | I31: 44688 | J31: SIEMENS LTD MIBILITY | K31: GURGAON | L31: MR. Ashish Mishra | M31: 40761719364 | N31: BLUE DART | O31: WAG-9/9K UPGRADE | R31: For TKD 9K Loco upgrade | S31: 136.2 | T31: INR | U31: =S31*F31 -> 953.4
A32: 29 | B32: 107123964 | C32: FAHZ5-P3-024/028/007 | D32: SPEED SENSOR NORIS | E32: Nos | F32: 70 | G32: UP/DC/FY22/00046 | H32: 44690 | I32: 44694 | J32: Siemens ltd Jodhpur Site | K32: Bhagat Ki kothi Jodhpur | L32: Mr. Arka Dey | M32: 223951853 | N32: Spoton | O32: DE loco AMC | P32: - | Q32: 62OP-30781.P.02 | R32: Faulty Batch Replacement from Noris And Transport and Packaging cost to be Debits CS | S32: 12996 | T32: INR | U32: =S32*F32 -> 909720
A33: 30 | B33: 107182194 | C33: 107182194 | D33: MS Louvers for HLC | E33: Nos | F33: 8 | G33: UP/DC/FY22/00053 | H33: 44694 | I33: 44694 | J33: ELECTRIC LOCO SHED LALAGUDA | K33: SECUNDERABAD | L33: MR. Akash Goyal | M33: 223951852 | N33: Spoton | O33: HLC Project | P33: - | Q33: 62303002 | R33: This material free supply to customer for HLC Project | S33: 2850 | T33: INR | U33: =S33*F33 -> 22800
A34: 31 | C34: CAB-ETH-M12-M12-5M | D34: COMMUNICATION CABLE CAB-ETH-M12-M12-5M | E34: Nos | F34: 15 | G34: UP/DC/FY22/00054 | H34: 44694 | I34: 44694 | J34: Siemens / Guest house | K34: Paschim Burdwan WB | L34: Mr. Arka Dey | M34: 223951851 | N34: Spoton | O34: 6000HP: CLW PO 6k49x | P34: 70201134101308 | Q34: 62OP 30878 | R34: Short material supply to CLW | S34: 1000 | T34: INR | U34: =S34*F34 -> 15000
A35: 32 | C35: POWER SUPPLY CABLE FOR RAMMLOT DEVICE | D35: POWER SUPPLY CABLE FOR RAMMLOT DEVICE | E35: Nos | F35: 1 | G35: UP/DC/FY22/00054 | H35: 44694 | I35: 44694 | J35: Siemens / Guest house | K35: Paschim Burdwan WB | L35: Mr. Arka Dey | M35: 223951851 | N35: Spoton | O35: 6000HP: CLW PO 6k49x | P35: 70201134101308 | Q35: 62OP 30878 | R35: Short material supply to CLW | S35: 1000 | T35: INR | U35: =S35*F35 -> 1000
A36: 33 | B36: 107157518 | C36: 107157518 | D36: REMMLOT DEVICE | E36: Nos | F36: 1 | G36: UP/DC/FY22/00054 | H36: 44694 | I36: 44694 | J36: Siemens / Guest house | K36: Paschim Burdwan WB | L36: Mr. Arka Dey | M36: 223951851 | N36: Spoton | O36: 6000HP: CLW PO 6k49x | P36: 70201134101308 | Q36: 62OP 30878 | R36: Short material supply to CLW | S36: 160800 | T36: INR | U36: =S36*F36 -> 160800
A37: 34 | B37: 107157518 | C37: 107157518 | D37: REMMLOT DEVICE | E37: Nos | F37: 3 | G37: UP/DC/FY22/00054 | H37: 44694 | I37: 44694 | J37: Siemens / Guest house | K37: Paschim Burdwan WB | L37: Mr. Arka Dey | M37: 223951851 | N37: Spoton | O37: 6000HP: CLW PO 6k49x | P37: 70201134101308 | Q37: 62OP 30878 | R37: Short material supply to CLW | S37: 160800 | T37: INR | U37: =S37*F37 -> 482400
A38: 35 | C38: PMU 22 ABB | D38: CRASH WORTHY MEMORY MODULE PMU22ABB U-BETR- 5VDC SR NO 180084164 , 180084167 | E38: Nos | F38: 2 | G38: UP/DC/FY22/00057 | H38: 44700 | I38: 44700 | J38: Siemens Ltd. - RSLM | K38: Gurgaon | L38: Mr. Ashok Tripathy | M38: 215973540 | N38: Spoton/Delhivery | O38: - | P38: - | Q38: - | R38: This is a damage (Faulty) material | S38: 5000 | T38: INR | U38: =S38*F38 -> 10000
A39: 36 | B39: 109492197 | C39: 61030000067 | D39: CRIMP FLANGE FOR D-SUB HARTING (S102117360) FORMVB CONNECTOR 61030000067 | E39: Nos | F39: 40 | G39: UP/DC/FY22/00058 | H39: 44700 | I39: 44700 | J39: TEKNOCRATS CONTROL PVT. LTD. | K39: NASIK | L39: Mr. Tushar Narkhade | M39: 215973541 | N39: Spoton/Delhivery | O39: WAG9/6k | P39: 70201134101308 | Q39: 62OP 30878 | R39: Short supply material dispatched now | S39: 66.92 | T39: INR | U39: =S39*F39 -> 2676.8
A40: 37 | B40: 109492180 | C40: 09670094701 | D40: D- SUB CRIMP 9-POLE FEMALE ASSEMBLY '09670094701 | E40: Nos | F40: 70 | G40: UP/DC/FY22/00058 | H40: 44700 | I40: 44700 | J40: Technocrats' Control Systems (India) Pvt. Ltd. | K40: NASIK | L40: Mr. Tushar Narkhade | M40: 215973541 | N40: Spoton/Delhivery | O40: 6000HP: CLW PO 6k49x | P40: 70201134101308 | Q40: 62OP 30878 | R40: Short supply material dispatched now | S40: 32.22 | T40: INR | U40: =S40*F40 -> 2255.4
A41: 38 | B41: 109492196 | C41: 61030000054 | D41: Harting Inducom Crimp ferrule 9,5- 10,5mm 61030000054 | E41: Nos | F41: 95 | G41: UP/DC/FY22/00058 | H41: 44700 | I41: 44700 | J41: TEKNOCRATS CONTROL PVT. LTD. | K41: NASIK | L41: Mr. Tushar Narkhade | M41: 215973541 | N41: Spoton/Delhivery | O41: WAG9/6k | P41: 70201134101308 | Q41: 62OP 30878 | R41: Short supply material dispatched now | S41: 21.36 | T41: INR | U41: =S41*F41 -> 2029.2
A42: 39 | B42: 109492196 | C42: 61030000054 | D42: Harting Inducom Crimp ferrule 9,5- 10,5mm 61030000054 | E42: Nos | F42: 25 | G42: UP/DC/FY22/00058 | H42: 44700 | I42: 44700 | J42: TEKNOCRATS CONTROL PVT. LTD. | K42: NASIK | L42: Mr. Tushar Narkhade | M42: 215973541 | N42: Spoton/Delhivery | O42: WAG9/6k | P42: 70201134101308 | Q42: 62OP 30878 | R42: Short supply material dispatched now | S42: 21.36 | T42: INR | U42: =S42*F42 -> 534
A43: 40 | B43: 109609637 | C43: 09670008476 | D43: M12 A TYPE FEMALE CONNECTER CRIMP CONTACT PIN PN 09670008476 | E43: Nos | F43: 80 | G43: UP/DC/FY22/00058 | H43: 44700 | I43: 44700 | J43: TEKNOCRATS CONTROL PVT. LTD. | K43: NASIK | L43: Mr. Tushar Narkhade | M43: 215973541 | N43: Spoton/Delhivery | O43: WAG9/6k | P43: 70201134101308 | Q43: 62OP 30878 | R43: Short supply material dispatched now | S43: 18.62 | T43: INR | U43: =S43*F43 -> 1489.6
A44: 41 | B44: 109492221 | C44: 21038212505 | D44: M12 SLIM FEMALE CRIMP 4/5 POL A COD 21038212505 | E44: Nos | F44: 9 | G44: UP/DC/FY22/00058 | H44: 44700 | I44: 44700 | J44: TEKNOCRATS CONTROL PVT. LTD. | K44: NASIK | L44: Mr. Tushar Narkhade | M44: 215973541 | N44: Spoton/Delhivery | O44: WAG9/6k | P44: 70201134101308 | Q44: 62OP 30878 | R44: Short supply material dispatched now | S44: 939.33 | T44: INR | U44: =S44*F44 -> 8453.97
A45: 42 | B45: 109492221 | C45: 21038212505 | D45: M12 SLIM FEMALE CRIMP 4/5 POL A COD 21038212505 | E45: Nos | F45: 11 | G45: UP/DC/FY22/00058 | H45: 44700 | I45: 44700 | J45: TEKNOCRATS CONTROL PVT. LTD. | K45: NASIK | L45: Mr. Tushar Narkhade | M45: 215973541 | N45: Spoton/Delhivery | O45: WAG9/6k | P45: 70201134101308 | Q45: 62OP 30878 | R45: Short supply material dispatched now | S45: 992.78 | T45: INR | U45: =S45*F45 -> 10920.58
A46: 43 | B46: 109492176 | C46: 45953050 | D46: MVB CABLE BL-02 X S (ST) CHX 2 X 2 X 0.5 MM DBN 459530 | E46: Mtr. | F46: 30 | G46: UP/DC/FY22/00058 | H46: 44700 | I46: 44700 | J46: TEKNOCRATS CONTROL PVT. LTD. | K46: NASIK | L46: Mr. Tushar Narkhade | M46: 215973541 | N46: Spoton/Delhivery | O46: WAG9/6k | P46: 70201134101308 | Q46: 62OP 30878 | R46: Short supply material dispatched now | S46: 191.98 | T46: INR | U46: =S46*F46 -> 5759.4
A47: 44 | B47: 112172545 | C47: 112172545 | D47: COUNTER SUNK FLAT HEAD SCREW IS: 1365- M4 | E47: Nos | F47: 36 | G47: UP/DC/FY22/00063 | H47: 44705 | I47: 44705 | J47: DDU Shed Mugal Sarai | K47: Varanasi | L47: Mr. Arka Dey | M47: By Hand | N47: By Hand Mr. Saurabh Mishra | O47: 6000HP: CLW PO 6k49x | P47: 20212095100413 | Q47: 62OP-30878.P.89 | R47: Material for BLW Commissioning against 49x CLW | S47: 8.5 | T47: INR | U47: =S47*F47 -> 306
A48: 45 | B48: 112172546 | C48: 112172546 | D48: COUNTER SUNK FLAT HEAD SCREW IS: 1365- M5 | E48: Nos | F48: 24 | G48: UP/DC/FY22/00063 | H48: 44705 | I48: 44705 | J48: DDU Shed Mugal Sarai | K48: Varanasi | L48: Mr. Arka Dey | M48: By Hand | N48: By Hand Mr. Saurabh Mishra | O48: 6000HP: CLW PO 6k49x | P48: 20212095100413 | Q48: 62OP-30878.P.89 | R48: Material for BLW Commissioning against 49x CLW | S48: 10.5 | T48: INR | U48: =S48*F48 -> 252
A49: 46 | B49: 112170848 | C49: 112170848 | D49: COUNTER SUNK FLAT HEAD SCREW M6 X 20 GRADE A-7 | E49: Nos | F49: 36 | G49: UP/DC/FY22/00063 | H49: 44705 | I49: 44705 | J49: DDU Shed Mugal Sarai | K49: Varanasi | L49: Mr. Arka Dey | M49: By Hand | N49: By Hand Mr. Saurabh Mishra | O49: 6000HP: CLW PO 6k49x | P49: 20212095100413 | Q49: 62OP-30878.P.89 | R49: Material for BLW Commissioning against 49x CLW | S49: 14 | T49: INR | U49: =S49*F49 -> 504
A50: 47 | B50: A5E49966102 | C50: A5E49966102A, Rev02 | D50: Cu bushing flag busbar 2 A5E49966102A, Rev02 | E50: Nos | F50: 24 | G50: UP/DC/FY22/00063 | H50: 44705 | I50: 44705 | J50: DDU Shed Mugal Sarai | K50: Varanasi | L50: Mr. Arka Dey | M50: By Hand | N50: By Hand Mr. Saurabh Mishra | O50: 6000HP: CLW PO 6k49x | P50: 20212095100413 | Q50: 62OP-30878.P.89 | R50: Material for BLW Commissioning against 49x CLW | S50: 1784.3 | T50: INR | U50: =S50*F50 -> 42823.2
A51: 48 | B51: 112172543 | C51: 112172543 | D51: DDU PLATE | E51: Nos | F51: 6 | G51: UP/DC/FY22/00063 | H51: 44705 | I51: 44705 | J51: DDU Shed Mugal Sarai | K51: Varanasi | L51: Mr. Arka Dey | M51: By Hand | N51: By Hand Mr. Saurabh Mishra | O51: 6000HP: CLW PO 6k49x | P51: 20212095100413 | Q51: 62OP-30878.P.89 | R51: Material for BLW Commissioning against 49x CLW | S51: 3480 | T51: INR | U51: =S51*F51 -> 20880
A52: 49 | B52: 112172541 | C52: 112172541 | D52: DDU Plate Bracket | E52: Nos | F52: 6 | G52: UP/DC/FY22/00063 | H52: 44705 | I52: 44705 | J52: DDU Shed Mugal Sarai | K52: Varanasi | L52: Mr. Arka Dey | M52: By Hand | N52: By Hand Mr. Saurabh Mishra | O52: 6000HP: CLW PO 6k49x | P52: 20212095100413 | Q52: 62OP-30878.P.89 | R52: Material for BLW Commissioning against 49x CLW | S52: 630 | T52: INR | U52: =S52*F52 -> 3780
A53: 50 | B53: 112172542 | C53: 112172542 | D53: DDU PLATE DISTANCE BOLT | E53: Nos | F53: 18 | G53: UP/DC/FY22/00063 | H53: 44705 | I53: 44705 | J53: DDU Shed Mugal Sarai | K53: Varanasi | L53: Mr. Arka Dey | M53: By Hand | N53: By Hand Mr. Saurabh Mishra | O53: 6000HP: CLW PO 6k49x | P53: 20212095100413 | Q53: 62OP-30878.P.89 | R53: Material for BLW Commissioning against 49x CLW | S53: 65 | T53: INR | U53: =S53*F53 -> 1170
A54: 51 | B54: 112172544 | C54: 112172544 | D54: DDU PLATE LOOMING BAR | E54: Nos | F54: 12 | G54: UP/DC/FY22/00063 | H54: 44705 | I54: 44705 | J54: DDU Shed Mugal Sarai | K54: Varanasi | L54: Mr. Arka Dey | M54: By Hand | N54: By Hand Mr. Saurabh Mishra | O54: 6000HP: CLW PO 6k49x | P54: 20212095100413 | Q54: 62OP-30878.P.89 | R54: Material for BLW Commissioning against 49x CLW | S54: 100 | T54: INR | U54: =S54*F54 -> 1200
A55: 52 | B55: 112170849 | C55: 112170849 | D55: HEX NUT M6 IS :1364-3 Grade A-70 | E55: Nos | F55: 36 | G55: UP/DC/FY22/00063 | H55: 44705 | I55: 44705 | J55: DDU Shed Mugal Sarai | K55: Varanasi | L55: Mr. Arka Dey | M55: By Hand | N55: By Hand Mr. Saurabh Mishra | O55: 6000HP: CLW PO 6k49x | P55: 20212095100413 | Q55: 62OP-30878.P.89 | R55: Material for BLW Commissioning against 49x CLW | S55: 5.5 | T55: INR | U55: =S55*F55 -> 198
A56: 53 | B56: 112161405 | C56: Laptop | D56: Laptop HP 240 G8 Intel Core i3 11th Gen Processor/8GB Ram , 512 GB SSD | E56: Nos | F56: 1 | G56: UP/DC/FY22/00063 | H56: 44705 | I56: 44705 | J56: DDU Shed Mugal Sarai | K56: Varanasi | L56: Mr. Arka Dey | M56: By Hand | N56: By Hand Mr. Saurabh Mishra | O56: 6000HP: CLW PO 6k49x | P56: 20212095100413 | Q56: 62OP-30878.P.89 | R56: For commissioning Laptop Sr. No. 1N12080G1S | S56: 46100 | T56: INR | U56: =S56*F56 -> 46100
A57: 54 | B57: 109492176 | C57: 45953050 | D57: MVB CABLE BL-02 X S (ST) CHX 2 X 2 X 0.5 MM DBN 459530 | E57: Mtr. | F57: 240 | G57: UP/DC/FY22/00063 | H57: 44705 | I57: 44705 | J57: DDU Shed Mugal Sarai | K57: Varanasi | L57: Mr. Arka Dey | M57: By Hand | N57: By Hand Mr. Saurabh Mishra | O57: 6000HP: CLW PO 6k49x | P57: 20212095100413 | Q57: 62OP-30878.P.89 | R57: Material for BLW Commissioning against 49x CLW | S57: 191.98 | T57: INR | U57: =S57*F57 -> 46075.2
A58: 55 | B58: 112161396 | C58: 09990000305 | D58: Removal tool Han C 1,5-6 mm2 09990000305 | E58: Nos | F58: 1 | G58: UP/DC/FY22/00063 | H58: 44705 | I58: 44705 | J58: DDU Shed Mugal Sarai | K58: Varanasi | L58: Mr. Arka Dey | M58: By Hand | N58: By Hand Mr. Saurabh Mishra | O58: 6000HP: CLW PO 6k49x | P58: 20212095100413 | Q58: 62OP-30878.P.89 | R58: For commissioning | S58: 579.58 | T58: INR | U58: =S58*F58 -> 579.58
A59: 56 | B59: 112161394 | C59: 09990000319 | D59: REMOVAL TOOL HAN E 09990000319 | E59: Nos | F59: 1 | G59: UP/DC/FY22/00063 | H59: 44705 | I59: 44705 | J59: DDU Shed Mugal Sarai | K59: Varanasi | L59: Mr. Arka Dey | M59: By Hand | N59: By Hand Mr. Saurabh Mishra | O59: 6000HP: CLW PO 6k49x | P59: 20212095100413 | Q59: 62OP-30878.P.89 | R59: For commissioning | S59: 1155.52 | T59: INR | U59: =S59*F59 -> 1155.52
A60: 57 | B60: 112168680 | C60: 112168680 | D60: TCC COOLENT FILLING PUMP ASSLY | E60: Nos | F60: 1 | G60: UP/DC/FY22/00063 | H60: 44705 | I60: 44705 | J60: DDU Shed Mugal Sarai | K60: Varanasi | L60: Mr. Arka Dey | M60: By Hand | N60: By Hand Mr. Saurabh Mishra | O60: 6000HP: CLW PO 6k49x | P60: 20212095100413 | Q60: 62OP-30878.P.89 | R60: Material for BLW Commissioning against 49x CLW | S60: 16500 | T60: INR | U60: =S60*F60 -> 16500
A61: 58 | B61: 109447744 | C61: 803203 | D61: 803203 LION-DO8-24V-110V-LUE LION I/O MODULE DIGITAL OUTPUTS | E61: Nos | F61: 3 | G61: UP/DC/FY22/00064 | H61: 44706 | I61: 44706 | J61: SR DEE ELECTRIC LOCO SHED | K61: TUGHALAKABAD DELHI | L61: Mr. Arka Dey | M61: 218110392 | N61: SPOTON LOGISTIC Pvt. Ltd. | O61: WAG9/6K | R61: Mitigate loco failure | S61: 19040 | T61: INR | U61: =S61*F61 -> 57120
A62: 59 | B62: 101999218 | C62: XL KF i (A2B00075622) | D62: A2B00075622 DRIVER'S DESK TERMINAL SITET XL KF 1 74V | E62: Nos | F62: 2 | G62: UP/DC/FY22/00064 | H62: 44706 | I62: 44706 | J62: SR DEE ELECTRIC LOCO SHED | K62: TUGHALAKABAD DELHI | L62: Mr. Arka Dey | M62: 218110392 | N62: SPOTON LOGISTIC Pvt. Ltd. | O62: WAG9/6K | R62: Mitigate loco failure | S62: 210800 | T62: INR | U62: =S62*F62 -> 421600
A63: 60 | B63: 109447749 | C63: 803401 | D63: LION Erweiterungsmodul, 4 analoge Ausg. 803401 | E63: Nos | F63: 2 | G63: UP/DC/FY22/00064 | H63: 44706 | I63: 44706 | J63: SR DEE ELECTRIC LOCO SHED | K63: TUGHALAKABAD DELHI | L63: Mr. Arka Dey | M63: 218110392 | N63: SPOTON LOGISTIC Pvt. Ltd. | O63: WAG9/6K | R63: Mitigate loco failure | S63: 22525 | T63: INR | U63: =S63*F63 -> 45050
A64: 61 | B64: 109447743 | C64: 803201 | D64: LION Erweiterungsmodul,8 Wechslerkanaele 803201 | E64: Nos | F64: 2 | G64: UP/DC/FY22/00064 | H64: 44706 | I64: 44706 | J64: SR DEE ELECTRIC LOCO SHED | K64: TUGHALAKABAD DELHI | L64: Mr. Arka Dey | M64: 218110392 | N64: SPOTON LOGISTIC Pvt. Ltd. | O64: WAG9/6K | R64: Mitigate loco failure | S64: 18615 | T64: INR | U64: =S64*F64 -> 37230
A65: 62 | B65: 109447737 | C65: 800103 | D65: LION POWER SUPPLY 36 W DC24V/110V 800103 | E65: Nos | F65: 2 | G65: UP/DC/FY22/00064 | H65: 44706 | I65: 44706 | J65: SR DEE ELECTRIC LOCO SHED | K65: TUGHALAKABAD DELHI | L65: Mr. Arka Dey | M65: 218110392 | N65: SPOTON LOGISTIC Pvt. Ltd. | O65: WAG9/6K | R65: Mitigate loco failure | S65: 18020 | T65: INR | U65: =S65*F65 -> 36040
A66: 63 | B66: 109447745 | C66: 803301 | D66: LION-AI4-U-LUE (Analog Input, 4 channels 803301 | E66: Nos | F66: 2 | G66: UP/DC/FY22/00064 | H66: 44706 | I66: 44706 | J66: SR DEE ELECTRIC LOCO SHED | K66: TUGHALAKABAD DELHI | L66: Mr. Arka Dey | M66: 218110392 | N66: SPOTON LOGISTIC Pvt. Ltd. | O66: WAG9/6K | R66: Mitigate loco failure | S66: 26265 | T66: INR | U66: =S66*F66 -> 52530
A67: 64 | B67: 109447740 | C67: 803001 | D67: LION-Busskoppler-MVB-LUE 803001 | E67: Nos | F67: 2 | G67: UP/DC/FY22/00064 | H67: 44706 | I67: 44706 | J67: SR DEE ELECTRIC LOCO SHED | K67: TUGHALAKABAD DELHI | L67: Mr. Arka Dey | M67: 218110392 | N67: SPOTON LOGISTIC Pvt. Ltd. | O67: WAG9/6K | R67: Mitigate loco failure | S67: 40800 | T67: INR | U67: =S67*F67 -> 81600
A68: 65 | C68: TRANSFORMER OIL | D68: TRANSFORMER OIL | E68: Ltr | F68: 250 | G68: UP/DC/FY22/00064 | H68: 44706 | I68: 44706 | J68: SR DEE ELECTRIC LOCO SHED | K68: TUGHALAKABAD DELHI | L68: Mr. Arka Dey | M68: 218110392 | N68: SPOTON LOGISTIC Pvt. Ltd. | O68: WAG9/6K | R68: Mitigate loco failure | S68: 339 | T68: INR | U68: =S68*F68 -> 84750
A69: 66 | B69: 102464571 | C69: 3RV2011-1GA10 | D69: 3RV2011-1GA10 \CIRCUIT-BREAKER SCREW CO ( MPCV 6000 HP) | E69: Nos | F69: 10 | G69: UP/DC/FY22/00065 | H69: 44707 | I69: 44707 | J69: SIEMENS LTD. G. HOUSE | K69: Paschim Burdwan WB | L69: Mr. Arka Dey | M69: 218110400 | N69: SPOTON/DELHIVERY | O69: WAG9/6k | P69: 70201134101308 | Q69: 62OP 30878 | R69: 5 Set Wag-9/6K Supply to CLW | S69: 1007.25 | T69: INR | U69: =S69*F69 -> 10072.5
A70: 67 | B70: 102951260 | C70: 3RV2901-1A | D70: 3RV2901-1A \LATERAL AUXILIARY SWITCH | E70: Nos | F70: 10 | G70: UP/DC/FY22/00065 | H70: 44707 | I70: 44707 | J70: SIEMENS LTD. G. HOUSE | K70: Paschim Burdwan WB | L70: Mr. Arka Dey | M70: 218110400 | N70: SPOTON/DELHIVERY | O70: WAG9/6k | P70: 70201134101308 | Q70: 62OP 30878 | R70: 5 Set Wag-9/6K Supply to CLW | S70: 216.59 | T70: INR | U70: =S70*F70 -> 2165.9
A71: 68 | B71: 101576439 | C71: 5SY5103-7 | D71: 5SY5103-7\CIRCUIT BREAKER UC 10KA 1P C03 | E71: Nos | F71: 10 | G71: UP/DC/FY22/00065 | H71: 44707 | I71: 44707 | J71: SIEMENS LTD. G. HOUSE | K71: Paschim Burdwan WB | L71: Mr. Arka Dey | M71: 218110400 | N71: SPOTON/DELHIVERY | O71: WAG9/6k | P71: 70201134101308 | Q71: 62OP 30878 | R71: 5 Set Wag-9/6K Supply to CLW | S71: 1184 | T71: INR | U71: =S71*F71 -> 11840
A72: 69 | B72: 109611234 | C72: 3742612236 | D72: Active Speed Sensors suitable for IGBT locos [3-Phase Locos] DSD 1616.73 QHW - F267S 3742612236 | E72: Nos | F72: 30 | G72: UP/DC/FY22/00065 | H72: 44707 | I72: 44707 | J72: SIEMENS LTD. G. HOUSE | K72: Paschim Burdwan WB | L72: Mr. Arka Dey | M72: 218110400 | N72: SPOTON/DELHIVERY | O72: WAG9/6k | P72: 70201134101308 | Q72: 62OP 30878 | R72: 5 Set Wag-9/6K Supply to CLW | S72: 19072.55 | T72: INR | U72: =S72*F72 -> 572176.5
A73: 70 | B73: 110408292 | C73: M6X16 | D73: Allen cap M6 X 16 Fixing Bolt for sensor plate Hexagonal socket head cap screws ISO 4762 – M6x16-8.8 with Zinc Plating | E73: Nos | F73: 300 | G73: UP/DC/FY22/00065 | H73: 44707 | I73: 44707 | J73: SIEMENS LTD. G. HOUSE | K73: Paschim Burdwan WB | L73: Mr. Arka Dey | M73: 218110400 | N73: SPOTON/DELHIVERY | O73: WAG9/6k | P73: 70201134101308 | Q73: 62OP 30878 | R73: 5 Set Wag-9/6K Supply to CLW | S73: 10 | T73: INR | U73: =S73*F73 -> 3000
A74: 71 | B74: 109492174 | C74: 1331M295FS | D74: AMPHENOL 1331M295FS (INCLUDING 1330-16F4+PE INCL. 5 FEMALE CRIMP CONTACTS) | E74: Nos | F74: 10 | G74: UP/DC/FY22/00065 | H74: 44707 | I74: 44707 | J74: SIEMENS LTD. G. HOUSE | K74: Paschim Burdwan WB | L74: Mr. Arka Dey | M74: 218110400 | N74: SPOTON/DELHIVERY | O74: WAG9/6k | P74: 70201134101308 | Q74: 62OP 30878 | R74: 5 Set Wag-9/6K Supply to CLW | S74: 4051 | T74: INR | U74: =S74*F74 -> 40510
A75: 72 | B75: 109492175 | C75: 13302P1 | D75: Amphenol Back Shell 13302P1 / 109492175 | E75: Nos | F75: 10 | G75: UP/DC/FY22/00065 | H75: 44707 | I75: 44707 | J75: SIEMENS LTD. G. HOUSE | K75: Paschim Burdwan WB | L75: Mr. Arka Dey | M75: 218110400 | N75: SPOTON/DELHIVERY | O75: WAG9/6k | P75: 70201134101308 | Q75: 62OP 30878 | R75: 5 Set Wag-9/6K Supply to CLW | S75: 1404 | T75: INR | U75: =S75*F75 -> 14040
A76: 73 | B76: 107171952 | C76: 99148781208 | D76: Binder Connector 8 POLE /AWG20 TIGHTENING TORQUE 0.2NM PN 99148781208 | E76: Nos | F76: 10 | G76: UP/DC/FY22/00065 | H76: 44707 | I76: 44707 | J76: SIEMENS LTD. G. HOUSE | K76: Paschim Burdwan WB | L76: Mr. Arka Dey | M76: 218110400 | N76: SPOTON/DELHIVERY | O76: WAG9/6k | P76: 70201134101308 | Q76: 62OP 30878 | R76: 5 Set Wag-9/6K Supply to CLW | S76: 2750 | T76: INR | U76: =S76*F76 -> 27500
A77: 74 | B77: 110710681 | C77: 3EHP430699R0001 | D77: Braided Busbars Item1 WAG9-6K-EN3-TES-01 | E77: Nos | F77: 40 | G77: UP/DC/FY22/00065 | H77: 44707 | I77: 44707 | J77: SIEMENS LTD. G. HOUSE | K77: Paschim Burdwan WB | L77: Mr. Arka Dey | M77: 218110400 | N77: SPOTON/DELHIVERY | O77: WAG9/6k | P77: 70201134101308 | Q77: 62OP 30878 | R77: 5 Set Wag-9/6K Supply to CLW | S77: 2047 | T77: INR | U77: =S77*F77 -> 81880
A78: 75 | B78: 110710682 | C78: 3EHP430699R0002 | D78: Braided Busbars Item2 WAG9-6K-EN3-TES-01 | E78: Nos | F78: 40 | G78: UP/DC/FY22/00065 | H78: 44707 | I78: 44707 | J78: SIEMENS LTD. G. HOUSE | K78: Paschim Burdwan WB | L78: Mr. Arka Dey | M78: 218110400 | N78: SPOTON/DELHIVERY | O78: WAG9/6k | P78: 70201134101308 | Q78: 62OP 30878 | R78: 5 Set Wag-9/6K Supply to CLW | S78: 2047 | T78: INR | U78: =S78*F78 -> 81880
A79: 76 | B79: 110710684 | C79: 3EHP431282R0001 | D79: Braided Busbars Item3 WAG9-6K-EN3-TES-01 | E79: Nos | F79: 20 | G79: UP/DC/FY22/00065 | H79: 44707 | I79: 44707 | J79: SIEMENS LTD. G. HOUSE | K79: Paschim Burdwan WB | L79: Mr. Arka Dey | M79: 218110400 | N79: SPOTON/DELHIVERY | O79: WAG9/6k | P79: 70201134101308 | Q79: 62OP 30878 | R79: 5 Set Wag-9/6K Supply to CLW | S79: 2047 | T79: INR | U79: =S79*F79 -> 40940
A80: 77 | B80: 112136081 | C80: 09000005094 | D80: CABLE GLAND PG29 KAD 18.0-14.0MM FCBL 09000005094 | E80: Nos | F80: 10 | G80: UP/DC/FY22/00065 | H80: 44707 | I80: 44707 | J80: SIEMENS LTD. G. HOUSE | K80: Paschim Burdwan WB | L80: Mr. Arka Dey | M80: 218110400 | N80: SPOTON/DELHIVERY | O80: WAG9/6k | P80: 70201134101308 | Q80: 62OP 30878 | R80: 5 Set Wag-9/6K Supply to CLW | S80: 570.47 | T80: INR | U80: =S80*F80 -> 5704.7
A81: 78 | B81: 112172545 | C81: 112172545 | D81: COUNTER SUNK FLAT HEAD SCREW IS: 1365- M4 | E81: Nos | F81: 60 | G81: UP/DC/FY22/00065 | H81: 44707 | I81: 44707 | J81: SIEMENS LTD. G. HOUSE | K81: Paschim Burdwan WB | L81: Mr. Arka Dey | M81: 218110400 | N81: SPOTON/DELHIVERY | O81: WAG9/6k | P81: 70201134101308 | Q81: 62OP 30878 | R81: 5 Set Wag-9/6K Supply to CLW | S81: 8.5 | T81: INR | U81: =S81*F81 -> 510
A82: 79 | B82: 112172546 | C82: 112172546 | D82: COUNTER SUNK FLAT HEAD SCREW IS: 1365- M5 | E82: Nos | F82: 40 | G82: UP/DC/FY22/00065 | H82: 44707 | I82: 44707 | J82: SIEMENS LTD. G. HOUSE | K82: Paschim Burdwan WB | L82: Mr. Arka Dey | M82: 218110400 | N82: SPOTON/DELHIVERY | O82: WAG9/6k | P82: 70201134101308 | Q82: 62OP 30878 | R82: 5 Set Wag-9/6K Supply to CLW | S82: 10.5 | T82: INR | U82: =S82*F82 -> 420
A83: 80 | B83: 112170848 | C83: 112170848 | D83: COUNTER SUNK FLAT HEAD SCREW M6 X 20 GRADE A-7 | E83: Nos | F83: 60 | G83: UP/DC/FY22/00065 | H83: 44707 | I83: 44707 | J83: SIEMENS LTD. G. HOUSE | K83: Paschim Burdwan WB | L83: Mr. Arka Dey | M83: 218110400 | N83: SPOTON/DELHIVERY | O83: WAG9/6k | P83: 70201134101308 | Q83: 62OP 30878 | R83: 5 Set Wag-9/6K Supply to CLW | S83: 14 | T83: INR | U83: =S83*F83 -> 840
A84: 81 | B84: 109492197 | C84: 61030000067 | D84: CRIMP FLANGE FOR D-SUB HARTING (S102117360) FORMVB CONNECTOR 61030000067 | E84: Nos | F84: 80 | G84: UP/DC/FY22/00065 | H84: 44707 | I84: 44707 | J84: SIEMENS LTD. G. HOUSE | K84: Paschim Burdwan WB | L84: Mr. Arka Dey | M84: 218110400 | N84: SPOTON/DELHIVERY | O84: WAG9/6k | P84: 70201134101308 | Q84: 62OP 30878 | R84: 5 Set Wag-9/6K Supply to CLW | S84: 66.92 | T84: INR | U84: =S84*F84 -> 5353.6
A85: 82 | B85: A5E49966102 | C85: A5E49966102A, Rev02 | D85: Cu bushing flag busbar 2 A5E49966102A, Rev02 | E85: Nos | F85: 40 | G85: UP/DC/FY22/00065 | H85: 44707 | I85: 44707 | J85: SIEMENS LTD. G. HOUSE | K85: Paschim Burdwan WB | L85: Mr. Arka Dey | M85: 218110400 | N85: SPOTON/DELHIVERY | O85: WAG9/6k | P85: 70201134101308 | Q85: 62OP 30878 | R85: 5 Set Wag-9/6K Supply to CLW | S85: 1784.3 | T85: INR | U85: =S85*F85 -> 71372
A86: 83 | B86: 109492180 | C86: 09670094701 | D86: D- SUB CRIMP 9-POLE FEMALE ASSEMBLY '09670094701 | E86: Nos | F86: 40 | G86: UP/DC/FY22/00065 | H86: 44707 | I86: 44707 | J86: SIEMENS LTD. G. HOUSE | K86: Paschim Burdwan WB | L86: Mr. Arka Dey | M86: 218110400 | N86: SPOTON/DELHIVERY | O86: WAG9/6k | P86: 70201134101308 | Q86: 62OP 30878 | R86: 5 Set Wag-9/6K Supply to CLW | S86: 32.22 | T86: INR | U86: =S86*F86 -> 1288.8
A87: 84 | B87: 112172543 | C87: 112172543 | D87: DDU PLATE | E87: Nos | F87: 10 | G87: UP/DC/FY22/00065 | H87: 44707 | I87: 44707 | J87: SIEMENS LTD. G. HOUSE | K87: Paschim Burdwan WB | L87: Mr. Arka Dey | M87: 218110400 | N87: SPOTON/DELHIVERY | O87: WAG9/6k | P87: 70201134101308 | Q87: 62OP 30878 | R87: 5 Set Wag-9/6K Supply to CLW | S87: 3480 | T87: INR | U87: =S87*F87 -> 34800
A88: 85 | B88: 112172541 | C88: 112172541 | D88: DDU Plate Bracket | E88: Nos | F88: 10 | G88: UP/DC/FY22/00065 | H88: 44707 | I88: 44707 | J88: SIEMENS LTD. G. HOUSE | K88: Paschim Burdwan WB | L88: Mr. Arka Dey | M88: 218110400 | N88: SPOTON/DELHIVERY | O88: WAG9/6k | P88: 70201134101308 | Q88: 62OP 30878 | R88: 5 Set Wag-9/6K Supply to CLW | S88: 630 | T88: INR | U88: =S88*F88 -> 6300
A89: 86 | B89: 112172542 | C89: 112172542 | D89: DDU PLATE DISTANCE BOLT | E89: Nos | F89: 30 | G89: UP/DC/FY22/00065 | H89: 44707 | I89: 44707 | J89: SIEMENS LTD. G. HOUSE | K89: Paschim Burdwan WB | L89: Mr. Arka Dey | M89: 218110400 | N89: SPOTON/DELHIVERY | O89: WAG9/6k | P89: 70201134101308 | Q89: 62OP 30878 | R89: 5 Set Wag-9/6K Supply to CLW | S89: 65 | T89: INR | U89: =S89*F89 -> 1950
A90: 87 | B90: 112172544 | C90: 112172544 | D90: DDU PLATE LOOMING BAR | E90: Nos | F90: 20 | G90: UP/DC/FY22/00065 | H90: 44707 | I90: 44707 | J90: SIEMENS LTD. G. HOUSE | K90: Paschim Burdwan WB | L90: Mr. Arka Dey | M90: 218110400 | N90: SPOTON/DELHIVERY | O90: WAG9/6k | P90: 70201134101308 | Q90: 62OP 30878 | R90: 5 Set Wag-9/6K Supply to CLW | S90: 100 | T90: INR | U90: =S90*F90 -> 2000
A91: 88 | B91: 109492192 | C91: 09670095601 | D91: D-SUB CRIMP 9-POLE MALE ASSEMBLY 09670095601 | E91: Nos | F91: 40 | G91: UP/DC/FY22/00065 | H91: 44707 | I91: 44707 | J91: SIEMENS LTD. G. HOUSE | K91: Paschim Burdwan WB | L91: Mr. Arka Dey | M91: 218110400 | N91: SPOTON/DELHIVERY | O91: WAG9/6k | P91: 70201134101308 | Q91: 62OP 30878 | R91: 5 Set Wag-9/6K Supply to CLW | S91: 24.1 | T91: INR | U91: =S91*F91 -> 964
A92: 89 | B92: 109492193 | C92: 09670003576 | D92: D-Sub, MA AWG 18-22 crimp cont 09670003576 | E92: Nos | F92: 170 | G92: UP/DC/FY22/00065 | H92: 44707 | I92: 44707 | J92: SIEMENS LTD. G. HOUSE | K92: Paschim Burdwan WB | L92: Mr. Arka Dey | M92: 218110400 | N92: SPOTON/DELHIVERY | O92: WAG9/6k | P92: 70201134101308 | Q92: 62OP 30878 | R92: 5 Set Wag-9/6K Supply to CLW | S92: 11.26 | T92: INR | U92: =S92*F92 -> 1914.2
A93: 90 | B93: 109492212 | C93: 09670008576 | D93: D-Sub, MA AWG 20-24 crimp cont 09670008576 | E93: Nos | F93: 320 | G93: UP/DC/FY22/00065 | H93: 44707 | I93: 44707 | J93: SIEMENS LTD. G. HOUSE | K93: Paschim Burdwan WB | L93: Mr. Arka Dey | M93: 218110400 | N93: SPOTON/DELHIVERY | O93: WAG9/6k | P93: 70201134101308 | Q93: 62OP 30878 | R93: 5 Set Wag-9/6K Supply to CLW | S93: 11.26 | T93: INR | U93: =S93*F93 -> 3603.2
A94: 91 | B94: 109492179 | C94: 12568935 | D94: Ethernet Cable RAILCAT CAT 5e 4 X 22AWG XMS RADOX TRACTION CABLE | E94: Mtr. | F94: 650 | G94: UP/DC/FY22/00065 | H94: 44707 | I94: 44707 | J94: SIEMENS LTD. G. HOUSE | K94: Paschim Burdwan WB | L94: Mr. Arka Dey | M94: 218110400 | N94: SPOTON/DELHIVERY | O94: WAG9/6k | P94: 70201134101308 | Q94: 62OP 30878 | R94: 5 Set Wag-9/6K Supply to CLW | S94: 174.89 | T94: INR | U94: =S94*F94 -> 113678.5
A95: 92 | B95: 112139784 | C95: TCP-V0 20MM | D95: Expendo TCP-V0 20MM | E95: Mtr. | F95: 400 | G95: UP/DC/FY22/00065 | H95: 44707 | I95: 44707 | J95: SIEMENS LTD. G. HOUSE | K95: Paschim Burdwan WB | L95: Mr. Arka Dey | M95: 218110400 | N95: SPOTON/DELHIVERY | O95: WAG9/6k | P95: 70201134101308 | Q95: 62OP 30878 | R95: 5 Set Wag-9/6K Supply to CLW | S95: 25.5 | T95: INR | U95: =S95*F95 -> 10200
A96: 93 | B96: 109609632 | C96: 09150043013 | D96: HAN 4 QUINTAX STIFT, 3-9.5MM 09150043013 | E96: Nos | F96: 20 | G96: UP/DC/FY22/00065 | H96: 44707 | I96: 44707 | J96: SIEMENS LTD. G. HOUSE | K96: Paschim Burdwan WB | L96: Mr. Arka Dey | M96: 218110400 | N96: SPOTON/DELHIVERY | O96: WAG9/6k | P96: 70201134101308 | Q96: 62OP 30878 | R96: 5 Set Wag-9/6K Supply to CLW | S96: 100.06 | T96: INR | U96: =S96*F96 -> 2001.2
A97: 94 | B97: 112136066 | C97: 09330062702 | D97: HAN 6E INSERT FEMALE CRIMP 09330062702 | E97: Nos | F97: 10 | G97: UP/DC/FY22/00065 | H97: 44707 | I97: 44707 | J97: SIEMENS LTD. G. HOUSE | K97: Paschim Burdwan WB | L97: Mr. Arka Dey | M97: 218110400 | N97: SPOTON/DELHIVERY | O97: WAG9/6k | P97: 70201134101308 | Q97: 62OP 30878 | R97: 5 Set Wag-9/6K Supply to CLW | S97: 113.51 | T97: INR | U97: =S97*F97 -> 1135.1
A98: 95 | B98: 112136070 | C98: 19628060446 | D98: HAN 6EMC/B-THE-M25 (HT) 19628060446 | E98: Nos | F98: 10 | G98: UP/DC/FY22/00065 | H98: 44707 | I98: 44707 | J98: SIEMENS LTD. G. HOUSE | K98: Paschim Burdwan WB | L98: Mr. Arka Dey | M98: 218110400 | N98: SPOTON/DELHIVERY | O98: WAG9/6k | P98: 70201134101308 | Q98: 62OP 30878 | R98: 5 Set Wag-9/6K Supply to CLW | S98: 721.74 | T98: INR | U98: =S98*F98 -> 7217.4
A99: 96 | B99: 112136069 | C99: 09330006223 | D99: Han E F Crimp Contact Au 2.5 mm / 14AWG 09330006223 | E99: Nos | F99: 30 | G99: UP/DC/FY22/00065 | H99: 44707 | I99: 44707 | J99: SIEMENS LTD. G. HOUSE | K99: Paschim Burdwan WB | L99: Mr. Arka Dey | M99: 218110400 | N99: SPOTON/DELHIVERY | O99: WAG9/6k | P99: 70201134101308 | Q99: 62OP 30878 | R99: 5 Set Wag-9/6K Supply to CLW | S99: 45.6 | T99: INR | U99: =S99*F99 -> 1368
A100: 97 | B100: 112136080 | C100: 9140009950 | D100: HAN-MODULAR DUMMY MODULE 09140009950 YYH | E100: Nos | F100: 40 | G100: UP/DC/FY22/00065 | H100: 44707 | I100: 44707 | J100: SIEMENS LTD. G. HOUSE | K100: Paschim Burdwan WB | L100: Mr. Arka Dey | M100: 218110400 | N100: SPOTON/DELHIVERY | O100: WAG9/6k | P100: 70201134101308 | Q100: 62OP 30878 | R100: 5 Set Wag-9/6K Supply to CLW | S100: 13.72 | T100: INR | U100: =S100*F100 -> 548.8
...

Sheet Summery
G1: =G2-'In-ward Register'!M2 -> -1157582.4 | H1: =H2-'Out-ward Register'!F2 -> 0 | J1: Value In Minr → | K1: =K2/1000000 -> 0.0948 | L1: =L2/1000000 -> 0 | M1: =M2/1000000 -> 0.0948 | N1: =L1+M1 -> 0.0948
B2: MIS As on 31-July -25 | G2: =SUBTOTAL(9,G4:G9660) -> 3 | H2: =SUM(H4:H1048576) -> 604899.94 | I2: =G2-H2 -> -604896.94 | K2: =SUBTOTAL(9,K4:K9660) -> 94800 | L2: =SUBTOTAL(9,L4:L9660) -> 0 | M2: =K2-L2 -> 94800 | R2: =M2-Q2 -> 94800
A3: Project | B3: Sr. No. | C3: SAP Code | D3: Part Code | E3: Description | F3: UOM | G3: Received Qty | H3: Dispatch Qty | I3: Balance Qty | J3: Avg. Price As per P.o. | K3: Received Qty Value | L3: Dispatched Qty Value | M3: Balance Qty Value | N3: Remark | O3: Value In % | P3: 1111a
A4: Project 6K | B4: 36 | C4: 109611234 | D4: 3742612236 | E4: ACTIVE SPEED SENSORS SUITABLE FOR IGBT LOCOS [3-PHASE LOCOS] DSD 1616.73 QHW - F267S 3742612236 | F4: Nos | G4: =SUMIF('In-ward Register'!$K:$K,Summery!$E:$E,'In-ward Register'!$M:$M) -> 3036 | H4: =SUMIF('Out-ward Register'!$D:$D,Summery!$E:$E,'Out-ward Register'!$F:$F) -> 2526 | I4: =G4-H4 -> 510 | J4: 26302 | K4: =J4*G4 -> 79852872 | L4: =J4*H4 -> 66438852 | M4: =K4-L4 -> 13414020 | O4: =M4/M$2*100 -> 14149.81
A5: Project 6K | B5: 998 | C5: 111393237 | D5: APTXA003C | E5: Driver Display Unit for 3- Phase Locomotive UIC keyboard, MVB | F5: Nos | G5: =SUMIF('In-ward Register'!$K:$K,Summery!$E:$E,'In-ward Register'!$M:$M) -> 324 | H5: =SUMIF('Out-ward Register'!$D:$D,Summery!$E:$E,'Out-ward Register'!$F:$F) -> 280 | I5: =G5-H5 -> 44 | J5: 178635.05 | K5: =J5*G5 -> 57877758 | L5: =J5*H5 -> 50017815 | M5: =K5-L5 -> 7859942.4
A6: Project-HLC | B6: 1165 | C6: 105401095 | D6: SA2V00001200316 | E6: SIBCOS M2500-2-0 | F6: Nos | G6: =SUMIF('In-ward Register'!$K:$K,Summery!$E:$E,'In-ward Register'!$M:$M) -> 31 | H6: =SUMIF('Out-ward Register'!$D:$D,Summery!$E:$E,'Out-ward Register'!$F:$F) -> 7 | I6: =G6-H6 -> 24 | J6: 201000 | K6: =J6*G6 -> 6231000 | L6: =J6*H6 -> 1407000 | M6: =K6-L6 -> 4824000
A7: Project 6K | B7: 934 | C7: 109447744 | D7: 803203 | E7: 803203 LION-DO8-24V-110V-LUE LION I/O MODULE DIGITAL OUTPUTS | F7: Nos | G7: =SUMIF('In-ward Register'!$K:$K,Summery!$E:$E,'In-ward Register'!$M:$M) -> 726 | H7: =SUMIF('Out-ward Register'!$D:$D,Summery!$E:$E,'Out-ward Register'!$F:$F) -> 530 | I7: =G7-H7 -> 196 | J7: 20246.37 | K7: =J7*G7 -> 14698865 | L7: =J7*H7 -> 10730576 | M7: =K7-L7 -> 3968288.5 | O7: =M7/M$2*100 -> 4185.9584
A8: Project 6K | B8: 355 | C8: 107157518/ 112171911 | D8: LT30 | E8: REMMLOT DEVICE | F8: Nos | G8: =SUMIF('In-ward Register'!$K:$K,Summery!$E:$E,'In-ward Register'!$M:$M) -> 351 | H8: =SUMIF('Out-ward Register'!$D:$D,Summery!$E:$E,'Out-ward Register'!$F:$F) -> 326 | I8: =G8-H8 -> 25 | J8: 158554.7 | K8: =J8*G8 -> 55652700 | L8: =J8*H8 -> 51688832 | M8: =K8-L8 -> 3963867.5 | O8: =M8/M$2*100 -> 4181.2948
A9: Project 6K | B9: 598 | C9: 109492176 | D9: 45953050 | E9: MVB CABLE BL-02 X S (ST) CHX 2 X 2 X 0.5 MM DBN 459530 | F9: Mtr. | G9: =SUMIF('In-ward Register'!$K:$K,Summery!$E:$E,'In-ward Register'!$M:$M) -> 48241 | H9: =SUMIF('Out-ward Register'!$D:$D,Summery!$E:$E,'Out-ward Register'!$F:$F) -> 38348.5 | I9: =G9-H9 -> 9892.5 | J9: 293.43 | K9: =J9*G9 -> 14155357 | L9: =J9*H9 -> 11252600 | M9: =K9-L9 -> 2902756.3 | O9: =M9/M$2*100 -> 3061.9792
A10: Project-HLC | B10: 1151 | C10: A5E38077362 | D10: SA5E35109084 | E10: A2V00001450989 HLC 4QS SPAR | F10: Nos | G10: =SUMIF('In-ward Register'!$K:$K,Summery!$E:$E,'In-ward Register'!$M:$M) -> 13 | H10: =SUMIF('Out-ward Register'!$D:$D,Summery!$E:$E,'Out-ward Register'!$F:$F) -> 10 | I10: =G10-H10 -> 3 | J10: 950000 | K10: =J10*G10 -> 12350000 | L10: =J10*H10 -> 9500000 | M10: =K10-L10 -> 2850000
A11: Project 6K | B11: 880 | C11: 112169820 | D11: ERLBT157013XXX2 | E11: CABLE 1C X 2.5 SQ MM - 4 GKW - 1.8/3 KV | F11: Mtr. | G11: =SUMIF('In-ward Register'!$K:$K,Summery!$E:$E,'In-ward Register'!$M:$M) -> 118746 | H11: =SUMIF('Out-ward Register'!$D:$D,Summery!$E:$E,'Out-ward Register'!$F:$F) -> 40457 | I11: =G11-H11 -> 78289 | J11: 34.6 | K11: =J11*G11 -> 4108611.6 | L11: =J11*H11 -> 1399812.2 | M11: =K11-L11 -> 2708799.4 | O11: =M11/M$2*100 -> 2857.3833
A12: Project 6K | B12: 10 | C12: 101999218 | D12: XL KF i (A2B00075622) | E12: A2B00075622 DRIVER'S DESK TERMINAL SITET XL KF 1 74V | F12: Nos | G12: =SUMIF('In-ward Register'!$K:$K,Summery!$E:$E,'In-ward Register'!$M:$M) -> 111 | H12: =SUMIF('Out-ward Register'!$D:$D,Summery!$E:$E,'Out-ward Register'!$F:$F) -> 101 | I12: =G12-H12 -> 10 | J12: 233573.6 | K12: =J12*G12 -> 25926670 | L12: =J12*H12 -> 23590934 | M12: =K12-L12 -> 2335736 | O12: =M12/M$2*100 -> 2463.8565
A13: Project 9K | B13: 741 | C13: 112137134 | D13: 21038811406 | E13: M12 CRIMP SLIM DESIGN 4 POL D CODED M '21038811406 | F13: Nos | G13: =SUMIF('In-ward Register'!$K:$K,Summery!$E:$E,'In-ward Register'!$M:$M) -> 8913 | H13: =SUMIF('Out-ward Register'!$D:$D,Summery!$E:$E,'Out-ward Register'!$F:$F) -> 6493 | I13: =G13-H13 -> 2420 | J13: 930.97 | K13: =J13*G13 -> 8297735.6 | L13: =J13*H13 -> 6044788.2 | M13: =K13-L13 -> 2252947.4 | O13: =M13/M$2*100 -> 2376.5268
A14: Project 6K | B14: 551 | C14: 110408288 | D14: 3062607559 | E14: PULSE WHEEL FTP 521/120 | F14: Nos | G14: =SUMIF('In-ward Register'!$K:$K,Summery!$E:$E,'In-ward Register'!$M:$M) -> 3244 | H14: =SUMIF('Out-ward Register'!$D:$D,Summery!$E:$E,'Out-ward Register'!$F:$F) -> 2484 | I14: =G14-H14 -> 760 | J14: 2750 | K14: =J14*G14 -> 8921000 | L14: =J14*H14 -> 6831000 | M14: =K14-L14 -> 2090000 | O14: =M14/M$2*100 -> 2204.6414
A15: Project 6K | B15: 679 | C15: 109492179 | D15: 12568935 | E15: ETHERNET CABLE RAILCAT CAT 5E 4 X 22AWG XMS RADOX TRACTION CABLE | F15: Mtr. | G15: =SUMIF('In-ward Register'!$K:$K,Summery!$E:$E,'In-ward Register'!$M:$M) -> 84701 | H15: =SUMIF('Out-ward Register'!$D:$D,Summery!$E:$E,'Out-ward Register'!$F:$F) -> 60702 | I15: =G15-H15 -> 23999 | J15: 82.11 | K15: =J15*G15 -> 6954799.1 | L15: =J15*H15 -> 4984241.2 | M15: =K15-L15 -> 1970557.9 | O15: =M15/M$2*100 -> 2078.6476
A16: Project-HLC | B16: 938 | C16: 111367611 | D16: 111367611 | E16: IV Coupler Socket with 1m cable ( Complete Set) | F16: Nos | G16: =SUMIF('In-ward Register'!$K:$K,Summery!$E:$E,'In-ward Register'!$M:$M) -> 66 | H16: =SUMIF('Out-ward Register'!$D:$D,Summery!$E:$E,'Out-ward Register'!$F:$F) -> 6 | I16: =G16-H16 -> 60 | J16: 32750 | K16: =J16*G16 -> 2161500 | L16: =J16*H16 -> 196500 | M16: =K16-L16 -> 1965000
A17: Project 6K | B17: 154 | C17: 111400055 | D17: MS3474W14-5P-SQSC 01268739 | E17: AMPHENOL PART NO:- MS3474W14-5P-SQSC 01268739 | F17: Nos | G17: =SUMIF('In-ward Register'!$K:$K,Summery!$E:$E,'In-ward Register'!$M:$M) -> 3780 | H17: =SUMIF('Out-ward Register'!$D:$D,Summery!$E:$E,'Out-ward Register'!$F:$F) -> 2659 | I17: =G17-H17 -> 1121 | J17: 1732 | K17: =J17*G17 -> 6546960 | L17: =J17*H17 -> 4605388 | M17: =K17-L17 -> 1941572 | O17: =M17/M$2*100 -> 2048.0717
A18: Project 6K | B18: 721 | C18: A5E49966102 | D18: A5E49966102A, Rev02 | E18: Cu bushing flag busbar 2 A5E49966102A, Rev02 | F18: Nos | G18: =SUMIF('In-ward Register'!$K:$K,Summery!$E:$E,'In-ward Register'!$M:$M) -> 4843 | H18: =SUMIF('Out-ward Register'!$D:$D,Summery!$E:$E,'Out-ward Register'!$F:$F) -> 3339 | I18: =G18-H18 -> 1504 | J18: 1241.95 | K18: =J18*G18 -> 6014763.9 | L18: =J18*H18 -> 4146871.1 | M18: =K18-L18 -> 1867892.8 | O18: =M18/M$2*100 -> 1970.3511
A19: Project 6K | B19: 620 | C19: 110710681 | D19: 3EHP430699R0001 | E19: Braided Busbars Item1 WAG9-6K-EN3-TES-01 | F19: Nos | G19: =SUMIF('In-ward Register'!$K:$K,Summery!$E:$E,'In-ward Register'!$M:$M) -> 4138 | H19: =SUMIF('Out-ward Register'!$D:$D,Summery!$E:$E,'Out-ward Register'!$F:$F) -> 3322 | I19: =G19-H19 -> 816 | J19: 2153 | K19: =J19*G19 -> 8909114 | L19: =J19*H19 -> 7152266 | M19: =K19-L19 -> 1756848 | O19: =M19/M$2*100 -> 1853.2152
A20: Project-HLC | B20: 1164 | C20: A5E39006935 | D20: A2V00001202513 | E20: Trigger Unit | F20: Nos | G20: =SUMIF('In-ward Register'!$K:$K,Summery!$E:$E,'In-ward Register'!$M:$M) -> 35 | H20: =SUMIF('Out-ward Register'!$D:$D,Summery!$E:$E,'Out-ward Register'!$F:$F) -> 9 | I20: =G20-H20 -> 26 | J20: 67185 | K20: =J20*G20 -> 2351475 | L20: =J20*H20 -> 604665 | M20: =K20-L20 -> 1746810
A21: WAP-7 Locomotive | B21: 699 | C21: 108221269 | D21: WAP-7 Locomotive | E21: FABRICATED BOGIE FRAME COMPLETE FOR WAG-9HC LOCOMOTIVE / FABRICATED BOGIE FRAME COMPLETE FOR WAP-7 LOCOMOTIVE | F21: Nos | G21: =SUMIF('In-ward Register'!$K:$K,Summery!$E:$E,'In-ward Register'!$M:$M) -> 2 | H21: =SUMIF('Out-ward Register'!$D:$D,Summery!$E:$E,'Out-ward Register'!$F:$F) -> 0 | I21: =G21-H21 -> 2 | J21: 873333 | K21: =J21*G21 -> 1746666 | L21: =J21*H21 -> 0 | M21: =K21-L21 -> 1746666 | O21: =M21/M$2*100 -> 1842.4747
A22: Project-HLC | B22: 1006 | C22: 105401093 | D22: SA2V00001680232 | E22: FAN 3PHASE 415V 3KW 1PP SA2V00001680232 | F22: Nos | G22: =SUMIF('In-ward Register'!$K:$K,Summery!$E:$E,'In-ward Register'!$M:$M) -> 15 | H22: =SUMIF('Out-ward Register'!$D:$D,Summery!$E:$E,'Out-ward Register'!$F:$F) -> 2 | I22: =G22-H22 -> 13 | J22: 133000 | K22: =J22*G22 -> 1995000 | L22: =J22*H22 -> 266000 | M22: =K22-L22 -> 1729000
A23: Project 6K | B23: 692 | C23: 110710682 | D23: Item2 WAG9-6K-EN3-TES-01 | E23: Braided Busbars Item2 WAG9-6K-EN3-TES-01 | F23: Nos | G23: =SUMIF('In-ward Register'!$K:$K,Summery!$E:$E,'In-ward Register'!$M:$M) -> 4126 | H23: =SUMIF('Out-ward Register'!$D:$D,Summery!$E:$E,'Out-ward Register'!$F:$F) -> 3310 | I23: =G23-H23 -> 816 | J23: 2078 | K23: =J23*G23 -> 8573828 | L23: =J23*H23 -> 6878180 | M23: =K23-L23 -> 1695648 | O23: =M23/M$2*100 -> 1788.6582
A24: other | B24: 534 | C24: 109447742 | D24: 803102 | E24: 803102 LION-DI16-72V-110V-LUE LION I/O MODULE DIGITAL OUTPUTS | F24: Nos | G24: =SUMIF('In-ward Register'!$K:$K,Summery!$E:$E,'In-ward Register'!$M:$M) -> 357 | H24: =SUMIF('Out-ward Register'!$D:$D,Summery!$E:$E,'Out-ward Register'!$F:$F) -> 253 | I24: =G24-H24 -> 104 | J24: 15118.36 | K24: =J24*G24 -> 5397254.5 | L24: =J24*H24 -> 3824945.1 | M24: =K24-L24 -> 1572309.4 | O24: =M24/M$2*100 -> 1658.5543
A25: Project-HLC | B25: 544 | C25: 112129061 | D25: S112129084 | E25: S112129084 SOCKET HOUSING ASSEMBLY | F25: Nos | G25: =SUMIF('In-ward Register'!$K:$K,Summery!$E:$E,'In-ward Register'!$M:$M) -> 182 | H25: =SUMIF('Out-ward Register'!$D:$D,Summery!$E:$E,'Out-ward Register'!$F:$F) -> 65 | I25: =G25-H25 -> 117 | J25: 13332 | K25: =J25*G25 -> 2426424 | L25: =J25*H25 -> 866580 | M25: =K25-L25 -> 1559844 | O25: =M25/M$2*100 -> 1645.4051
A26: other | B26: 683 | C26: 109674086 | D26: 5182-78083-01 | E26: HOTEL LOAD FILTER CAPACITOR FOR ELECTRIC LOCOMOTIVE WAP7 UPGRADE 750V / 50HZ / 0.6MF " SPEC NO - A6Z00044012347 REV-A "VISHAY PART NO- ACMKP 1.061/600 µF" | F26: Nos | G26: =SUMIF('In-ward Register'!$K:$K,Summery!$E:$E,'In-ward Register'!$M:$M) -> 30 | H26: =SUMIF('Out-ward Register'!$D:$D,Summery!$E:$E,'Out-ward Register'!$F:$F) -> 0 | I26: =G26-H26 -> 30 | J26: 51400 | K26: =J26*G26 -> 1542000 | L26: =J26*H26 -> 0 | M26: =K26-L26 -> 1542000 | O26: =M26/M$2*100 -> 1626.5823
A27: Project 6K | B27: 1161 | C27: A5E46683174 | D27: SA5E51759588 | E27: SIBCOS-MB_M1305-20-0 | F27: Nos | G27: =SUMIF('In-ward Register'!$K:$K,Summery!$E:$E,'In-ward Register'!$M:$M) -> 8 | H27: =SUMIF('Out-ward Register'!$D:$D,Summery!$E:$E,'Out-ward Register'!$F:$F) -> 0 | I27: =G27-H27 -> 8 | J27: 180000 | K27: =J27*G27 -> 1440000 | L27: =J27*H27 -> 0 | M27: =K27-L27 -> 1440000
A28: Project 6K | B28: 753 | C28: A5E49965045 | D28: A5E49965045 | E28: CU BUSHING FLAG BUSBAR 1 | F28: Nos | G28: =SUMIF('In-ward Register'!$K:$K,Summery!$E:$E,'In-ward Register'!$M:$M) -> 2368 | H28: =SUMIF('Out-ward Register'!$D:$D,Summery!$E:$E,'Out-ward Register'!$F:$F) -> 1616 | I28: =G28-H28 -> 752 | J28: 1798.2 | K28: =J28*G28 -> 4258137.6 | L28: =J28*H28 -> 2905891.2 | M28: =K28-L28 -> 1352246.4 | O28: =M28/M$2*100 -> 1426.4203
A29: Project 6K | B29: 933 | C29: 112148136 | D29: XS1-1113 | E29: 911113 Kaliber-XS1-1113 ( Storage Device) | F29: Nos | G29: =SUMIF('In-ward Register'!$K:$K,Summery!$E:$E,'In-ward Register'!$M:$M) -> 519 | H29: =SUMIF('Out-ward Register'!$D:$D,Summery!$E:$E,'Out-ward Register'!$F:$F) -> 438 | I29: =G29-H29 -> 81 | J29: 16356.12 | K29: =J29*G29 -> 8488826.3 | L29: =J29*H29 -> 7163980.6 | M29: =K29-L29 -> 1324845.7 | O29: =M29/M$2*100 -> 1397.5166
A30: Project 9K | B30: 782 | C30: 108221257 | D30: 590400005 | E30: SPHERIBLOC FOR AXLE GUIDE ROD/TM SUPPORT ARM FOR WAG9/WAP7 LOCO AS PER RDSO SPEC NO. RDSO/2007/EL/SPEC/0051 (REV.3) | F30: Nos | G30: =SUMIF('In-ward Register'!$K:$K,Summery!$E:$E,'In-ward Register'!$M:$M) -> 418 | H30: =SUMIF('Out-ward Register'!$D:$D,Summery!$E:$E,'Out-ward Register'!$F:$F) -> 266 | I30: =G30-H30 -> 152 | J30: 7400 | K30: =J30*G30 -> 3093200 | L30: =J30*H30 -> 1968400 | M30: =K30-L30 -> 1124800 | O30: =M30/M$2*100 -> 1186.4979
A31: Project 9K | B31: 882 | C31: 112169824 | D31: ERLBT153012XXX2 | E31: CABLE 1C X 0.5 SQ MM - 3 GKW - 600 V | F31: Mtr. | G31: =SUMIF('In-ward Register'!$K:$K,Summery!$E:$E,'In-ward Register'!$M:$M) -> 83560 | H31: =SUMIF('Out-ward Register'!$D:$D,Summery!$E:$E,'Out-ward Register'!$F:$F) -> 3323 | I31: =G31-H31 -> 80237 | J31: 13.6 | K31: =J31*G31 -> 1136416 | L31: =J31*H31 -> 45192.8 | M31: =K31-L31 -> 1091223.2 | O31: =M31/M$2*100 -> 1151.0793
A32: Project 6K | B32: 354 | C32: 112172543 | D32: 112172543 | E32: DDU PLATE | F32: Nos | G32: =SUMIF('In-ward Register'!$K:$K,Summery!$E:$E,'In-ward Register'!$M:$M) -> 1120 | H32: =SUMIF('Out-ward Register'!$D:$D,Summery!$E:$E,'Out-ward Register'!$F:$F) -> 813 | I32: =G32-H32 -> 307 | J32: 3480 | K32: =J32*G32 -> 3897600 | L32: =J32*H32 -> 2829240 | M32: =K32-L32 -> 1068360 | O32: =M32/M$2*100 -> 1126.962
A33: Project 6K | B33: 1182 | C33: A5E46681280 | D33: SA5E43995136 | E33: WAG9 6K Rectifier assly | F33: Nos | G33: =SUMIF('In-ward Register'!$K:$K,Summery!$E:$E,'In-ward Register'!$M:$M) -> 5 | H33: =SUMIF('Out-ward Register'!$D:$D,Summery!$E:$E,'Out-ward Register'!$F:$F) -> 0 | I33: =G33-H33 -> 5 | J33: 213300 | K33: =J33*G33 -> 1066500 | L33: =J33*H33 -> 0 | M33: =K33-L33 -> 1066500
A34: other | B34: 682 | C34: 109688221 | D34: 157-58345674 | E34: CONTACTOR 3P 900V 700A 110V DC Z00194A DC 201932524982 | F34: Nos | G34: =SUMIF('In-ward Register'!$K:$K,Summery!$E:$E,'In-ward Register'!$M:$M) -> 9 | H34: =SUMIF('Out-ward Register'!$D:$D,Summery!$E:$E,'Out-ward Register'!$F:$F) -> 0 | I34: =G34-H34 -> 9 | J34: 116579 | K34: =J34*G34 -> 1049211 | L34: =J34*H34 -> 0 | M34: =K34-L34 -> 1049211 | O34: =M34/M$2*100 -> 1106.7627
A35: Project 6K | B35: 691 | C35: 110710684 | D35: Item3 WAG9-6K-EN3-TES-01 | E35: Braided Busbars Item3 WAG9-6K-EN3-TES-01 | F35: Nos | G35: =SUMIF('In-ward Register'!$K:$K,Summery!$E:$E,'In-ward Register'!$M:$M) -> 2064 | H35: =SUMIF('Out-ward Register'!$D:$D,Summery!$E:$E,'Out-ward Register'!$F:$F) -> 1656 | I35: =G35-H35 -> 408 | J35: 2548 | K35: =J35*G35 -> 5259072 | L35: =J35*H35 -> 4219488 | M35: =K35-L35 -> 1039584 | O35: =M35/M$2*100 -> 1096.6076
A36: other | B36: 568 | C36: 100720304 | D36: 6702ED694 | E36: AC CONTACTOR-2 POLE 6702ED694 | F36: Nos | G36: =SUMIF('In-ward Register'!$K:$K,Summery!$E:$E,'In-ward Register'!$M:$M) -> 38 | H36: =SUMIF('Out-ward Register'!$D:$D,Summery!$E:$E,'Out-ward Register'!$F:$F) -> 0 | I36: =G36-H36 -> 38 | J36: 26702 | K36: =J36*G36 -> 1014676 | L36: =J36*H36 -> 0 | M36: =K36-L36 -> 1014676 | O36: =M36/M$2*100 -> 1070.3333
A37: Project 6K | B37: 702 | C37: 112161405 | D37: Laptop | E37: LAPTOP HP 240 G8 INTEL CORE I3 11TH GEN PROCESSOR/8GB RAM , 512 GB SSD | F37: Nos | G37: =SUMIF('In-ward Register'!$K:$K,Summery!$E:$E,'In-ward Register'!$M:$M) -> 48 | H37: =SUMIF('Out-ward Register'!$D:$D,Summery!$E:$E,'Out-ward Register'!$F:$F) -> 27 | I37: =G37-H37 -> 21 | J37: 44377.78 | K37: =J37*G37 -> 2130133.4 | L37: =J37*H37 -> 1198200.1 | M37: =K37-L37 -> 931933.38 | O37: =M37/M$2*100 -> 983.05209
A38: Project-HLC | B38: 1023 | C38: 105988752 | D38: SA2V00156028459 | E38: SA2V00156028459 CONTACTOR 1000A 2000V SE | F38: Nos | G38: =SUMIF('In-ward Register'!$K:$K,Summery!$E:$E,'In-ward Register'!$M:$M) -> 15 | H38: =SUMIF('Out-ward Register'!$D:$D,Summery!$E:$E,'Out-ward Register'!$F:$F) -> 8 | I38: =G38-H38 -> 7 | J38: 128000 | K38: =J38*G38 -> 1920000 | L38: =J38*H38 -> 1024000 | M38: =K38-L38 -> 896000
A39: Project 6K | B39: 1015 | C39: 113837420 | D39: 4414N | E39: Electric Fan (4414 N EBM past) | F39: Nos | G39: =SUMIF('In-ward Register'!$K:$K,Summery!$E:$E,'In-ward Register'!$M:$M) -> 656 | H39: =SUMIF('Out-ward Register'!$D:$D,Summery!$E:$E,'Out-ward Register'!$F:$F) -> 505 | I39: =G39-H39 -> 151 | J39: 5800 | K39: =J39*G39 -> 3804800 | L39: =J39*H39 -> 2929000 | M39: =K39-L39 -> 875800
A40: other | B40: 548 | C40: 108221274 | D40: 108221274 | E40: HELICAL SPRINGS FOR WAP7 PRIMERY SPRING | F40: Nos | G40: =SUMIF('In-ward Register'!$K:$K,Summery!$E:$E,'In-ward Register'!$M:$M) -> 64 | H40: =SUMIF('Out-ward Register'!$D:$D,Summery!$E:$E,'Out-ward Register'!$F:$F) -> 0 | I40: =G40-H40 -> 64 | J40: 13338 | K40: =J40*G40 -> 853632 | L40: =J40*H40 -> 0 | M40: =K40-L40 -> 853632 | O40: =M40/M$2*100 -> 900.4557
A41: Project-HLC | B41: 1007 | C41: 105401096 | D41: SA2V00001666501 | E41: CAP POLYEST 600uF 750V A SA2V00001666501 | F41: Nos | G41: =SUMIF('In-ward Register'!$K:$K,Summery!$E:$E,'In-ward Register'!$M:$M) -> 31 | H41: =SUMIF('Out-ward Register'!$D:$D,Summery!$E:$E,'Out-ward Register'!$F:$F) -> 14 | I41: =G41-H41 -> 17 | J41: 50000 | K41: =J41*G41 -> 1550000 | L41: =J41*H41 -> 700000 | M41: =K41-L41 -> 850000
A42: Project-HLC | B42: 1152 | C42: A5E38077215 | D42: SA5E35109075 | E42: A2V00001450988 HLC PWR SPAR15 | F42: Nos | G42: =SUMIF('In-ward Register'!$K:$K,Summery!$E:$E,'In-ward Register'!$M:$M) -> 14 | H42: =SUMIF('Out-ward Register'!$D:$D,Summery!$E:$E,'Out-ward Register'!$F:$F) -> 13 | I42: =G42-H42 -> 1 | J42: 840500 | K42: =J42*G42 -> 11767000 | L42: =J42*H42 -> 10926500 | M42: =K42-L42 -> 840500
A43: other | B43: 594 | C43: 100712728 | D43: 12545534 | E43: RADOX TRACTION CABLE BK 4GKW-AX 1800V 1 X 150M | F43: Mtr. | G43: =SUMIF('In-ward Register'!$K:$K,Summery!$E:$E,'In-ward Register'!$M:$M) -> 610 | H43: =SUMIF('Out-ward Register'!$D:$D,Summery!$E:$E,'Out-ward Register'!$F:$F) -> 0 | I43: =G43-H43 -> 610 | J43: 1375 | K43: =J43*G43 -> 838750 | L43: =J43*H43 -> 0 | M43: =K43-L43 -> 838750 | O43: =M43/M$2*100 -> 884.75738
A44: Project 6K | B44: 17 | C44: 109492194 | D44: 61030012010 | E44: HARTING INDU COM 9P 1T ENTRY HEX SCREW 4-40 P.N. 61030012010 | F44: Nos | G44: =SUMIF('In-ward Register'!$K:$K,Summery!$E:$E,'In-ward Register'!$M:$M) -> 11224 | H44: =SUMIF('Out-ward Register'!$D:$D,Summery!$E:$E,'Out-ward Register'!$F:$F) -> 7732 | I44: =G44-H44 -> 3492 | J44: 234.9 | K44: =J44*G44 -> 2636517.6 | L44: =J44*H44 -> 1816246.8 | M44: =K44-L44 -> 820270.8 | O44: =M44/M$2*100 -> 865.26456 | Q44: 17
A45: Project 6K | B45: 153 | C45: 111400054 | D45: MS3474W12-3P-SQSC-00022983 | E45: AMPHENOL PART NO:- MS3474W12-3P-SQSC-00022983 | F45: Nos | G45: =SUMIF('In-ward Register'!$K:$K,Summery!$E:$E,'In-ward Register'!$M:$M) -> 3210 | H45: =SUMIF('Out-ward Register'!$D:$D,Summery!$E:$E,'Out-ward Register'!$F:$F) -> 2654 | I45: =G45-H45 -> 556 | J45: 1410 | K45: =J45*G45 -> 4526100 | L45: =J45*H45 -> 3742140 | M45: =K45-L45 -> 783960 | O45: =M45/M$2*100 -> 826.96203
A46: Project 6K | B46: 963 | C46: 109563338 | D46: 857-409 (60498872) | E46: Isolation amplifier; Current and voltage 857-409 | F46: Nos | G46: =SUMIF('In-ward Register'!$K:$K,Summery!$E:$E,'In-ward Register'!$M:$M) -> 166 | H46: =SUMIF('Out-ward Register'!$D:$D,Summery!$E:$E,'Out-ward Register'!$F:$F) -> 114 | I46: =G46-H46 -> 52 | J46: 14744.35 | K46: =J46*G46 -> 2447562.1 | L46: =J46*H46 -> 1680855.9 | M46: =K46-L46 -> 766706.2
A47: Project 9K | B47: 943 | C47: 108296493 | E47: Traction Motor Blower Sr. No. 22M64AF55 & 22M64AF56 Traction Motor Blower including Motor | F47: Nos | G47: =SUMIF('In-ward Register'!$K:$K,Summery!$E:$E,'In-ward Register'!$M:$M) -> 2 | H47: =SUMIF('Out-ward Register'!$D:$D,Summery!$E:$E,'Out-ward Register'!$F:$F) -> 0 | I47: =G47-H47 -> 2 | J47: 380000 | K47: =J47*G47 -> 760000 | L47: =J47*H47 -> 0 | M47: =K47-L47 -> 760000
A48: Project-HLC | B48: 930 | C48: 105988750 | D48: SA2V00150267634 | E48: SA2V00150267634 Combined seal___EPDM/VA- | F48: Mtr. | G48: =SUMIF('In-ward Register'!$K:$K,Summery!$E:$E,'In-ward Register'!$M:$M) -> 500 | H48: =SUMIF('Out-ward Register'!$D:$D,Summery!$E:$E,'Out-ward Register'!$F:$F) -> 50 | I48: =G48-H48 -> 450 | J48: 1648 | K48: =J48*G48 -> 824000 | L48: =J48*H48 -> 82400 | M48: =K48-L48 -> 741600 | O48: =M48/M$2*100 -> 782.27848
A49: Project 6K | B49: 867 | C49: 111382476 | D49: RRM2-COIN 208-001 | E49: MODULE RRM2-COIN 208MAKE AMIT,SPOL.S R.O | F49: Nos | G49: =SUMIF('In-ward Register'!$K:$K,Summery!$E:$E,'In-ward Register'!$M:$M) -> 8 | H49: =SUMIF('Out-ward Register'!$D:$D,Summery!$E:$E,'Out-ward Register'!$F:$F) -> 0 | I49: =G49-H49 -> 8 | J49: 92320 | K49: =J49*G49 -> 738560 | L49: =J49*H49 -> 0 | M49: =K49-L49 -> 738560 | O49: =M49/M$2*100 -> 779.07173
A50: Project 9K | B50: 942 | C50: 108296494 | E50: Oil Cooling unit Sr. No 32301AF2582 & 32301AF2583 BLOWER FOR OIL COOLING UNIT WITH CASING INCLUDING 30KW MOTOR FOR OIL COOLING UNIT | F50: Nos | G50: =SUMIF('In-ward Register'!$K:$K,Summery!$E:$E,'In-ward Register'!$M:$M) -> 2 | H50: =SUMIF('Out-ward Register'!$D:$D,Summery!$E:$E,'Out-ward Register'!$F:$F) -> 0 | I50: =G50-H50 -> 2 | J50: 355000 | K50: =J50*G50 -> 710000 | L50: =J50*H50 -> 0 | M50: =K50-L50 -> 710000
A51: Project 6K | B51: 1147 | C51: A5E52828826 | D51: SA5E03370286 | E51: TCN-GW, position C027 6FH9415-3KY60 | F51: Nos | G51: =SUMIF('In-ward Register'!$K:$K,Summery!$E:$E,'In-ward Register'!$M:$M) -> 5 | H51: =SUMIF('Out-ward Register'!$D:$D,Summery!$E:$E,'Out-ward Register'!$F:$F) -> 0 | I51: =G51-H51 -> 5 | J51: 140600 | K51: =J51*G51 -> 703000 | L51: =J51*H51 -> 0 | M51: =K51-L51 -> 703000
A52: Project 9K | B52: 974 | C52: 108311392 | E52: Battery Charger Aux, Sr. No 19100002, 22090024, 22090018,22090019 | F52: Nos | G52: =SUMIF('In-ward Register'!$K:$K,Summery!$E:$E,'In-ward Register'!$M:$M) -> 4 | H52: =SUMIF('Out-ward Register'!$D:$D,Summery!$E:$E,'Out-ward Register'!$F:$F) -> 1 | I52: =G52-H52 -> 3 | J52: 229000 | K52: =J52*G52 -> 916000 | L52: =J52*H52 -> 229000 | M52: =K52-L52 -> 687000
A53: Project 6K | B53: 1138 | C53: A5E45983547 | D53: SA1A650663 | E53: SA1A650663 Line disconnector | F53: Nos | G53: =SUMIF('In-ward Register'!$K:$K,Summery!$E:$E,'In-ward Register'!$M:$M) -> 5 | H53: =SUMIF('Out-ward Register'!$D:$D,Summery!$E:$E,'Out-ward Register'!$F:$F) -> 0 | I53: =G53-H53 -> 5 | J53: 133500 | K53: =J53*G53 -> 667500 | L53: =J53*H53 -> 0 | M53: =K53-L53 -> 667500
A54: Project 6K | B54: 1021 | C54: 113769815 | D54: 906W0802 | E54: 2 Core x 0.75 SQ MM Black Cable | F54: Mtr. | G54: =SUMIF('In-ward Register'!$K:$K,Summery!$E:$E,'In-ward Register'!$M:$M) -> 10641 | H54: =SUMIF('Out-ward Register'!$D:$D,Summery!$E:$E,'Out-ward Register'!$F:$F) -> 3635 | I54: =G54-H54 -> 7006 | J54: 95.2 | K54: =J54*G54 -> 1013023.2 | L54: =J54*H54 -> 346052 | M54: =K54-L54 -> 666971.2
A55: 2x130 kVA Static Inverter (SIV | B55: 1196 | C55: A5E51759588 | E55: SIBCOS -MB_M1305-20-0 | F55: Nos | G55: =SUMIF('In-ward Register'!$K:$K,Summery!$E:$E,'In-ward Register'!$M:$M) -> 5 | H55: =SUMIF('Out-ward Register'!$D:$D,Summery!$E:$E,'Out-ward Register'!$F:$F) -> 0 | I55: =G55-H55 -> 5 | J55: 132227 | K55: =J55*G55 -> 661135 | L55: =J55*H55 -> 0 | M55: =K55-L55 -> 661135
A56: Project 6K | B56: 1046 | C56: A5E52819319 | D56: SA5E44269032 | E56: SA5E44269032_ICU-PWR 6FH9675-3BX8-0JJ4 | F56: Nos | G56: =SUMIF('In-ward Register'!$K:$K,Summery!$E:$E,'In-ward Register'!$M:$M) -> 5 | H56: =SUMIF('Out-ward Register'!$D:$D,Summery!$E:$E,'Out-ward Register'!$F:$F) -> 0 | I56: =G56-H56 -> 5 | J56: 131000 | K56: =J56*G56 -> 655000 | L56: =J56*H56 -> 0 | M56: =K56-L56 -> 655000
A57: Project 6K | B57: 1191 | C57: A5E52828762 | D57: A5E44268898 | E57: ICU-PWR 6FH9675-3BX8-0JJ2 | F57: Nos | G57: =SUMIF('In-ward Register'!$K:$K,Summery!$E:$E,'In-ward Register'!$M:$M) -> 5 | H57: =SUMIF('Out-ward Register'!$D:$D,Summery!$E:$E,'Out-ward Register'!$F:$F) -> 0 | I57: =G57-H57 -> 5 | J57: 131000 | K57: =J57*G57 -> 655000 | L57: =J57*H57 -> 0 | M57: =K57-L57 -> 655000
A58: Project 6K | B58: 1184 | C58: A5E46683156 | D58: SA5E43795246 | E58: Battery charger WAG9 | F58: Nos | G58: =SUMIF('In-ward Register'!$K:$K,Summery!$E:$E,'In-ward Register'!$M:$M) -> 5 | H58: =SUMIF('Out-ward Register'!$D:$D,Summery!$E:$E,'Out-ward Register'!$F:$F) -> 3 | I58: =G58-H58 -> 2 | J58: 315000 | K58: =J58*G58 -> 1575000 | L58: =J58*H58 -> 945000 | M58: =K58-L58 -> 630000
A59: Project 6K | B59: 1133 | C59: A5E45983575 | D59: SA5E43549982 | E59: SA5E43549982 WAG9 TCC 6K Pump | F59: Nos | G59: =SUMIF('In-ward Register'!$K:$K,Summery!$E:$E,'In-ward Register'!$M:$M) -> 7 | H59: =SUMIF('Out-ward Register'!$D:$D,Summery!$E:$E,'Out-ward Register'!$F:$F) -> 0 | I59: =G59-H59 -> 7 | J59: 89000 | K59: =J59*G59 -> 623000 | L59: =J59*H59 -> 0 | M59: =K59-L59 -> 623000
A60: Project 6K | B60: 192 | C60: 110408290 | D60: 110408290 | E60: SENSOR PLATE SS 3MM 114 X 114MM sensor plate CLW/es/3/sk-2/153_rev_4 | F60: Nos | G60: =SUMIF('In-ward Register'!$K:$K,Summery!$E:$E,'In-ward Register'!$M:$M) -> 3618 | H60: =SUMIF('Out-ward Register'!$D:$D,Summery!$E:$E,'Out-ward Register'!$F:$F) -> 2490 | I60: =G60-H60 -> 1128 | J60: 540.55 | K60: =J60*G60 -> 1955709.9 | L60: =J60*H60 -> 1345969.5 | M60: =K60-L60 -> 609740.4 | O60: =M60/M$2*100 -> 643.18608
A61: Project 6K | B61: 1021 | C61: 113831700 | E61: Pin Crimping tool,9990000001(Harting) | F61: Nos | G61: =SUMIF('In-ward Register'!$K:$K,Summery!$E:$E,'In-ward Register'!$M:$M) -> 10 | H61: =SUMIF('Out-ward Register'!$D:$D,Summery!$E:$E,'Out-ward Register'!$F:$F) -> 0 | I61: =G61-H61 -> 10 | J61: 58400 | K61: =J61*G61 -> 584000 | L61: =J61*H61 -> 0 | M61: =K61-L61 -> 584000
A62: Project 9K | B62: 883 | C62: 112169826 | D62: ERLBT5L012XXX2 | E62: CABLE 1C X 185 – 4 GKW (1.8/3 KV) | F62: Mtr. | G62: =SUMIF('In-ward Register'!$K:$K,Summery!$E:$E,'In-ward Register'!$M:$M) -> 3889 | H62: =SUMIF('Out-ward Register'!$D:$D,Summery!$E:$E,'Out-ward Register'!$F:$F) -> 3594 | I62: =G62-H62 -> 295 | J62: 1959 | K62: =J62*G62 -> 7618551 | L62: =J62*H62 -> 7040646 | M62: =K62-L62 -> 577905 | O62: =M62/M$2*100 -> 609.60443
A63: Project-HLC | B63: 1180 | C63: 107081830 | D63: SA2V00001856027 | E63: IGBT -DRV-3K3-1200-03 | F63: Nos | G63: =SUMIF('In-ward Register'!$K:$K,Summery!$E:$E,'In-ward Register'!$M:$M) -> 20 | H63: =SUMIF('Out-ward Register'!$D:$D,Summery!$E:$E,'Out-ward Register'!$F:$F) -> 0 | I63: =G63-H63 -> 20 | J63: 28000 | K63: =J63*G63 -> 560000 | L63: =J63*H63 -> 0 | M63: =K63-L63 -> 560000
A64: Project 6K | B64: 1176 | C64: A5E46683201 | D64: SA5E51351211 | E64: SA5E51351211 - SIBCOS-MB_M2005-33-0 | F64: Nos | G64: =SUMIF('In-ward Register'!$K:$K,Summery!$E:$E,'In-ward Register'!$M:$M) -> 8 | H64: =SUMIF('Out-ward Register'!$D:$D,Summery!$E:$E,'Out-ward Register'!$F:$F) -> 0 | I64: =G64-H64 -> 8 | J64: 69652 | K64: =J64*G64 -> 557216 | L64: =J64*H64 -> 0 | M64: =K64-L64 -> 557216
A65: Project 6K | B65: 372 | C65: 112139784 | D65: TCP-V0 20MM | E65: Expendo TCP-V0 20MM | F65: Mtr. | G65: =SUMIF('In-ward Register'!$K:$K,Summery!$E:$E,'In-ward Register'!$M:$M) -> 46791 | H65: =SUMIF('Out-ward Register'!$D:$D,Summery!$E:$E,'Out-ward Register'!$F:$F) -> 25614 | I65: =G65-H65 -> 21177 | J65: 25.86 | K65: =J65*G65 -> 1210015.3 | L65: =J65*H65 -> 662378.04 | M65: =K65-L65 -> 547637.22 | O65: =M65/M$2*100 -> 577.67639
A66: Project 6K | B66: 474 | C66: 107171952 | D66: 99148781208 | E66: BINDER CONNECTOR 8 POLE /AWG20 TIGHTENING TORQUE 0.2NM PN 99148781208 | F66: Nos | G66: =SUMIF('In-ward Register'!$K:$K,Summery!$E:$E,'In-ward Register'!$M:$M) -> 1260 | H66: =SUMIF('Out-ward Register'!$D:$D,Summery!$E:$E,'Out-ward Register'!$F:$F) -> 920 | I66: =G66-H66 -> 340 | J66: 1560 | K66: =J66*G66 -> 1965600 | L66: =J66*H66 -> 1435200 | M66: =K66-L66 -> 530400 | O66: =M66/M$2*100 -> 559.49367
A67: Project 6K | B67: 1173 | C67: A5E52828776 | D67: SA5E44381596 | E67: SA5E44381596_\ICU-PWR 6FH9675-3BX8-0JJ3 | F67: Nos | G67: =SUMIF('In-ward Register'!$K:$K,Summery!$E:$E,'In-ward Register'!$M:$M) -> 4 | H67: =SUMIF('Out-ward Register'!$D:$D,Summery!$E:$E,'Out-ward Register'!$F:$F) -> 0 | I67: =G67-H67 -> 4 | J67: 131000 | K67: =J67*G67 -> 524000 | L67: =J67*H67 -> 0 | M67: =K67-L67 -> 524000
A68: other | B68: 1007 | C68: 113722716 | D68: M22520/2-01 | E68: HARWIN Hand Ratcheting Crimping Tool M22520/2-01 | F68: Nos | G68: =SUMIF('In-ward Register'!$K:$K,Summery!$E:$E,'In-ward Register'!$M:$M) -> 20 | H68: =SUMIF('Out-ward Register'!$D:$D,Summery!$E:$E,'Out-ward Register'!$F:$F) -> 8 | I68: =G68-H68 -> 12 | J68: 42350 | K68: =J68*G68 -> 847000 | L68: =J68*H68 -> 338800 | M68: =K68-L68 -> 508200
A69: Project-HLC | B69: 37 | C69: 107143203 | D69: 107143203 | E69: PANEL LIFTING ARRANGEMENT LOA LIMIT-2MT (TACKLER) | F69: Nos | G69: =SUMIF('In-ward Register'!$K:$K,Summery!$E:$E,'In-ward Register'!$M:$M) -> 8 | H69: =SUMIF('Out-ward Register'!$D:$D,Summery!$E:$E,'Out-ward Register'!$F:$F) -> 2 | I69: =G69-H69 -> 6 | J69: 84537.5 | K69: =J69*G69 -> 676300 | L69: =J69*H69 -> 169075 | M69: =K69-L69 -> 507225 | O69: =M69/M$2*100 -> 535.04747
A70: Project 9K | B70: 124 | C70: 109492247 | D70: 20772083003 | E70: HARTING ETHERNET SWITCH Ha-VIS eCon 4080-B3 20772083003 | F70: Nos | G70: =SUMIF('In-ward Register'!$K:$K,Summery!$E:$E,'In-ward Register'!$M:$M) -> 87 | H70: =SUMIF('Out-ward Register'!$D:$D,Summery!$E:$E,'Out-ward Register'!$F:$F) -> 75 | I70: =G70-H70 -> 12 | J70: 40838.07 | K70: =J70*G70 -> 3552912.1 | L70: =J70*H70 -> 3062855.2 | M70: =K70-L70 -> 490056.84 | O70: =M70/M$2*100 -> 516.93759
A71: other | B71: 578 | C71: 100140225 | D71: 3TC5217-0LF4 | E71: 3TC5217-0LF4 \CONTACTOR SIZE 8 2-POLE | F71: Nos | G71: =SUMIF('In-ward Register'!$K:$K,Summery!$E:$E,'In-ward Register'!$M:$M) -> 20 | H71: =SUMIF('Out-ward Register'!$D:$D,Summery!$E:$E,'Out-ward Register'!$F:$F) -> 0 | I71: =G71-H71 -> 20 | J71: 23747.12 | K71: =J71*G71 -> 474942.4 | L71: =J71*H71 -> 0 | M71: =K71-L71 -> 474942.4 | O71: =M71/M$2*100 -> 500.99409 | P71: BIN -1 BIG
A72: Project 6K | B72: 5 | C72: 112136075 | D72: 09300240581 | E72: HARTING Hood Female HAN 24B-GS-ZV-29 '09300240581 | F72: Nos | G72: =SUMIF('In-ward Register'!$K:$K,Summery!$E:$E,'In-ward Register'!$M:$M) -> 1262 | H72: =SUMIF('Out-ward Register'!$D:$D,Summery!$E:$E,'Out-ward Register'!$F:$F) -> 874 | I72: =G72-H72 -> 388 | J72: 1196.19 | K72: =J72*G72 -> 1509591.8 | L72: =J72*H72 -> 1045470.1 | M72: =K72-L72 -> 464121.72 | O72: =M72/M$2*100 -> 489.57987
A73: Project 9K | B73: 363 | C73: 109492221 | D73: 21038212505 | E73: M12 SLIM FEMALE CRIMP 4/5 POL A COD 21038212505 | F73: Nos | G73: =SUMIF('In-ward Register'!$K:$K,Summery!$E:$E,'In-ward Register'!$M:$M) -> 851 | H73: =SUMIF('Out-ward Register'!$D:$D,Summery!$E:$E,'Out-ward Register'!$F:$F) -> 364 | I73: =G73-H73 -> 487 | J73: 939.33 | K73: =J73*G73 -> 799369.83 | L73: =J73*H73 -> 341916.12 | M73: =K73-L73 -> 457453.71 | O73: =M73/M$2*100 -> 482.54611
A74: 2x130 kVA Static Inverter (SIV | B74: 1215 | C74: A5E47255278 | E74: DC_Link_Choke_26mH_165A | F74: Nos | G74: =SUMIF('In-ward Register'!$K:$K,Summery!$E:$E,'In-ward Register'!$M:$M) -> 2 | H74: =SUMIF('Out-ward Register'!$D:$D,Summery!$E:$E,'Out-ward Register'!$F:$F) -> 0 | I74: =G74-H74 -> 2 | J74: 226262 | K74: =J74*G74 -> 452524 | L74: =J74*H74 -> 0 | M74: =K74-L74 -> 452524
A75: Project 6K | B75: 1186 | C75: 101965762 | D75: S102124251 | E75: FAN 110VDC Axial 7210N-70181 | F75: Nos | G75: =SUMIF('In-ward Register'!$K:$K,Summery!$E:$E,'In-ward Register'!$M:$M) -> 58 | H75: =SUMIF('Out-ward Register'!$D:$D,Summery!$E:$E,'Out-ward Register'!$F:$F) -> 0 | I75: =G75-H75 -> 58 | J75: 7600 | K75: =J75*G75 -> 440800 | L75: =J75*H75 -> 0 | M75: =K75-L75 -> 440800
A76: Project 6K | B76: 334 | C76: 111402534 | D76: 2101P1001 | E76: L-SHAP BUS BAR FOR WAG9 6K TCC | F76: Nos | G76: =SUMIF('In-ward Register'!$K:$K,Summery!$E:$E,'In-ward Register'!$M:$M) -> 3086 | H76: =SUMIF('Out-ward Register'!$D:$D,Summery!$E:$E,'Out-ward Register'!$F:$F) -> 2149 | I76: =G76-H76 -> 937 | J76: 469.44 | K76: =J76*G76 -> 1448691.8 | L76: =J76*H76 -> 1008826.6 | M76: =K76-L76 -> 439865.28 | O76: =M76/M$2*100 -> 463.99291
A77: Project 6K | B77: 1060 | C77: 115010962 | E77: Socket contact size 12, 2.5mm² 10-40560- | F77: Nos | G77: =SUMIF('In-ward Register'!$K:$K,Summery!$E:$E,'In-ward Register'!$M:$M) -> 3384 | H77: =SUMIF('Out-ward Register'!$D:$D,Summery!$E:$E,'Out-ward Register'!$F:$F) -> 640 | I77: =G77-H77 -> 2744 | J77: 160 | K77: =J77*G77 -> 541440 | L77: =J77*H77 -> 102400 | M77: =K77-L77 -> 439040
A78: other | B78: 546 | C78: 108221274 | D78: 108221274 | E78: HELICAL SPRINGS FOR WAP7 SECONDARY SPRING | F78: Nos | G78: =SUMIF('In-ward Register'!$K:$K,Summery!$E:$E,'In-ward Register'!$M:$M) -> 32 | H78: =SUMIF('Out-ward Register'!$D:$D,Summery!$E:$E,'Out-ward Register'!$F:$F) -> 0 | I78: =G78-H78 -> 32 | J78: 13338 | K78: =J78*G78 -> 426816 | L78: =J78*H78 -> 0 | M78: =K78-L78 -> 426816 | O78: =M78/M$2*100 -> 450.22785
A79: other | B79: 549 | C79: 108221274 | D79: 108221274 | E79: HELICAL SPRINGS FOR WAP7 PRIMERY SPRING MID AXLE OUTER | F79: Nos | G79: =SUMIF('In-ward Register'!$K:$K,Summery!$E:$E,'In-ward Register'!$M:$M) -> 32 | H79: =SUMIF('Out-ward Register'!$D:$D,Summery!$E:$E,'Out-ward Register'!$F:$F) -> 0 | I79: =G79-H79 -> 32 | J79: 13338 | K79: =J79*G79 -> 426816 | L79: =J79*H79 -> 0 | M79: =K79-L79 -> 426816 | O79: =M79/M$2*100 -> 450.22785
A80: other | B80: 550 | C80: 108221274 | D80: 108221274 | E80: HELICAL SPRINGS FOR WAP7 PRIMERY SPRING MID AXLE INNER | F80: Nos | G80: =SUMIF('In-ward Register'!$K:$K,Summery!$E:$E,'In-ward Register'!$M:$M) -> 32 | H80: =SUMIF('Out-ward Register'!$D:$D,Summery!$E:$E,'Out-ward Register'!$F:$F) -> 0 | I80: =G80-H80 -> 32 | J80: 13338 | K80: =J80*G80 -> 426816 | L80: =J80*H80 -> 0 | M80: =K80-L80 -> 426816 | O80: =M80/M$2*100 -> 450.22785
A81: other | B81: 569 | C81: 100720311 | D81: 6702ED695 | E81: AC CONTACTOR-3 POLE 6702ED695 | F81: Nos | G81: =SUMIF('In-ward Register'!$K:$K,Summery!$E:$E,'In-ward Register'!$M:$M) -> 14 | H81: =SUMIF('Out-ward Register'!$D:$D,Summery!$E:$E,'Out-ward Register'!$F:$F) -> 0 | I81: =G81-H81 -> 14 | J81: 30134 | K81: =J81*G81 -> 421876 | L81: =J81*H81 -> 0 | M81: =K81-L81 -> 421876 | O81: =M81/M$2*100 -> 445.01688 | P81: BIN -1 BIG
A82: Project-HLC | B82: 936 | C82: 113562221 | D82: 113562221 | E82: IV Coupler Locking Handle(Ratchet arrangement) | F82: Nos | G82: =SUMIF('In-ward Register'!$K:$K,Summery!$E:$E,'In-ward Register'!$M:$M) -> 110 | H82: =SUMIF('Out-ward Register'!$D:$D,Summery!$E:$E,'Out-ward Register'!$F:$F) -> 35 | I82: =G82-H82 -> 75 | J82: 5500 | K82: =J82*G82 -> 605000 | L82: =J82*H82 -> 192500 | M82: =K82-L82 -> 412500 | O82: =M82/M$2*100 -> 435.12658
A83: Project 6K | B83: 693 | C83: 109609634 | D83: 21038812425 | E83: PFT Slim design female D-coded 21038812425 | F83: Nos | G83: =SUMIF('In-ward Register'!$K:$K,Summery!$E:$E,'In-ward Register'!$M:$M) -> 1300 | H83: =SUMIF('Out-ward Register'!$D:$D,Summery!$E:$E,'Out-ward Register'!$F:$F) -> 917 | I83: =G83-H83 -> 383 | J83: 1069.11 | K83: =J83*G83 -> 1389843 | L83: =J83*H83 -> 980373.87 | M83: =K83-L83 -> 409469.13 | O83: =M83/M$2*100 -> 431.92946
A84: Project-HLC | B84: 1018 | C84: A5E39926148 | D84: SA5E32619283 | E84: HLC flat band Cable | F84: Nos | G84: =SUMIF('In-ward Register'!$K:$K,Summery!$E:$E,'In-ward Register'!$M:$M) -> 48 | H84: =SUMIF('Out-ward Register'!$D:$D,Summery!$E:$E,'Out-ward Register'!$F:$F) -> 24 | I84: =G84-H84 -> 24 | J84: 17000 | K84: =J84*G84 -> 816000 | L84: =J84*H84 -> 408000 | M84: =K84-L84 -> 408000
A85: Project 6K | B85: 724 | C85: 112172541 | D85: 112172541 | E85: DDU Plate Bracket | F85: Nos | G85: =SUMIF('In-ward Register'!$K:$K,Summery!$E:$E,'In-ward Register'!$M:$M) -> 1565 | H85: =SUMIF('Out-ward Register'!$D:$D,Summery!$E:$E,'Out-ward Register'!$F:$F) -> 927 | I85: =G85-H85 -> 638 | J85: 630 | K85: =J85*G85 -> 985950 | L85: =J85*H85 -> 584010 | M85: =K85-L85 -> 401940 | O85: =M85/M$2*100 -> 423.98734
A86: Project 9K | B86: 899 | C86: - | D86: - | E86: Aux trafo Cubicle Assembly | F86: Nos | G86: =SUMIF('In-ward Register'!$K:$K,Summery!$E:$E,'In-ward Register'!$M:$M) -> 1 | H86: =SUMIF('Out-ward Register'!$D:$D,Summery!$E:$E,'Out-ward Register'!$F:$F) -> 0 | I86: =G86-H86 -> 1 | J86: 400000 | K86: =J86*G86 -> 400000 | L86: =J86*H86 -> 0 | M86: =K86-L86 -> 400000 | O86: =M86/M$2*100 -> 421.94093
A87: Project-HLC | B87: 1010 | C87: 101575929 | D87: S100713950 | E87: I/O MODULE M9000 FOR ACU-EMU S100713950 | F87: Nos | G87: =SUMIF('In-ward Register'!$K:$K,Summery!$E:$E,'In-ward Register'!$M:$M) -> 35 | H87: =SUMIF('Out-ward Register'!$D:$D,Summery!$E:$E,'Out-ward Register'!$F:$F) -> 27 | I87: =G87-H87 -> 8 | J87: 49000 | K87: =J87*G87 -> 1715000 | L87: =J87*H87 -> 1323000 | M87: =K87-L87 -> 392000
A88: Project 6K | B88: 1183 | C88: A5E46682698 | D88: SA5E42598768 | E88: PWM Inverter WAG9 | F88: Nos | G88: =SUMIF('In-ward Register'!$K:$K,Summery!$E:$E,'In-ward Register'!$M:$M) -> 3 | H88: =SUMIF('Out-ward Register'!$D:$D,Summery!$E:$E,'Out-ward Register'!$F:$F) -> 2 | I88: =G88-H88 -> 1 | J88: 390000 | K88: =J88*G88 -> 1170000 | L88: =J88*H88 -> 780000 | M88: =K88-L88 -> 390000
A89: Project 6K | B89: 866 | C89: 111381218 | D89: RRM2-CION 108-001 | E89: MODULE RRM2-CION 108 MAKE AMIT,SPOL. | F89: Nos | G89: =SUMIF('In-ward Register'!$K:$K,Summery!$E:$E,'In-ward Register'!$M:$M) -> 4 | H89: =SUMIF('Out-ward Register'!$D:$D,Summery!$E:$E,'Out-ward Register'!$F:$F) -> 0 | I89: =G89-H89 -> 4 | J89: 93822 | K89: =J89*G89 -> 375288 | L89: =J89*H89 -> 0 | M89: =K89-L89 -> 375288 | O89: =M89/M$2*100 -> 395.87342
A90: Project 6K | B90: 868 | C90: 111381218 | D90: RRM2-CION 108-002 | E90: MODULE RRM2-CION 108 MAKE AMIT, SPOL. | F90: Nos | G90: =SUMIF('In-ward Register'!$K:$K,Summery!$E:$E,'In-ward Register'!$M:$M) -> 4 | H90: =SUMIF('Out-ward Register'!$D:$D,Summery!$E:$E,'Out-ward Register'!$F:$F) -> 0 | I90: =G90-H90 -> 4 | J90: 93822 | K90: =J90*G90 -> 375288 | L90: =J90*H90 -> 0 | M90: =K90-L90 -> 375288 | O90: =M90/M$2*100 -> 395.87342
A91: other | B91: 23 | C91: 111391860 | D91: 111391860 | E91: MICRO VOLUME VISCOMETER-OIL APPLICATION | F91: Set | G91: =SUMIF('In-ward Register'!$K:$K,Summery!$E:$E,'In-ward Register'!$M:$M) -> 1 | H91: =SUMIF('Out-ward Register'!$D:$D,Summery!$E:$E,'Out-ward Register'!$F:$F) -> 0 | I91: =G91-H91 -> 1 | J91: 375000 | K91: =J91*G91 -> 375000 | L91: =J91*H91 -> 0 | M91: =K91-L91 -> 375000 | O91: =M91/M$2*100 -> 395.56962
A92: Project 6K | B92: 881 | C92: 112169822 | D92: ERLBT156013XXX2 | E92: CABLE 1C X 1.5 SQ MM - 4 GKW -- 1.8/3 KV | F92: Mtr. | G92: =SUMIF('In-ward Register'!$K:$K,Summery!$E:$E,'In-ward Register'!$M:$M) -> 51991 | H92: =SUMIF('Out-ward Register'!$D:$D,Summery!$E:$E,'Out-ward Register'!$F:$F) -> 35546 | I92: =G92-H92 -> 16445 | J92: 22.7 | K92: =J92*G92 -> 1180195.7 | L92: =J92*H92 -> 806894.2 | M92: =K92-L92 -> 373301.5 | O92: =M92/M$2*100 -> 393.77795
A93: Project 6K | B93: 538 | C93: 102464571 | D93: 3RV2011-1GA10 | E93: 3RV2011-1GA10 \CIRCUIT-BREAKER SCREW CO ( MPCV 6000 HP) | F93: Nos | G93: =SUMIF('In-ward Register'!$K:$K,Summery!$E:$E,'In-ward Register'!$M:$M) -> 1208 | H93: =SUMIF('Out-ward Register'!$D:$D,Summery!$E:$E,'Out-ward Register'!$F:$F) -> 838 | I93: =G93-H93 -> 370 | J93: 1007.25 | K93: =J93*G93 -> 1216758 | L93: =J93*H93 -> 844075.5 | M93: =K93-L93 -> 372682.5 | O93: =M93/M$2*100 -> 393.125
A94: Project-HLC | B94: 1181 | C94: 107081840 | D94: SA2V00001856028 | E94: IGBT-DRV-3K3-1200-04 | F94: Nos | G94: =SUMIF('In-ward Register'!$K:$K,Summery!$E:$E,'In-ward Register'!$M:$M) -> 15 | H94: =SUMIF('Out-ward Register'!$D:$D,Summery!$E:$E,'Out-ward Register'!$F:$F) -> 2 | I94: =G94-H94 -> 13 | J94: 28200 | K94: =J94*G94 -> 423000 | L94: =J94*H94 -> 56400 | M94: =K94-L94 -> 366600
A95: Project 6K | B95: 922 | C95: 112177659 | E95: Lifting Jig 6K TCC | F95: Nos | G95: =SUMIF('In-ward Register'!$K:$K,Summery!$E:$E,'In-ward Register'!$M:$M) -> 27 | H95: =SUMIF('Out-ward Register'!$D:$D,Summery!$E:$E,'Out-ward Register'!$F:$F) -> 24 | I95: =G95-H95 -> 3 | J95: 120000 | K95: =J95*G95 -> 3240000 | L95: =J95*H95 -> 2880000 | M95: =K95-L95 -> 360000 | O95: =M95/M$2*100 -> 379.74684
A96: Project 6K | B96: 1006 | C96: 113721325 112066861 | D96: RJ-45 | E96: Ethernet Cable (Ethernet to RJ45 ) | F96: Nos | G96: =SUMIF('In-ward Register'!$K:$K,Summery!$E:$E,'In-ward Register'!$M:$M) -> 168 | H96: =SUMIF('Out-ward Register'!$D:$D,Summery!$E:$E,'Out-ward Register'!$F:$F) -> 99 | I96: =G96-H96 -> 69 | J96: 5200 | K96: =J96*G96 -> 873600 | L96: =J96*H96 -> 514800 | M96: =K96-L96 -> 358800
A97: Project-HLC | B97: 1179 | C97: 105988783 | D97: SA2V00156022648 | E97: FAN 3PH 400V W2D250GA02 | F97: Nos | G97: =SUMIF('In-ward Register'!$K:$K,Summery!$E:$E,'In-ward Register'!$M:$M) -> 24 | H97: =SUMIF('Out-ward Register'!$D:$D,Summery!$E:$E,'Out-ward Register'!$F:$F) -> 3 | I97: =G97-H97 -> 21 | J97: 17000 | K97: =J97*G97 -> 408000 | L97: =J97*H97 -> 51000 | M97: =K97-L97 -> 357000
A98: Project 6K | B98: 770 | C98: 112158708 | D98: 2104A1001 | E98: Remmlot Mounting Bkt. Assy | F98: Nos | G98: =SUMIF('In-ward Register'!$K:$K,Summery!$E:$E,'In-ward Register'!$M:$M) -> 607 | H98: =SUMIF('Out-ward Register'!$D:$D,Summery!$E:$E,'Out-ward Register'!$F:$F) -> 420 | I98: =G98-H98 -> 187 | J98: 1900 | K98: =J98*G98 -> 1153300 | L98: =J98*H98 -> 798000 | M98: =K98-L98 -> 355300 | O98: =M98/M$2*100 -> 374.78903
A99: Project 6K | B99: 992 | C99: 101638461 | D99: SA5E00296016 | E99: SA5E00296016 \DC-DC SMPS 110V-24V | F99: Nos | G99: =SUMIF('In-ward Register'!$K:$K,Summery!$E:$E,'In-ward Register'!$M:$M) -> 26 | H99: =SUMIF('Out-ward Register'!$D:$D,Summery!$E:$E,'Out-ward Register'!$F:$F) -> 0 | I99: =G99-H99 -> 26 | J99: 13500 | K99: =J99*G99 -> 351000 | L99: =J99*H99 -> 0 | M99: =K99-L99 -> 351000
A100: Project 6K | B100: 999 | C100: 113782133 | D100: 10-40561-18AU | E100: Pin Contact Size 12/1.5 10-40561-18AU | F100: Nos | G100: =SUMIF('In-ward Register'!$K:$K,Summery!$E:$E,'In-ward Register'!$M:$M) -> 4392 | H100: =SUMIF('Out-ward Register'!$D:$D,Summery!$E:$E,'Out-ward Register'!$F:$F) -> 1076 | I100: =G100-H100 -> 3316 | J100: 105.6 | K100: =J100*G100 -> 463795.2 | L100: =J100*H100 -> 113625.6 | M100: =K100-L100 -> 350169.6
...

Sheet Return from Nasik
A1: Sr. No | B1: Date of receipt | C1: Material Receipt From | D1: Warehouse Doc. No & Vendor Document No. | E1: Warehouse Documents Date / Vendor Doc. Date | F1: LR No/ Date | G1: Vendor Place | H1: SAP Code | I1: Part Code | J1: Description | K1: UOM | L1: Received Qty | M1: Dispatched Qty | N1: Balance Qty | O1: VNS Item Location | P1: Box No / Bin No | Q1: Unit price | R1: DC.NO | S1: Date | T1: Dispatch Date | U1: Consignee
A2: 1 | B2: 45076 | C2: Teknocrats Control Systems (I) Pvt. Ltd. | D2: MDC2324/048 | E2: 45064 | F2: 922777634/ Criticalog India Pvt. Ltd | G2: Nasik | H2: 107020640 | I2: 3RH2131-2XF400LA2 | J2: Auxiliary Contactor for VCB Auxiliary Contactor Siemens 1 | K2: Nos. | L2: 3 | N2: =L2-M2 -> 3 | O2: Box No 396 | P2: Rack No 1
A3: 2 | B3: 45076 | C3: Teknocrats Control Systems (I) Pvt. Ltd. | D3: MDC2324/048 | E3: 45064 | F3: 922777634/ Criticalog India Pvt. Ltd | G3: Nasik | H3: 109461607 | I3: 12553871 | J3: Cable 1.5mm² Yellow Green H&S 4 MTR. | K3: Mtr | L3: 10 | N3: =L3-M3 -> 10 | O3: Box No 396 | P3: Rack No 1
A4: 3 | B4: 45076 | C4: Teknocrats Control Systems (I) Pvt. Ltd. | D4: MDC2324/048 | E4: 45064 | F4: 922777634/ Criticalog India Pvt. Ltd | G4: Nasik | H4: 109492180 | I4: 9670094701 | J4: Harting 9 pin D type connector Harting Female | K4: Nos. | L4: 120 | N4: =L4-M4 -> 120 | O4: Box No 396 | P4: Rack No 1 | Q4: 34.19
A5: 4 | B5: 45076 | C5: Teknocrats Control Systems (I) Pvt. Ltd. | D5: MDC2324/048 | E5: 45064 | F5: 922777634/ Criticalog India Pvt. Ltd | G5: Nasik | H5: 109498054 | I5: SUCB1 | J5: Coding Plate Size 1 Gimota-PPS | K5: Nos. | L5: 320 | N5: =L5-M5 -> 320 | O5: Box No 396 | P5: Rack No 1
A6: 5 | B6: 45076 | C6: Teknocrats Control Systems (I) Pvt. Ltd. | D6: MDC2324/048 | E6: 45064 | F6: 922777634/ Criticalog India Pvt. Ltd | G6: Nasik | H6: 109498055 | I6: SUCB2 | J6: Coding Plate Size 2 Gimota-PPS | K6: Nos. | L6: 12 | N6: =L6-M6 -> 12 | O6: Box No 396 | P6: Rack No 1
A7: 6 | B7: 45076 | C7: Teknocrats Control Systems (I) Pvt. Ltd. | D7: MDC2324/048 | E7: 45064 | F7: 922777634/ Criticalog India Pvt. Ltd | G7: Nasik | H7: 109498057 | I7: SUCB3 | J7: Coding Plate Size 3 Gimota-PPS | K7: Nos. | L7: 186 | N7: =L7-M7 -> 186 | O7: Box No 396 | P7: Rack No 1
A8: 7 | B8: 45076 | C8: Teknocrats Control Systems (I) Pvt. Ltd. | D8: MDC2324/048 | E8: 45064 | F8: 922777634/ Criticalog India Pvt. Ltd | G8: Nasik | H8: 109544072 | I8: SUHV09P | J8: Sub D 9 pin Assembly - Male Housing Pin 9 Pole SUHV09P Gimota-PPS | K8: Nos. | L8: 371 | N8: =L8-M8 -> 371 | O8: Box No 396 | P8: Rack No 1
A9: 8 | B9: 45076 | C9: Teknocrats Control Systems (I) Pvt. Ltd. | D9: MDC2324/048 | E9: 45064 | F9: 922777634/ Criticalog India Pvt. Ltd | G9: Nasik | H9: 109544074 | I9: SUHV15P | J9: Sub D 15 pin Assembly - Male Housing Pin 15 Pole SUHV15P Gimota-PPS | K9: Nos. | L9: 18 | N9: =L9-M9 -> 18 | O9: Box No 396 | P9: Rack No 1 | Q9: 205
A10: 9 | B10: 45076 | C10: Teknocrats Control Systems (I) Pvt. Ltd. | D10: MDC2324/048 | E10: 45064 | F10: 922777634/ Criticalog India Pvt. Ltd | G10: Nasik | H10: 109544076 | I10: SUHV25P | J10: Sub D 25 pin Assembly - Male Housing Pin 25 Pole SUHV25P Gimota-PPS | K10: Nos. | L10: 166 | N10: =L10-M10 -> 166 | O10: Box No 396 | P10: Rack No 1 | Q10: 230
A11: 10 | B11: 45076 | C11: Teknocrats Control Systems (I) Pvt. Ltd. | D11: MDC2324/048 | E11: 45064 | F11: 922777634/ Criticalog India Pvt. Ltd | G11: Nasik | H11: 109598700 | I11: Little Fuse 234 Series | J11: Fuse for Fan Little Fuse / RS Component 4 | K11: Nos. | L11: 380 | N11: =L11-M11 -> 380 | O11: Box No 396 | P11: Rack No 1 | Q11: 29.24
A12: 11 | B12: 45076 | C12: Teknocrats Control Systems (I) Pvt. Ltd. | D12: MDC2324/048 | E12: 45064 | F12: 922777634/ Criticalog India Pvt. Ltd | G12: Nasik | H12: 109612592 | I12: WAGO 280-941 | J12: WAGO 280-941 - Double Deck WAGO 2 | K12: Nos. | L12: 78 | N12: =L12-M12 -> 78 | O12: Box No 396 | P12: Rack No 1
A13: 12 | B13: 45076 | C13: Teknocrats Control Systems (I) Pvt. Ltd. | D13: MDC2324/048 | E13: 45064 | F13: 922777634/ Criticalog India Pvt. Ltd | G13: Nasik | H13: 109710324 | I13: WAGO 279-623 | J13: WAGO 279-623 WAGO 2 | K13: Nos. | L13: 52 | N13: =L13-M13 -> 52 | O13: Box No 396 | P13: Rack No 1
A14: 13 | B14: 45076 | C14: Teknocrats Control Systems (I) Pvt. Ltd. | D14: MDC2324/048 | E14: 45064 | F14: 922777634/ Criticalog India Pvt. Ltd | G14: Nasik | H14: 109710325 | I14: WAGO 279-316 | J14: End Plate 2.5 mm WAGO 4 | K14: Nos. | L14: 212 | N14: =L14-M14 -> 212 | O14: Box No 396 | P14: Rack No 1
A15: 14 | B15: 45076 | C15: Teknocrats Control Systems (I) Pvt. Ltd. | D15: MDC2324/048 | E15: 45064 | F15: 922777634/ Criticalog India Pvt. Ltd | G15: Nasik | H15: 109710326 | I15: WAGO 249-117 | J15: Din Rail End Stop WAGO | K15: Nos. | L15: 90 | N15: =L15-M15 -> 90 | O15: Box No 396 | P15: Rack No 1
A16: 15 | B16: 45076 | C16: Teknocrats Control Systems (I) Pvt. Ltd. | D16: MDC2324/048 | E16: 45064 | F16: 922777634/ Criticalog India Pvt. Ltd | G16: Nasik | H16: 109710327 | I16: WAGO 280-621 | J16: 4 Conductor Through Terminal WAGO | K16: Nos. | L16: 800 | N16: =L16-M16 -> 800 | O16: Box No 396 | P16: Rack No 1
A17: 16 | B17: 45076 | C17: Teknocrats Control Systems (I) Pvt. Ltd. | D17: MDC2324/048 | E17: 45064 | F17: 922777634/ Criticalog India Pvt. Ltd | G17: Nasik | H17: 109710328 | I17: WAGO 280-316 | J17: End Plate - 4 Conductor WAGO 10 | K17: Nos. | L17: 108 | N17: =L17-M17 -> 108 | O17: Box No 396 | P17: Rack No 1
A18: 17 | B18: 45076 | C18: Teknocrats Control Systems (I) Pvt. Ltd. | D18: MDC2324/048 | E18: 45064 | F18: 922777634/ Criticalog India Pvt. Ltd | G18: Nasik | H18: 110294841 | I18: WAGO 281-611 | J18: Fuse Holder WAGO 4.00 | K18: Nos. | L18: 226 | N18: =L18-M18 -> 226 | O18: Box No 396 | P18: Rack No 1
A19: 18 | B19: 45076 | C19: Teknocrats Control Systems (I) Pvt. Ltd. | D19: MDC2324/048 | E19: 45064 | F19: 922777634/ Criticalog India Pvt. Ltd | G19: Nasik | H19: 110315359 | I19: LM-370A | J19: Ink Ribbon Black for Letatwin LM370A Max-Letatwin | K19: Nos. | L19: 75 | N19: =L19-M19 -> 75 | O19: Box No 396 | P19: Rack No 1
A20: 19 | B20: 45076 | C20: Teknocrats Control Systems (I) Pvt. Ltd. | D20: MDC2324/048 | E20: 45064 | F20: 922777634/ Criticalog India Pvt. Ltd | G20: Nasik | H20: 110317038 | I20: WAGO 209-501 | J20: WAGO Marking Card Wago 130 | K20: Nos. | L20: 39 | N20: =L20-M20 -> 39 | O20: Box No 396 | P20: Rack No 1
A21: 20 | B21: 45076 | C21: Teknocrats Control Systems (I) Pvt. Ltd. | D21: MDC2324/048 | E21: 45064 | F21: 922777634/ Criticalog India Pvt. Ltd | G21: Nasik | H21: 110317058 | I21: 110708884 | J21: Ring type Cable Lug 1.5 x M4 Panduit 50 | K21: Nos. | L21: 4600 | N21: =L21-M21 -> 4600 | O21: Box No 396 | P21: Rack No 1
A22: 21 | B22: 45076 | C22: Teknocrats Control Systems (I) Pvt. Ltd. | D22: MDC2324/048 | E22: 45064 | F22: 922777634/ Criticalog India Pvt. Ltd | G22: Nasik | H22: 110317060 | J22: M6x15 Hex Hd Bolt Minus SS304 TVS / Unbrako 15 | K22: Nos. | L22: 240 | N22: =L22-M22 -> 240 | O22: Box No 396 | P22: Rack No 1
A23: 22 | B23: 45076 | C23: Teknocrats Control Systems (I) Pvt. Ltd. | D23: MDC2324/048 | E23: 45064 | F23: 922777634/ Criticalog India Pvt. Ltd | G23: Nasik | H23: 110492019 | I23: WAGO 281-311 | J23: End Plate - Fuse Holder WAGO 4 | K23: Nos. | L23: 160 | N23: =L23-M23 -> 160 | O23: Box No 396 | P23: Rack No 1
A24: 23 | B24: 45076 | C24: Teknocrats Control Systems (I) Pvt. Ltd. | D24: MDC2324/048 | E24: 45064 | F24: 922777634/ Criticalog India Pvt. Ltd | G24: Nasik | H24: A5E51979678 | J24: Suraksha CCL 25K Fire resistance cement | K24: Kg | L24: 50 | N24: =L24-M24 -> 50 | O24: Drum 1 &2 | P24: Rack No 1
A25: 24 | B25: 45076 | C25: Teknocrats Control Systems (I) Pvt. Ltd. | D25: MDC2324/048 | E25: 45064 | F25: 922777634/ Criticalog India Pvt. Ltd | G25: Nasik | H25: 111448667 | I25: 221 | J25: Sikaflex 221 Sikaflex 221 1 No. | K25: Nos. | L25: 45 | N25: =L25-M25 -> 45 | O25: Box No 398 | P25: Rack No 1
A26: 25 | B26: 45076 | C26: Teknocrats Control Systems (I) Pvt. Ltd. | D26: MDC2324/048 | E26: 45064 | F26: 922777634/ Criticalog India Pvt. Ltd | G26: Nasik | J26: Nylon Jacket grey colour Net Sleeve | K26: Mtr | L26: 4 | N26: =L26-M26 -> 4 | O26: Box No 396 | P26: Rack No 1
A27: 26 | B27: 45076 | C27: Teknocrats Control Systems (I) Pvt. Ltd. | D27: MDC2324/048 | E27: 45064 | F27: 922777634/ Criticalog India Pvt. Ltd | G27: Nasik | H27: 111397722 | I27: 9140043141 | J27: HAN CC PROTECTED MODULE CRIMP FEMALE 09140043141 | K27: Nos. | L27: 8 | N27: =L27-M27 -> 8 | O27: Box No 396 | P27: Rack No 1 | Q27: 135.23
A28: 27 | B28: 45076 | C28: Teknocrats Control Systems (I) Pvt. Ltd. | D28: MDC2324/048 | E28: 45064 | F28: 922777634/ Criticalog India Pvt. Ltd | G28: Nasik | H28: 112173252 | I28: 19000005081 | J28: Han CGM-M M20x1,5 D.5-9mm/6-12mm 19000005081 | K28: Nos. | L28: 20 | N28: =L28-M28 -> 20 | O28: Box No 396 | P28: Rack No 1 | Q28: 215.44
A29: 28 | B29: 45076 | C29: Teknocrats Control Systems (I) Pvt. Ltd. | D29: MDC2324/048 | E29: 45064 | F29: 922777634/ Criticalog India Pvt. Ltd | G29: Nasik | J29: Black rubber Pad | K29: Nos. | L29: 1170 | N29: =L29-M29 -> 1170 | O29: Box No 397 | P29: Rack No 1
A30: 29 | B30: 45076 | C30: Teknocrats Control Systems (I) Pvt. Ltd. | D30: MDC2324/048 | E30: 45064 | F30: 922777634/ Criticalog India Pvt. Ltd | G30: Nasik | J30: Terminal 280- | K30: Nos. | L30: 48 | N30: =L30-M30 -> 48 | O30: Box No 396 | P30: Rack No 1
A31: 30 | B31: 45076 | C31: Teknocrats Control Systems (I) Pvt. Ltd. | D31: MDC2324/048 | E31: 45064 | F31: 922777634/ Criticalog India Pvt. Ltd | G31: Nasik | J31: spring washer M-10 | K31: Nos. | L31: 89 | N31: =L31-M31 -> 89 | O31: Box No 396 | P31: Rack No 1
A32: 31 | B32: 45076 | C32: Teknocrats Control Systems (I) Pvt. Ltd. | D32: MDC2324/048 | E32: 45064 | F32: 922777634/ Criticalog India Pvt. Ltd | G32: Nasik | J32: M10x30 Hex Hd Bolt | K32: Nos. | L32: 80 | N32: =L32-M32 -> 80 | O32: Box No 396 | P32: Rack No 1
A33: 32 | B33: 45076 | C33: Teknocrats Control Systems (I) Pvt. Ltd. | D33: MDC2324/048 | E33: 45064 | F33: 922777634/ Criticalog India Pvt. Ltd | G33: Nasik | J33: M6x30 Hex Hd Bolt | K33: Nos. | L33: 80 | N33: =L33-M33 -> 80 | O33: Box No 396 | P33: Rack No 1
A34: 33 | B34: 45076 | C34: Teknocrats Control Systems (I) Pvt. Ltd. | D34: MDC2324/048 | E34: 45064 | F34: 922777634/ Criticalog India Pvt. Ltd | G34: Nasik | J34: Nut - M4 | K34: Nos. | L34: 4000 | N34: =L34-M34 -> 4000 | O34: Box No 396 | P34: Rack No 1
A35: 34 | B35: 45076 | C35: Teknocrats Control Systems (I) Pvt. Ltd. | D35: MDC2324/048 | E35: 45064 | F35: 922777634/ Criticalog India Pvt. Ltd | G35: Nasik | J35: Plain Washer - M10 | K35: Nos. | L35: 100 | N35: =L35-M35 -> 100 | O35: Box No 396 | P35: Rack No 1
A36: 35 | B36: 45076 | C36: Teknocrats Control Systems (I) Pvt. Ltd. | D36: MDC2324/048 | E36: 45064 | F36: 922777634/ Criticalog India Pvt. Ltd | G36: Nasik | H36: 109552693 | I36: CMF60500R00BEEK | J36: 500 Ohm Burden Resistor CMF60500R00BEEK OMEGA Part no - OMF50 500R 0.5W 1% 25PPM" | K36: Nos. | L36: 3000 | N36: =L36-M36 -> 3000 | O36: Box No 396 | P36: Rack No 1
A37: 36 | B37: 45076 | C37: Teknocrats Control Systems (I) Pvt. Ltd. | D37: MDC2324/048 | E37: 45064 | F37: 922777634/ Criticalog India Pvt. Ltd | G37: Nasik | H37: A1A260190 | J37: SHIL DIN40008 WS1-2-100-KF-DRUSCOTCH3650 | K37: Nos. | L37: 12 | N37: =L37-M37 -> 12 | O37: Box No 396 | P37: Rack No 1
A38: 37 | B38: 45076 | C38: Teknocrats Control Systems (I) Pvt. Ltd. | D38: MDC2324/048 | E38: 45064 | F38: 922777634/ Criticalog India Pvt. Ltd | G38: Nasik | J38: A2V001553102 | K38: Nos. | L38: 100 | N38: =L38-M38 -> 100 | O38: Box No 396 | P38: Rack No 1
A39: 38 | B39: 45076 | C39: Teknocrats Control Systems (I) Pvt. Ltd. | D39: MDC2324/048 | E39: 45064 | F39: 922777634/ Criticalog India Pvt. Ltd | G39: Nasik | H39: A5E51856166 | J39: Label list_VCU1 | K39: Nos. | L39: 6 | N39: =L39-M39 -> 6 | O39: Box No 396 | P39: Rack No 1
A40: 39 | B40: 45076 | C40: Teknocrats Control Systems (I) Pvt. Ltd. | D40: MDC2324/048 | E40: 45064 | F40: 922777634/ Criticalog India Pvt. Ltd | G40: Nasik | H40: A5E51856167 | J40: Label list_VCU2 | K40: Nos. | L40: 6 | N40: =L40-M40 -> 6 | O40: Box No 396 | P40: Rack No 1
A41: 40 | B41: 45076 | C41: Teknocrats Control Systems (I) Pvt. Ltd. | D41: MDC2324/048 | E41: 45064 | F41: 922777634/ Criticalog India Pvt. Ltd | G41: Nasik | H41: 100715435 | I41: 000000035618 | J41: label DIN40011 2B16 -10-KF-DRU- SC365 | K41: Nos. | L41: 12 | N41: =L41-M41 -> 12 | O41: Box No 396 | P41: Rack No 1
A42: 41 | B42: 45076 | C42: Teknocrats Control Systems (I) Pvt. Ltd. | D42: MDC2324/048 | E42: 45064 | F42: 922777634/ Criticalog India Pvt. Ltd | G42: Nasik | J42: Connector 6 Pin | K42: Nos. | L42: 27 | N42: =L42-M42 -> 27 | O42: Box No 396 | P42: Rack No 1
A43: 42 | B43: 45076 | C43: Teknocrats Control Systems (I) Pvt. Ltd. | D43: MDC2324/048 | E43: 45064 | F43: 922777634/ Criticalog India Pvt. Ltd | G43: Nasik | J43: Connector 10 Pin | K43: Nos. | L43: 8 | N43: =L43-M43 -> 8 | O43: Box No 396 | P43: Rack No 1
A44: 43 | B44: 45076 | C44: Teknocrats Control Systems (I) Pvt. Ltd. | D44: MDC2324/048 | E44: 45064 | F44: 922777634/ Criticalog India Pvt. Ltd | G44: Nasik | J44: Grommet 13Mm | K44: Nos. | L44: 648 | N44: =L44-M44 -> 648 | O44: Box No 396 | P44: Rack No 1
A45: 44 | B45: 45076 | C45: Teknocrats Control Systems (I) Pvt. Ltd. | D45: MDC2324/048 | E45: 45064 | F45: 922777634/ Criticalog India Pvt. Ltd | G45: Nasik | J45: Cable Tie 100mm white Colour 500 | K45: Nos. | L45: 100 | N45: =L45-M45 -> 100 | O45: Box No 396 | P45: Rack No 1
A46: 45 | B46: 45076 | C46: Teknocrats Control Systems (I) Pvt. Ltd. | D46: MDC2324/048 | E46: 45064 | F46: 922777634/ Criticalog India Pvt. Ltd | G46: Nasik | H46: 102117361 | I46: 6103 000 0054 | J46: ACC_D-SUB_CRIMP FERRULE_9,5/10,5 | K46: Nos. | L46: 12 | N46: =L46-M46 -> 12 | O46: Box No 396 | P46: Rack No 1
A47: 46 | B47: 45076 | C47: Teknocrats Control Systems (I) Pvt. Ltd. | D47: MDC2324/048 | E47: 45064 | F47: 922777634/ Criticalog India Pvt. Ltd | G47: Nasik | I47: WAGO-210-508 | J47: WAGO Din rail 2mtr | K47: Nos. | L47: 35 | N47: =L47-M47 -> 35 | O47: Loose | P47: Rack No 1
A48: 47 | B48: 45124 | C48: POWERTECH ENGINEERS | D48: GS202324128 | E48: 45106 | F48: 929093292/ Criticalog | G48: Nasik | H48: 112137134 | I48: 21038811406 | J48: M12 Crimp slim design 4 pol D coded m '21038811406 | K48: Nos | L48: 50 | M48: 3 | N48: =L48-M48 -> 47 | O48: Rack No 2 | P48: Box No 437 | Q48: 1252.82 | R48: UP/FY23/DC/00427 | S48: 45349 | T48: 45349 | U48: Powertech Engineers
A49: 47 | B49: 45124 | C49: POWERTECH ENGINEERS | D49: GS202324128 | E49: 45106 | F49: 929093292/ Criticalog | G49: Nasik | H49: 112137134 | I49: 21038811406 | J49: M12 Crimp slim design 4 pol D coded m '21038811406 | K49: Nos | M49: 7 | N49: =L49-M49 -> -7 | O49: Rack No 2 | P49: Box No 437 | R49: UP/FY25/DC/00084 | S49: 45804 | T49: 45804 | U49: Powertech Engineers
A50: 48 | B50: 45450 | C50: Siemens Ltd Nashik | D50: MH1427750868 | E50: 45447 | F50: 58831341483 Blue Dart | G50: Nasik | H50: A5E45983529 | I50: SA5E01077957 | J50: Discharge Contactor | K50: Nos | L50: 1 | N50: =L50-M50 -> 1 | O50: Area K | P50: Box No.612 | U50: Dammage received against Inv.No.MH1327754660 (FOC)
A51: 49 | B51: 45450 | C51: Siemens Ltd Nashik | D51: MH1427750868 | E51: 45447 | F51: 58831341483 Blue Dart | G51: Nasik | H51: 105777225 | I51: S100705887 | J51: S100705887 CAP AL EL 6800uF 350VDC 20% 1 | K51: Nos | L51: 4 | N51: =L51-M51 -> 4 | O51: Area K | P51: Box No.612 | U51: Dammage received against Inv.No.MH1327754660 (FOC)

Sheet Site Return Material 
A2: Material Inward - Outward Register | N2: =SUBTOTAL(9,N4:N4419) -> 2017 | O2: =SUBTOTAL(9,O4:O4419) -> 45 | P2: =+N2-O2 -> 1972
A3: Project Name | B3: Sr. No. | C3: Date of receipt | D3: Material Receipt From | E3: Warehouse Doc. No & Vendor Document No. | F3: Warehouse Documents Date / Vendor Doc. Date | G3: LR No/ Date | H3: Location | I3: P.O. No. | J3: SAP Code | K3: Part Code | L3: Description | M3: UOM | N3: Received Qty | O3: Dispatched Qty | P3: Balance Qty | Q3: Rack No | R3: Box No | S3: Remark if Any | T3: Customer Invoice / Challan No | U3: Date | V3: Dispatch Date | W3: Consignee | X3: Location | Y3: Order By | Z3: Docket No or Vehicle No. | AA3: Transporter / Courier Name | AB3: Project | AC3: Customer P.O. No | AD3: WBS | AE3: Remark if Any | AG3: Category
A4: Project 6K | B4: 1 | C4: 45129 | D4: BLW | E4: - | F4: - | G4: By Hand Mr. Anant Mishra | H4: Varanasi | I4: - | J4: 109563338 | K4: 857-409 (60498872) | L4: Isolation amplifier; Current and voltage 857-409 | M4: Nos | N4: 6 | O4: 6 | P4: =N4-O4 -> 0 | S4: Faulty Material received from BLW | T4: UP/FY23/DC/00102 | U4: 45132 | V4: 45134 | W4: Siemens Ltd | X4: Gurgaon | Y4: Mr. Arvind pandey | Z4: 923389224 | AA4: Criticalog india Pvt. Ltd. | AB4: Wag 9/6K | AC4: - | AD4: - | AE4: Faulty Material sent to Gurgaon office | AG4: Faulty
A5: Project 6K | B5: 2 | C5: 45129 | D5: BLW | E5: - | F5: - | G5: By Hand Mr. Anant Mishra | H5: Varanasi | I5: - | J5: - | K5: - | L5: Analog Input ( AI) Card | M5: Nos | N5: 1 | O5: 1 | P5: =N5-O5 -> 0 | S5: Faulty Material received from BLW Sr. No2260323 | T5: UP/FY23/DC/00102 | U5: 45132 | V5: 45134 | W5: Siemens Ltd | X5: Gurgaon | Y5: Mr. Arvind pandey | Z5: 923389224 | AA5: Criticalog india Pvt. Ltd. | AB5: Wag 9/6K | AC5: - | AD5: - | AE5: Faulty Material sent to Gurgaon office
A6: Project 6K | B6: 3 | C6: 45129 | D6: BLW | E6: - | F6: - | G6: By Hand Mr. Anant Mishra | H6: Varanasi | I6: - | J6: - | K6: - | L6: Power Supply of I/O | M6: Nos | N6: 1 | O6: 1 | P6: =N6-O6 -> 0 | S6: Faulty Material received from BLW _ Sr. No 2237619 | T6: UP/FY23/DC/00102 | U6: 45132 | V6: 45134 | W6: Siemens Ltd | X6: Gurgaon | Y6: Mr. Arvind pandey | Z6: 923389224 | AA6: Criticalog india Pvt. Ltd. | AB6: Wag 9/6K | AC6: - | AD6: - | AE6: Faulty Material sent to Gurgaon office
A7: Project 6K | B7: 4 | C7: 45129 | D7: BLW | E7: - | F7: - | G7: By Hand Mr. Anant Mishra | H7: Varanasi | I7: - | J7: - | K7: - | L7: Remmlot Device | M7: Nos | N7: 1 | O7: 1 | P7: =N7-O7 -> 0 | S7: Faulty Material received from BLW Sr. No 582 | T7: UP/FY23/DC/00117 | U7: 45138 | V7: 45139 | W7: Lotus Wireless Technologies | X7: Vishakhapatnam | Y7: Mr. Arvind pandey | Z7: 378840232 | AA7: GatiKWE | AB7: Wag 9/6K | AE7: Faulty material sent to supplier for repairing
A8: Project 6K | B8: 5 | C8: 45129 | D8: BLW | E8: - | F8: - | G8: By Hand Mr. Anant Mishra | H8: Varanasi | I8: - | J8: 112171911 | K8: - | L8: Remmlot Device | M8: Nos | N8: 1 | O8: 1 | P8: =N8-O8 -> 0 | S8: It is healthy device Sr. No 537 | T8: UP/FY23/DC/00110 | U8: 45134 | V8: 45134 | W8: SD II Store depot PLW | X8: Patiala | Y8: Mr. Arka Dey | Z8: 923388594 | AA8: Criticalog India Pvt. Ltd. | AB8: Project 6K | AC8: '20221047101382 | AE8: 2 Remmlot out of 5 is not working
A9: Project 6K | B9: 6 | C9: 45135 | D9: BNDM | E9: WB/FY23/DC/00035 | F9: 45126 | G9: 58025464685/Bluedart | H9: BNDM | I9: - | J9: 112171911 | K9: LT30 | L9: Remmlot Device Sr No 407 | M9: Nos | N9: 1 | P9: =N9-O9 -> 1 | S9: USB Type connector
A10: Project 6K | B10: 7 | C10: 45135 | D10: BNDM | E10: WB/FY23/DC/00035 | F10: 45126 | G10: 58025464685/Bluedart | H10: BNDM | I10: - | J10: 112171911 | K10: LT30 | L10: Remmlot Device Sr No 323 | M10: Nos | N10: 1 | O10: 1 | P10: =N10-O10 -> 0 | S10: Mounting Base Broken | T10: UP/FY23/DC/00117 | U10: 45138 | V10: 45139 | W10: Lotus Wireless Technologies | X10: Vishakhapatnam | Y10: Mr. Arvind pandey | Z10: 378840232 | AA10: GatiKWE | AB10: Wag 9/6K | AE10: Faulty material sent to supplier for repairing
A11: Project 6K | B11: 8 | C11: 45159 | D11: BLW | E11: - | F11: - | G11: By Hand Mr. Anant Mishra | H11: Varanasi | I11: - | J11: - | K11: - | L11: Sitet Display LBPD164409 | M11: Nos | N11: 1 | O11: 1 | P11: =N11-O11 -> 0 | S11: Faulty | T11: UP/FY23/DC/00188 | U11: 45183 | V11: 45184 | W11: Siemens Ltd | X11: Gurgaon | Y11: Mr. Pratik Sawant | Z11: 350958869 | AA11: GatiKWE | AB11: Wag 9/6K | AE11: Faulty material sent to supplier for repairing
A12: Project 6K | B12: 9 | C12: 45167 | D12: BLW | E12: - | F12: - | G12: By Hand Mr. Anant Mishra | H12: BNDM | I12: - | J12: 112161405 | K12: - | L12: Laptop HP 240 G8 Intel Core i3 11th Gen Processor/8GB Ram , 512 GB SSD Sr. No 1N12080G1S | M12: Nos | N12: 1 | P12: =N12-O12 -> 1 | Q12: Rack No 88 | R12: Box No 481 | S12: Material Received in Good Condition
A13: Project 6K | B13: 10 | C13: 45167 | D13: CLW | E13: 407680705 | F13: 45162 | G13: D70448913/ DTDC Courier | H13: Chittaranjan | I13: - | J13: 112161405 | K13: - | L13: Laptop HP 240 G8 Intel Core i3 11th Gen Processor/8GB Ram , 512 GB SSD Sr. No:- | M13: Nos | N13: 2 | P13: =N13-O13 -> 2 | Q13: Rack No 88 | R13: Box No 481 | S13: Material Received in Good Condition
A14: Project 6K | B14: 11 | C14: 45173 | D14: Dinesh Das ( PLW) | E14: NA | F14: - | G14: D76072140/ DTDC Courier | H14: Patiala | I14: - | J14: 112161405 | K14: - | L14: Laptop HP 240 G8 Intel Core i3 11th Gen Processor/8GB Ram , 512 GB SSD Sr. No:- 1N12080FVT | M14: Nos | N14: 1 | P14: =N14-O14 -> 1 | Q14: Rack No 88 | R14: Box No 487 | S14: Material Received in Good Condition
A15: Project 6K | B15: 12 | C15: 45238 | D15: Katni | E15: MP/FY23/DC/00017 | F15: 45232 | G15: 51696550684 Blue Dart | H15: Varanasi | I15: - | J15: 109611234 | K15: 3742612236 | L15: ACTIVE SPEED SENSORS SUITABLE FOR IGBT LOCOS [3-PHASE LOCOS] DSD 1616.73 QHW - F267S 3742612236 | M15: Nos | N15: 4 | O15: 3 | P15: =N15-O15 -> 1 | Q15: Rack No 54 | R15: Box No 546 | S15: Serial no. S2236006933/S2236006984/S2237004439/S2236007088 | T15: UP/FY/24/DC/00004 | U15: 45386 | V15: 45386 | W15: Siemens Ltd -Htderabad | X15: Hyderabad | Y15: Mr.Arvind Pandey | Z15: 397302247 | AA15: GatiKWE | AB15: 6k | AE15: 1 nos Faulty (dent Mark) | AG15: Faulty
A16: Project 6K | B16: 12 | C16: 45238 | D16: Katni | E16: MP/FY23/DC/00017 | F16: 45232 | G16: 51696550684 Blue Dart | H16: Varanasi | I16: - | J16: 109611234 | K16: 3742612236 | L16: ACTIVE SPEED SENSORS SUITABLE FOR IGBT LOCOS [3-PHASE LOCOS] DSD 1616.73 QHW - F267S 3742612236 | O16: 1 | P16: =P15-O16 -> 0 | Q16: Rack No 54 | R16: Box No 546 | S16: S2237004439 | T16: UP/FY/24/DC/00101 | U16: 45542 | V16: 45542 | W16: Siemens Ltd -Htderabad | X16: Hyderabad | Y16: Mr.Arvind Pandey | Z16: By Hand | AA16: GatiKWE | AB16: 6k | AG16: Faulty
B17: 13 | C17: 44791 | D17: BLW | I17: - | J17: 109447744 | K17: 803203 | L17: LION DA 8xDC24V/110V 803203 | M17: Nos | N17: 1 | O17: 1 | P17: =N17-O17 -> 0 | Q17: Area -A | R17: S.S Bin no.06 | T17: UP/FY24/DC/00120 | U17: 23/07/2024 | V17: 23/07/2024 | W17: Siemens ltd | X17: Gurgaon | Y17: Mr.Arvind Pandey | Z17: 385142158 | AA17: GatiKWE | AB17: 6K | AE17: Faulty Material Received
B18: 14 | C18: 44791 | D18: BLW | I18: - | L18: Sibcos M2500-2-0 | M18: Nos | N18: 1 | P18: =N18-O18 -> 1 | Q18: Area -A | R18: S.S Bin no.06 | AE18: Faulty Material Received | AG18: Faulty
B19: 15 | C19: 44791 | D19: BLW | I19: - | L19: Contactor 3RT1064-6….6 | M19: Nos | N19: 1 | P19: =N19-O19 -> 1 | Q19: Area -A | R19: S.S Bin no.06 | AE19: Faulty Material Received | AG19: Faulty
B20: 16 | C20: 44791 | D20: BLW | I20: - | J20: 110710684 | L20: Braided Bus Bar | M20: Nos | N20: 12 | P20: =N20-O20 -> 12 | Q20: Area -A | R20: S.S Bin no.06 | AE20: Faulty Material Received | AG20: Faulty
A21: Project 6K | B21: 17 | C21: 45311 | D21: Gurgoan | E21: HR/FY23/DC/00235 | F21: 45308 | G21: 58136402483 Bluedart | H21: Gurgoan | I21: - | J21: 109611234 | K21: 3742612236 | L21: ACTIVE SPEED SENSORS SUITABLE FOR IGBT LOCOS [3-PHASE LOCOS] DSD 1616.73 QHW - F267S 3742612236 | M21: Nos | N21: 1 | O21: 1 | P21: =N21-O21 -> 0 | Q21: Rack No 54 | R21: Box No 546 | S21: Sr.no. S2239006061 Faulty | T21: UP/FY/24/DC/00005 | U21: 45386 | V21: 45386 | W21: Siemens Ltd -Vadodara | X21: Vadodara | Y21: Mr.Arvind Pandey | Z21: 397302254 | AA21: GatiKWE | AB21: 6k | AE21: Faulty Material Received | AG21: Faulty
A22: Project 6K | B22: 18 | C22: 45390 | D22: Katni | E22: MP/FY24/DC/00002 | F22: 45383 | G22: 53493943952 Blue Dart | H22: Katni | I22: - | J22: 107146625 | K22: 4318N | L22: Churning Fan-Model No- 4318N/2N | M22: Nos | N22: 2 | O22: 2 | P22: =N22-O22 -> 0 | Q22: Rack No.54 | R22: Box No.627 | S22: Sr.noWP009742/WP009743 | T22: UP/FY24/DC/00245 | U22: 45616 | V22: 45616 | W22: RS Components & Control India Ltd | X22: Noaida | Y22: Mr .Arka Dey | Z22: 385199534 | AA22: GatiKWE | AB22: 6K | AE22: Dispatch for Replace ment
A23: Project 6K | B23: 19 | C23: 45397 | D23: Vadodara | E23: GJ/FY23/DC/05727 | F23: 45391 | H23: Vadodara | I23: - | J23: 109563338 | K23: 857-409 (60498872) | L23: Isolation amplifier; Current and voltage 857-409 | M23: Nos | N23: 6 | P23: =N23-O23 -> 6 | Q23: Area -A | R23: S.S Bin no.06 | S23: Defective Material from BRC | AE23: Faulty Material Received | AG23: Faulty
A24: Project 6K | B24: 20 | C24: 45397 | D24: Vadodara | E24: GJ/FY23/DC/05727 | F24: 45391 | G24: A52564588 DTDC | H24: Vadodara | I24: - | J24: 113837420 | K24: 4414N | L24: Electric Fan (4414 N EBM past) | M24: Nos | N24: 1 | O24: 1 | P24: =N24-O24 -> 0 | Q24: Area -A | R24: S.S Bin no.06 | S24: Defective Material from BRC | T24: UP/FY24/DC/00245 | U24: 45616 | V24: 45616 | W24: RS Components & Control India Ltd | X24: Noaida | Y24: Mr .Arka Dey | Z24: 385199534 | AA24: GatiKWE | AB24: 6K | AE24: Dispatch for Replace ment
A25: Project 6K | B25: 21 | C25: 45423 | D25: Vadodara | E25: GJ/FY24/DC/00686 | F25: 45509 | H25: Vadodara | I25: - | J25: 109611234 | K25: 3742612236 | L25: ACTIVE SPEED SENSORS SUITABLE FOR IGBT LOCOS [3-PHASE LOCOS] DSD 1616.73 QHW - F267S 3742612236 | M25: Nos | N25: 1 | P25: =N25-O25 -> 1 | Q25: Area -A | R25: S.S Bin no.06 | S25: Defective Material from BRC | AE25: Faulty Material Received | AG25: Faulty
A26: Project 6K | B26: 22 | C26: 45455 | D26: Vadodara | E26: GJ/FY24/DC/01290 | F26: 45450 | G26: 51716372654 Blue Dart | H26: Vadodara | I26: - | J26: 109563338 | K26: 857-409 (60498872) | L26: Isolation amplifier; Current and voltage 857-409 | M26: Nos | N26: 8 | P26: =N26-O26 -> 8 | Q26: Area -A | R26: S.S Bin no.06 | S26: loco no.39285 | AE26: Faulty Material Received | AG26: Faulty
A27: Project 6K | B27: 23 | C27: 45455 | D27: Vadodara | E27: GJ/FY24/DC/01290 | F27: 45450 | G27: 51716372654 Blue Dart | H27: Vadodara | I27: - | J27: 113837420 | K27: 4414N | L27: Electric Fan (4414 N EBM past) | M27: Nos | N27: 3 | O27: 3 | P27: =N27-O27 -> 0 | Q27: Area -A | R27: S.S Bin no.06 | S27: loco no.39285/39258/39243 | T27: UP/FY24/DC/00245 | U27: 45616 | V27: 45616 | W27: RS Components & Control India Ltd | X27: Noaida | Y27: Mr .Arka Dey | Z27: 385199534 | AA27: GatiKWE | AB27: 6K | AE27: Dispatch for Replace ment
A28: Project 6K | B28: 24 | C28: 45455 | D28: Vadodara | E28: GJ/FY24/DC/01290 | F28: 45450 | G28: 51716372654 Blue Dart | H28: Vadodara | I28: - | J28: 109447742 | K28: 803102 | L28: 803102 LION-DI16-72V-110V-LUE LION I/O MODULE DIGITAL OUTPUTS | M28: Nos | N28: 3 | O28: 3 | P28: =N28-O28 -> 0 | Q28: Area -A | R28: S.S Bin no.06 | S28: Card Sr.no.0002263016,0002263015/0002263088 | T28: UP/FY24/DC/00120 | U28: 23/07/2024 | V28: 23/07/2024 | W28: Siemens ltd | X28: Gurgaon | Y28: Mr.Arvind Pandey | Z28: 385142158 | AA28: GatiKWE | AB28: 6K | AE28: Faulty Material Received
A29: Project 6K | B29: 25 | C29: 45469 | D29: Secunderabad | E29: TG/FY24/DC/00028 | F29: 45463 | H29: Secunderabad | I29: - | J29: 109611234 | K29: 3742612236 | L29: ACTIVE SPEED SENSORS SUITABLE FOR IGBT LOCOS [3-PHASE LOCOS] DSD 1616.73 QHW - F267S 3742612236 | M29: Nos | N29: 4 | P29: =N29-O29 -> 4 | AG29: Faulty
A30: Project 6K | B30: 26 | C30: 45477 | D30: Vadodara | E30: GJ/FY24/DC/01731 | F30: 45469 | G30: 51696340010 | H30: Vadodara | I30: - | J30: 113694314 | K30: DB 6200 AG | L30: Bipolar Isolation amplifier DB 6200 AG Drago make | M30: Nos | N30: 1 | P30: =N30-O30 -> 1 | Q30: Area -A | R30: S.S Bin no.06 | S30: Faulty Material Received from | AG30: Faulty
A31: Project 6K | B31: 27 | C31: 45477 | D31: Vadodara | E31: GJ/FY24/DC/01731 | F31: 45469 | G31: 51696340010 | H31: Vadodara | I31: - | J31: 113837420 | K31: 4414N | L31: Electric Fan (4414 N EBM past) | M31: Nos | N31: 2 | O31: 2 | P31: =N31-O31 -> 0 | Q31: Area -A | R31: S.S Bin no.06 | S31: Faulty Material Received from | T31: UP/FY24/DC/00245 | U31: 45616 | V31: 45616 | W31: RS Components & Control India Ltd | X31: Noaida | Y31: Mr .Arka Dey | Z31: 385199534 | AA31: GatiKWE | AB31: 6K | AE31: Dispatch for Replace ment
A32: Project 6K | B32: 28 | C32: 45486 | D32: CLW/Chittaranjan | E32: WB/FY24/DC/00081 | F32: 45450 | G32: 323733028 | H32: CLW | I32: - | J32: 10947744 | K32: 803203 | L32: 803203 LION-DO8-24V-110V-LUE LION I/O MODULE DIGITAL OUTPUTS | M32: Nos | N32: 1 | O32: 1 | P32: =N32-O32 -> 0 | Q32: Area -A | R32: S.S Bin no.06 | T32: UP/FY24/DC/00120 | U32: 23/07/2024 | V32: 23/07/2024 | W32: Siemens ltd | X32: Gurgaon | Y32: Mr.Arvind Pandey | Z32: 385142158 | AA32: GatiKWE | AB32: 6K
A33: Project 6K | B33: 29 | C33: 45486 | D33: CLW/Chittaranjan | E33: WB/FY24/DC/00081 | F33: 45450 | G33: 323733028 | H33: CLW | I33: - | J33: 109447743 | K33: 803201 | L33: LION Erweiterungsmodul,8 Wechslerkanaele 803201 | M33: Nos | N33: 1 | O33: 1 | P33: =N33-O33 -> 0 | Q33: Area -A | R33: S.S Bin no.06 | T33: UP/FY24/DC/00120 | U33: 23/07/2024 | V33: 23/07/2024 | W33: Siemens ltd | X33: Gurgaon | Y33: Mr.Arvind Pandey | Z33: 385142158 | AA33: GatiKWE | AB33: 6K | AG33: Faulty
A34: Project 6K | B34: 30 | C34: 45486 | D34: CLW/Chittaranjan | E34: WB/FY24/DC/00081 | F34: 45450 | G34: 323733028 | H34: CLW | I34: - | J34: 109447740 | K34: 803001 | L34: LION-Busskoppler-MVB-LUE 803001 | M34: Nos | N34: 2 | O34: 2 | P34: =N34-O34 -> 0 | Q34: Area -A | R34: S.S Bin no.06 | T34: UP/FY24/DC/00120 | U34: 23/07/2024 | V34: 23/07/2024 | W34: Siemens ltd | X34: Gurgaon | Y34: Mr.Arvind Pandey | Z34: 385142158 | AA34: GatiKWE | AB34: 6K
A35: Project 6K | B35: 31 | C35: 45486 | D35: CLW/Chittaranjan | E35: WB/FY24/DC/00081 | F35: 45450 | G35: 323733028 | H35: CLW | I35: - | J35: 111381215 | K35: BRIO R114 | L35: MODULE BRIO R114 MAKE LEROY-AUTOMATION | M35: Nos | N35: 1 | O35: 1 | P35: =N35-O35 -> 0 | Q35: Area -A | R35: S.S Bin no.06 | T35: UP/FY24/DC/00120 | U35: 23/07/2024 | V35: 23/07/2024 | W35: Siemens ltd | X35: Gurgaon | Y35: Mr.Arvind Pandey | Z35: 385142158 | AA35: GatiKWE | AB35: 6K
A36: Project 6K | B36: 32 | C36: 45499 | D36: Vadodara | E36: GJ/FY24/DC/002209 | F36: 45493 | G36: 51691952141 Blue Dart | H36: Vadodara | I36: - | J36: 109563338 | K36: 857-409 (60498872) | L36: Isolation amplifier; Current and voltage 857-409 | M36: Nos | N36: 2 | P36: =N36-O36 -> 2 | Q36: Area -A | R36: S.S Bin no.06 | AG36: Faulty
A37: Project 6K | B37: 33 | C37: 45499 | D37: Vadodara | E37: GJ/FY24/DC/002209 | F37: 45493 | G37: 51691952141 Blue Dart | H37: Vadodara | I37: - | J37: 113694314 | K37: DB 6200 AG | L37: Bipolar Isolation amplifier DB 6200 AG Drago make | M37: Nos | N37: 1 | P37: =N37-O37 -> 1 | Q37: Area -A | R37: S.S Bin no.06 | AG37: Faulty
A38: Project 6K | B38: 34 | C38: 45598 | D38: Vadodara | E38: GJ/FY24/DC/03973 | F38: 45589 | G38: 51517141885 Blue Dart | H38: Vadodara | I38: - | J38: 113837420 | K38: 4414N | L38: Electric Fan (4414 N EBM past) | M38: Nos | N38: 3 | O38: 3 | P38: =N38-O38 -> 0 | Q38: Area -A | R38: S.S Bin no.06 | S38: Faulty Material | T38: UP/FY24/DC/00245 | U38: 45616 | V38: 45616 | W38: RS Components & Control India Ltd | X38: Noaida | Y38: Mr .Arka Dey | Z38: 385199534 | AA38: GatiKWE | AB38: 6K | AE38: Dispatch for Replace ment
A39: Project 6K | B39: 35 | C39: 45629 | D39: Katni | E39: MOS/WR/NKJ/AQ/51 | F39: 45608 | H39: katni | I39: - | J39: 113837420 | K39: 4414N | L39: Electric Fan (4414 N EBM past) | M39: Nos | N39: 6 | O39: 6 | P39: =N39-O39 -> 0 | Q39: Area -A | R39: S.S Bin no.06 | S39: Faulty Material | T39: UP/FY24/DC/00245 | U39: 45616 | V39: 45616 | W39: RS Components & Control India Ltd | X39: Noaida | Y39: Mr .Arka Dey | Z39: 385199534 | AA39: GatiKWE | AB39: 6K | AE39: Dispatch for Replace ment
A40: Project 6K | B40: 36 | C40: 45629 | D40: Katni | E40: MOS/WR/NKJ/AQ/51 | F40: 45608 | H40: katni | I40: - | J40: 109611234 | K40: 3742612236 | L40: ACTIVE SPEED SENSORS SUITABLE FOR IGBT LOCOS [3-PHASE LOCOS] DSD 1616.73 QHW - F267S 3742612236 | M40: Nos | N40: 4 | P40: =N40-O40 -> 4 | Q40: Area -A | R40: S.S Bin no.06 | S40: Faulty Material | AG40: Faulty
A41: Project 6K | B41: 37 | C41: 45629 | D41: Katni | E41: MOS/WR/NKJ/AQ/51 | F41: 45608 | H41: katni | I41: - | J41: 107146625 | K41: 4318N | L41: Churning Fan-Model No- 4318N/2N | M41: Nos | N41: 1 | O41: 1 | P41: =N41-O41 -> 0 | Q41: Area -A | R41: S.S Bin no.06 | S41: Faulty Material | T41: UP/FY24/DC/00245 | U41: 45616 | V41: 45616 | W41: RS Components & Control India Ltd | X41: Noaida | Y41: Mr .Arka Dey | Z41: 385199534 | AA41: GatiKWE | AB41: 6K | AE41: Dispatch for Replace ment
A42: Project 6K | B42: 38 | C42: 45636 | D42: Gurgoan | E42: HR/FY24/DC/00188 | F42: 45632 | G42: 58917996406 Blue Dart | H42: Gurgoan | I42: - | J42: 107146625 | K42: 4318N/2N | L42: Ebm-Papst Churning Fan-Model No- 4318N/2N | M42: Nos | N42: 7 | P42: =N42-O42 -> 7 | Q42: Area -A | R42: S.S Bin no.06 | S42: Faulty Material | AG42: Faulty
A43: Project 6K | B43: 39 | C43: 45636 | D43: Gurgoan | E43: HR/FY24/DC/00188 | F43: 45632 | G43: 58917996406 Blue Dart | H43: Gurgoan | I43: - | J43: 109563338 | K43: 857-409 (60498872) | L43: Isolation amplifier; Current and voltage 857-409 | M43: Nos | N43: 7 | P43: =N43-O43 -> 7 | Q43: Area -A | R43: S.S Bin no.06 | S43: Faulty Material | AG43: Faulty
A44: Project 6K | B44: 40 | C44: 45636 | D44: Gurgoan | E44: HR/FY24/DC/00188 | F44: 45632 | G44: 58917996406 Blue Dart | H44: Gurgoan | I44: - | J44: 113837420 | K44: 4414N | L44: Electric Fan (4414 N EBM past) | M44: Nos | N44: 1 | P44: =N44-O44 -> 1 | Q44: Area -A | R44: S.S Bin no.06 | S44: Faulty Material | AG44: Faulty
A45: Project 6K | B45: 41 | C45: 45636 | D45: Gurgoan | E45: HR/FY24/DC/00188 | F45: 45632 | G45: 58917996406 Blue Dart | H45: Gurgoan | I45: - | J45: 113694314 | K45: DB 6200 AG | L45: Bipolar Isolation amplifier DB 6200 AG Drago make | M45: Nos | N45: 2 | P45: =N45-O45 -> 2 | Q45: Area -A | R45: S.S Bin no.06 | S45: Faulty Material | AG45: Faulty
A46: Project 6K | B46: 42 | C46: 45636 | D46: Gurgoan | E46: HR/FY24/DC/00188 | F46: 45632 | G46: 58917996406 Blue Dart | H46: Gurgoan | I46: - | J46: 101999218 | L46: Dipalay SITET | M46: Nos | N46: 1 | P46: =N46-O46 -> 1 | Q46: Area -A | R46: S.S Bin no.06 | S46: Faulty Material | AG46: Faulty
A47: Project 6K | B47: 43 | C47: 45636 | D47: Gurgoan | E47: HR/FY24/DC/00188 | F47: 45632 | G47: 58917996406 Blue Dart | H47: Gurgoan | I47: - | K47: 857-402 | L47: 857-402 Isolation amplifier | M47: Nos | N47: 4 | P47: =N47-O47 -> 4 | Q47: Area -A | R47: S.S Bin no.06 | S47: Faulty Material | AG47: Faulty
A48: Project 6K | B48: 44 | C48: 45636 | D48: Gurgoan | E48: HR/FY24/DC/00188 | F48: 45632 | G48: 58917996406 Blue Dart | H48: Gurgoan | I48: - | J48: 109447742 | K48: 803102 | L48: 803102 LION-DI16-72V-110V-LUE LION I/O MODULE DIGITAL OUTPUTS | M48: Nos | N48: 45 | P48: =N48-O48 -> 45 | Q48: Area -A | R48: S.S Bin no.06 | S48: Faulty Material | AG48: Faulty
A49: Project 6K | B49: 45 | C49: 45636 | D49: Gurgoan | E49: HR/FY24/DC/00188 | F49: 45632 | G49: 58917996406 Blue Dart | H49: Gurgoan | I49: - | J49: 109447744 | K49: 803203 | L49: Lion DO Card Relay | M49: Nos | N49: 55 | P49: =N49-O49 -> 55 | Q49: Area -A | R49: S.S Bin no.06 | S49: Faulty Material | AG49: Faulty
A50: Project 6K | B50: 46 | C50: 45636 | D50: Gurgoan | E50: HR/FY24/DC/00188 | F50: 45632 | G50: 58917996406 Blue Dart | H50: Gurgoan | I50: - | J50: 109447743 | K50: 803201 | L50: Lion RO Card Relay | M50: Nos | N50: 1 | P50: =N50-O50 -> 1 | Q50: Area -A | R50: S.S Bin no.06 | S50: Faulty Material | AG50: Faulty
A51: Project 6K | B51: 47 | C51: 45636 | D51: Gurgoan | E51: HR/FY24/DC/00188 | F51: 45632 | G51: 58917996406 Blue Dart | H51: Gurgoan | I51: - | J51: 109447745 | K51: 803301 | L51: LION AI 4-U | M51: Nos | N51: 1 | P51: =N51-O51 -> 1 | Q51: Area -A | R51: S.S Bin no.06 | S51: Faulty Material | AG51: Faulty
A52: Project 6K | B52: 48 | C52: 45636 | D52: Gurgoan | E52: HR/FY24/DC/00188 | F52: 45632 | G52: 58917996406 Blue Dart | H52: Gurgoan | I52: - | J52: 109447737 | K52: 800103 | L52: LOIN-PS-24-110V POWER SUPPLY | M52: Nos | N52: 1 | P52: =N52-O52 -> 1 | Q52: Area -A | R52: S.S Bin no.06 | S52: Faulty Material | AG52: Faulty
A53: Project 6K | B53: 49 | C53: 45636 | D53: Gurgoan | E53: HR/FY24/DC/00188 | F53: 45632 | G53: 58917996406 Blue Dart | H53: Gurgoan | I53: - | K53: TV | L53: TV | M53: Nos | N53: 1 | P53: =N53-O53 -> 1 | Q53: Area -A | R53: S.S Bin no.06 | S53: Faulty Material | AG53: Damage
A54: Project 6K | C54: 45696 | D54: Katni | E54: MOS/WR/NKJ/AQ/52 | F54: 45688 | G54: 51600118382 Blue Dart | H54: Katni | J54: 107146625 | K54: 4318N | L54: Churning Fan-Model No- 4318N/2N | M54: Nos | N54: 1 | P54: =N54-O54 -> 1 | Q54: Area -A | R54: S.S Bin no.06 | AG54: Faulty
A55: Project 6K | C55: 45696 | D55: Katni | E55: MOS/WR/NKJ/AQ/52 | F55: 45688 | G55: 51600118382 Blue Dart | H55: Katni | J55: 113837420 | K55: 4414N | L55: Electric Fan (4414 N EBM past) | M55: Nos | N55: 1 | P55: =N55-O55 -> 1 | Q55: Area -A | R55: S.S Bin no.06 | AG55: Faulty
A56: Project 6K | C56: 45696 | D56: Katni | E56: MOS/WR/NKJ/AQ/52 | F56: 45688 | G56: 51600118382 Blue Dart | H56: Katni | J56: 109611234 | K56: 3742612236 | L56: ACTIVE SPEED SENSORS SUITABLE FOR IGBT LOCOS [3-PHASE LOCOS] DSD 1616.73 QHW - F267S 3742612236 | M56: Nos | N56: 2 | P56: =N56-O56 -> 2 | Q56: Area -A | R56: S.S Bin no.06 | AG56: Faulty
A57: Project 6K | C57: 45708 | E57: WB/FY24/DC/00221 | F57: 45701 | G57: 152491761 Gati | H57: CLW | I57: Return from CLW | J57: 100742433 | L57: Battery Charger Module | M57: Nos | N57: 1 | P57: =N57-O57 -> 1 | Q57: RACK -23 | R57: Box No. 786 | S57: Healthy
A58: Project 6K | C58: 45708 | E58: WB/FY24/DC/00221 | F58: 45701 | G58: 152491761 Gati | H58: CLW | I58: Return from CLW | L58: M10x14 Allen Bolt | M58: Nos | N58: 90 | P58: =N58-O58 -> 90 | Q58: AREA-O | R58: W.Box NO.788 | S58: Healthy
A59: Project 6K | C59: 45708 | E59: WB/FY24/DC/00221 | F59: 45701 | G59: 152491761 Gati | H59: CLW | I59: Return from CLW | J59: 107156657 | K59: 107156657 | L59: M10x40 Hex Bolt | M59: Nos | N59: 32 | P59: =N59-O59 -> 32 | Q59: AREA-O | R59: W.Box NO.788 | S59: Healthy
A60: Project 6K | C60: 45708 | E60: WB/FY24/DC/00221 | F60: 45701 | G60: 152491761 Gati | H60: CLW | I60: Return from CLW | J60: 107156629 | K60: 107156629 | L60: M10x50 Hex Bolt | M60: Nos | N60: 127 | P60: =N60-O60 -> 127 | Q60: AREA-O | R60: W.Box NO.788 | S60: Healthy
A61: Project 6K | C61: 45708 | E61: WB/FY24/DC/00221 | F61: 45701 | G61: 152491761 Gati | H61: CLW | I61: Return from CLW | J61: 107186267 | K61: 107186267 | L61: Spring Washer M10 | M61: Nos | N61: 160 | P61: =N61-O61 -> 160 | Q61: AREA-O | R61: W.Box NO.788 | S61: Healthy
A62: Project 6K | C62: 45708 | E62: WB/FY24/DC/00221 | F62: 45701 | G62: 152491761 Gati | H62: CLW | I62: Return from CLW | J62: 108214979 | K62: 108214979 | L62: HEX NUT M10 SS 304 | M62: Nos | N62: 160 | P62: =N62-O62 -> 160 | Q62: AREA-O | R62: W.Box NO.788 | S62: Healthy
A63: Project 6K | C63: 45708 | E63: WB/FY24/DC/00221 | F63: 45701 | G63: 152491761 Gati | H63: CLW | I63: Return from CLW | J63: 107184793 | K63: 107184793 | L63: PLAIN WASHER M4 V4D 9044 | M63: Nos | N63: 160 | P63: =N63-O63 -> 160 | Q63: AREA-O | R63: W.Box NO.788 | S63: Healthy
A64: Project 6K | C64: 45708 | E64: WB/FY24/DC/00221 | F64: 45701 | G64: 152491761 Gati | H64: CLW | I64: Return from CLW | L64: Hex Nut M24 | M64: Nos | N64: 48 | P64: =N64-O64 -> 48 | Q64: AREA-O | R64: W.Box NO.788 | S64: Healthy
A65: Project 6K | C65: 45708 | E65: WB/FY24/DC/00221 | F65: 45701 | G65: 152491761 Gati | H65: CLW | I65: Return from CLW | L65: Aux Duct Plate | M65: Nos | N65: 2 | P65: =N65-O65 -> 2 | Q65: AREA-O | R65: LOOSE NO.787(1 to2 ) | S65: Healthy
A66: Project 6K | C66: 45708 | E66: WB/FY24/DC/00221 | F66: 45701 | G66: 152491761 Gati | H66: CLW | I66: Return from CLW | L66: Aluminium Plate | M66: Nos | N66: 1 | P66: =N66-O66 -> 1 | Q66: AREA-O | R66: W.Box NO.788 | S66: Healthy
A67: Project 6K | C67: 45708 | E67: WB/FY24/DC/00221 | F67: 45701 | G67: 152491761 Gati | H67: CLW | I67: Return from CLW | L67: Indicator Guide For Silicagel | M67: Nos | N67: 1 | P67: =N67-O67 -> 1 | Q67: AREA-O | R67: W.Box NO.788 | S67: Healthy
A68: Project 6K | C68: 45708 | E68: WB/FY24/DC/00221 | F68: 45701 | G68: 152491761 Gati | H68: CLW | I68: Return from CLW | K68: B32373A4257J080 | L68: Capacitor 250UF+_5% | M68: Nos | N68: 1 | P68: =N68-O68 -> 1 | Q68: AREA-O | R68: W.Box NO.788 | S68: Healthy
A69: Project 6K | C69: 45708 | E69: WB/FY24/DC/00221 | F69: 45701 | G69: 152491761 Gati | H69: CLW | I69: Return from CLW | L69: Power Cable Clit | M69: Nos | N69: 78 | P69: =N69-O69 -> 78 | Q69: AREA-O | R69: W.Box NO.788 | S69: Healthy
A70: Project 6K | C70: 45708 | E70: WB/FY24/DC/00221 | F70: 45701 | G70: 152491761 Gati | H70: CLW | I70: Return from CLW | L70: Batter charger Fuse 100A or^1000V | M70: Nos | N70: 2 | P70: =N70-O70 -> 2 | Q70: AREA-O | R70: W.Box NO.788 | S70: Healthy
A71: Project 6K | C71: 45708 | E71: WB/FY24/DC/00221 | F71: 45701 | G71: 152491761 Gati | H71: CLW | I71: Return from CLW | J71: 110408292 | K71: M6X16 | L71: Allen cap M6 X 16 Fixing Bolt for sensor plate | M71: Nos | N71: 144 | P71: =N71-O71 -> 144 | Q71: AREA-O | R71: W.Box NO.788 | S71: Healthy
A72: Project 6K | C72: 45708 | E72: WB/FY24/DC/00221 | F72: 45701 | G72: 152491761 Gati | H72: CLW | I72: Return from CLW | J72: 109492179 | K72: 12568935 | L72: Ethernet Cable RAILCAT CAT 5e 4 X 22AWG XMS RADOX TRACTION CABLE | M72: MTR | N72: 120 | P72: =N72-O72 -> 120 | Q72: AREA-O | R72: W.Box NO.788 | S72: Healthy
A73: Project 6K | C73: 45708 | E73: WB/FY24/DC/00221 | F73: 45701 | G73: 152491761 Gati | H73: CLW | I73: Return from CLW | J73: 112139784 | K73: TCP-V0 20MM | L73: Expendo TCP-V0 20MM | M73: MTR | N73: 152 | P73: =N73-O73 -> 152 | Q73: AREA-O | R73: W.Box NO.788 | S73: Healthy
A74: Project 6K | C74: 45708 | E74: WB/FY24/DC/00221 | F74: 45701 | G74: 152491761 Gati | H74: CLW | I74: Return from CLW | J74: 111400054 | K74: MS3474W12-3P-SQSC | L74: AMPHENOL PART NO:- MS3474W12-3P-SQSC-00022983 | M74: Nos | N74: 30 | P74: =N74-O74 -> 30 | Q74: AREA-O | R74: W.Box NO.788 | S74: Healthy
A75: Project 6K | C75: 45708 | E75: WB/FY24/DC/00221 | F75: 45701 | G75: 152491761 Gati | H75: CLW | I75: Return from CLW | J75: 111400055 | K75: MS3474W14-5P-SQSC | L75: AMPHENOL PART NO:- MS3474W14-5P-SQSC 01268739 | M75: Nos | N75: 30 | P75: =N75-O75 -> 30 | Q75: AREA-O | R75: W.Box NO.788 | S75: Healthy
A76: Project 6K | C76: 45708 | E76: WB/FY24/DC/00221 | F76: 45701 | G76: 152491761 Gati | H76: CLW | I76: Return from CLW | L76: Tie Belt | M76: Nos | N76: 7 | P76: =N76-O76 -> 7 | Q76: AREA-O | R76: W.Box NO.788 | S76: Healthy
A77: Project 6K | C77: 45708 | E77: WB/FY24/DC/00221 | F77: 45701 | G77: 152491761 Gati | H77: CLW | I77: Return from CLW | J77: 109447742 | K77: 803102 | L77: LION DE 16XDC72V/110V (DI MODULE ) | M77: Nos | N77: 2 | P77: =N77-O77 -> 2 | Q77: AREA-O | R77: W.Box NO.788 | S77: Healthy
A78: Project 6K | C78: 45708 | E78: WB/FY24/DC/00221 | F78: 45701 | G78: 152491761 Gati | H78: CLW | I78: Return from CLW | J78: 10947744 | K78: 803203 | L78: LION DA 8XDC24V/110V 803203 | M78: Nos | N78: 4 | P78: =N78-O78 -> 4 | Q78: AREA-O | R78: W.Box NO.788 | S78: Healthy
A79: Project 6K | C79: 45708 | E79: WB/FY24/DC/00221 | F79: 45701 | G79: 152491761 Gati | H79: CLW | I79: Return from CLW | J79: 102464571 | K79: 3RV2011-1GA10 | L79: 3RV2011-1GA10 \CIRCUIT-BREAKER SCREW CO ( MPCV 6000 HP) | M79: Nos | N79: 1 | P79: =N79-O79 -> 1 | Q79: AREA-O | R79: W.Box NO.788 | S79: Healthy
A80: Project 6K | C80: 45708 | E80: WB/FY24/DC/00221 | F80: 45701 | G80: 152491761 Gati | H80: CLW | I80: Return from CLW | J80: 110408290 | K80: CLW/ES/3/SK-2/0153_REV_4 | L80: SENSOR PLATE SS 3MM 114 X 114MM | M80: Nos | N80: 17 | P80: =N80-O80 -> 17 | Q80: AREA-O | R80: W.Box NO.788 | S80: Healthy
A81: Project 6K | C81: 45708 | E81: WB/FY24/DC/00221 | F81: 45701 | G81: 152491761 Gati | H81: CLW | I81: Return from CLW | J81: 107016274 | K81: 3SU1062-2DF10-0AA0 | L81: \ Selector switch, O-I ACC _ Switch | M81: Nos | N81: 1 | P81: =N81-O81 -> 1 | Q81: AREA-O | R81: W.Box NO.788 | S81: Healthy
A82: Project 6K | C82: 45708 | E82: WB/FY24/DC/00221 | F82: 45701 | G82: 152491761 Gati | H82: CLW | I82: Return from CLW | L82: USB 2.0 Allied Connectors | M82: Nos | N82: 8 | O82: 1 | P82: =N82-O82 -> 7 | Q82: AREA-O | R82: W.Box NO.788 | S82: Healthy | T82: UP/FY24/DC/00367 | U82: 45741 | V82: 45741 | W82: Siemens Ltd | X82: Bangalore | Y82: Mr.Arka Dey | Z82: 270390293 | AA82: GatiKWE | AE82: Returanable basis
A83: Project 6K | C83: 45708 | E83: WB/FY24/DC/00221 | F83: 45701 | G83: 152491761 Gati | H83: CLW | I83: Return from CLW | L83: VMT-16-1" BSP-2L-2F-PG9-160 | M83: Nos | N83: 1 | P83: =N83-O83 -> 1 | Q83: AREA-O | R83: W.Box NO.788 | S83: Healthy
A84: Project 6K | C84: 45708 | E84: WB/FY24/DC/00221 | F84: 45701 | G84: 152491761 Gati | H84: CLW | I84: Return from CLW | L84: AUX Output insulator | M84: Nos | N84: 3 | P84: =N84-O84 -> 3 | Q84: AREA-O | R84: W.Box NO.788 | S84: Healthy
